Workbook

Sheet Start Here
A1: NOVADRIVE | CLEAN RESEARCH DATA PACK
A2: Purpose-built for feeding the useful evidence and analysis into an AI dashboard builder. No duplicate dashboard, outreach tracker, or redundant summary sheets.
A3: Field | B3: Description
A4: Purpose | B4: Compact research data pack for AI/dashboard creation. Includes only core source data, derived risk assessments, event handling, and alternate supplier fitment research.
A5: How to use | B5: Use the source evidence and network relationship sheets as the traceable foundation. Use risk score sheets for prioritization. Use alternate fitment separately from supplier risk.
A6: Core deliverables represented | B6: Supplier network mapping; supplier risk scorecard; event-based risk alerts; alternate supplier assessment with public evidence; management action context embedded in component risk and alert sheets.
A7: Source data | B7: The case workbook is synthetic case data. Relationship Evidence contains evidence IDs, dates, source families, detail, record status, and locators. Public candidate evidence is in Alternate Supplier Assessment.
A8: Relationship status | B8: Confirmed = supported by relationship evidence. Inferred = reasonable but not fully established. Unresolved hypothesis = do not treat as a confirmed network link. Excluded / mismatch = do not use as supplier exposure. Excluded / mismatch items are listed in 'Excluded & Mismatches'.
A9: Allocation caveat | B9: Supplier allocations are planning/contracted allocations from case evidence, not necessarily realized purchase shares or actual deliveries.
A10: Event caveat | B10: EV-001 and EV-002 are the same flood-watch signal; count once. A flood watch does not establish damage or shutdown. EV-003 reports Meridian financing pressure while production continues. EV-004 and EV-009 are entity mismatches. EV-005 is stale. EV-007 is administrative HQ relocation. EV-010 route exposure to Estuary is unconfirmed.
A11: Risk vs fitment | B11: Supplier risk score measures vulnerability/exposure. Alternate fitment score estimates plausible capability match based on public evidence. They are different assessments and must not be combined as if they measured the same thing.
A12: Alternate candidate limitation | B12: All alternate candidates are initial public-source screens only. Scores do not establish exact interchangeability, available capacity, pricing, qualification, approval, or actual supplier willingness.
A13: Excluded operational trackers | B13: Contact logs, sample status, quotation trackers, qualification gate checklists and duplicate dashboard sheets are intentionally excluded because no actual supplier outreach/qualification has occurred and these are not required for the research deliverable.
A14: Data cut-off | B14: Event dates and source dates are those in the supplied case data and public-source research captured in the working assessment. Verify live public evidence before final external use.
... A17: Open items for the team | B17: 1) Original supplier-level weights remain undocumented; headline scores unchanged. 2) Access dates for the 14 original alternate-supplier rows are not recorded: fill the yellow cells after re-checking each URL. 3) Concentration score for M10/M20 (80) not changed despite common ownership: review. 4) PolarSwitch (DOC-078) has no public evidence. 5) Tier-2 alternates are screens; qualification runs through the Tier-1 supplier.

Sheet Business & Components
A1: BUSINESS CONTEXT
A2: Product ID | B2: Product Name | C2: Annual Revenue (USD m) | D2: Weekly Units | E2: Primary Manufacturing Footprint | F2: Management Context
A3: P1 | B3: DriveCore industrial inverter | C3: 624 | D3: 2000 | E3: Harbor Works (60%); Plateau Works (40%) | F3: Use revenue and product footprint as business-criticality context; no supplier spend is provided.
A4: P2 | B4: ChargeBridge charging power unit | C4: 520 | D4: 1000 | E4: Harbor Works (30%); Coastal Works (70%) | F4: Use revenue and product footprint as business-criticality context; no supplier spend is provided.
A5: P3 | B5: StoreLink storage control cabinet | C5: 416 | D5: 800 | E5: Plateau Works (100%) | F5: Use revenue and product footprint as business-criticality context; no supplier spend is provided.
A8: COMPONENT CONTEXT
A9: Component ID | B9: Component Name | C9: Key application | D9: Indicative supplier Qualification Lead Time (Weeks) | E9: Key Criteria for Alternate Supplier Search
A10: M10 | B10: Standard power assembly | C10: Industrial inverter power assembly; IGBT/SiC-capable module integration | D10: 16 | E10: 1. Products Using This Component: P1, P3 2. Application / Use Case: Industrial drives / power conversion 3. Supplier Screening Criteria: Search for manufacturers with comparable power-module assembly capability; technical qualification remains required.
A11: M20 | B11: High-voltage power assembly | C11: High-voltage power assembly for charging power conversion; IGBT/SiC-capable | D11: 16 | E11: 1. Products Using This Component: P2 2. Application / Use Case: EV / industrial charging power conversion 3. Supplier Screening Criteria: Assess voltage/current class, thermal design, quality systems and production scale before treating any candidate as a substitute.
A12: C10 | B12: Control board | C12: Industrial control PCB/PCBA with embedded microcontroller and power-control interfaces | D12: 12 | E12: 1. Products Using This Component: P1, P2, P3 2. Application / Use Case: Industrial electronics / power control 3. Supplier Screening Criteria: Look for design-and-manufacture capability, industrial quality systems, controller ecosystem and production footprint.
A13: C20 | B13: DC-link capacitor | C13: High-energy DC-link film capacitor for power-electronics applications | D13: 8 | E13: 1. Products Using This Component: P1, P2 2. Application / Use Case: Inverters / power conversion 3. Supplier Screening Criteria: Fit depends on electrical, thermal, lifetime and packaging requirements; public similarity is only an initial screen.
A14: H10 | B14: Protective housing | C14: Machined/fabricated aluminum enclosure for industrial power electronics | D14: 4 | E14: 1. Products Using This Component: P1 2. Application / Use Case: Industrial electronics enclosure 3. Supplier Screening Criteria: Assess material, tolerance, environmental protection, tooling and regional manufacturing capability.
A15: H20 | B15: Cooling assembly | C15: Thermal-management / liquid-cooling assembly for power electronics | D15: 6 | E15: 1. Products Using This Component: P2, P3 2. Application / Use Case: Power electronics thermal management 3. Supplier Screening Criteria: Assess thermal performance, materials, leak/reliability testing, scale and geographic suitability.
A16: B10 | B16: Battery-monitoring board | C16: Battery-monitoring/control PCBA with sensing and embedded electronics | D16: 12 | E16: 1. Products Using This Component: P3 2. Application / Use Case: Battery systems / energy storage electronics 3. Supplier Screening Criteria: Assess battery-control experience, electronics manufacturing capability, safety/quality systems and production scale.

Sheet Supplier Universe & Risk
A1: SUPPLIER UNIVERSE + INDICATORS + RISK
A2: One row per entity from the case Supplier Universe, enriched with raw business indicators and available supplier risk score/category. Blank score means no mapped supplier score was assigned.
A3: Entity ID | B3: Legal Name | C3: Entity Type | D3: Public Capability | E3: Registered Market | F3: Registered Zone | G3: Primary Facility ID | H3: Primary Facility Name | I3: Facility Zone | J3: Facility Role | K3: Facility Capability | L3: Other Known Site / Note | M3: Current Ratio | N3: Net Debt / EBITDA | O3: Shipment Timeliness - 3M Avg (%) | P3: Timeliness Change - Jan To Latest (pp) | Q3: Assurance Gap Index | R3: Physical Hazard Index | S3: Logistics Friction Index | T3: Infrastructure Index | U3: Supplier Risk Score | V3: Supplier Risk Category | W3: Risk Data Completeness | X3: Relationship Confidence | Y3: Risk Notes
A4: ORG-247 | B4: Aster Power Assemblies Ltd. | C4: Manufacturer | D4: Power assemblies M10/M20 | E4: Norland | F4: Z02 | G4: SITE-018 | H4: Aster Works | I4: Z02 | J4: Manufacturing | K4: Power assemblies M10/M20 | M4: 2.13 | N4: 2 | O4: 80.9 | P4: 2.3 | Q4: 24 | R4: 27 | S4: 30 | T4: 24 | U4: 51.8 | V4: MEDIUM | W4: High | X4: Confirmed
A5: ORG-725 | B5: Boreal Power Systems Ltd. | C5: Manufacturer | D5: Power assemblies M10/M20 | E5: Westmere | F5: Z05 | G5: SITE-025 | H5: Boreal Works | I5: Z05 | J5: Manufacturing | K5: Power assemblies M10/M20 | M5: 1.54 | N5: 3 | O5: 83.1 | P5: 2.2 | Q5: 33 | R5: 31 | S5: 23 | T5: 19 | U5: 52.7 | V5: MEDIUM | W5: High | X5: Confirmed
A6: ORG-119 | B6: Cobalt Control Electronics Ltd. | C6: Manufacturer | D6: Control board C10 | E6: Estara | F6: Z04 | G6: SITE-032 | H6: Cobalt Works | I6: Z04 | J6: Manufacturing | K6: Control board C10 | M6: 2.34 | N6: 4 | O6: 83.3 | P6: -2.3 | Q6: 42 | R6: 58 | S6: 62 | T6: 52 | U6: 69 | V6: HIGH | W6: High | X6: Confirmed
A7: ORG-268 | B7: CommonSpan Holdings Ltd. | C7: Holding company | D7: Holding company | E7: Westmere | F7: Z05 | G7: SITE-221 | H7: CommonSpan Works | I7: Z05 | J7: Office or service | K7: Holding company | M7: 2.04 | N7: 1 | O7: 87.6 | P7: -1.1 | Q7: 45 | R7: 31 | S7: 23 | T7: 19
A8: ORG-922 | B8: Delta Capacitor Works Ltd. | C8: Manufacturer | D8: Capacitor C20 | E8: Westmere | F8: Z03 | G8: SITE-039 | H8: Delta Works | I8: Z03 | J8: Manufacturing | K8: Capacitor C20 | M8: 1.82 | N8: 1.67 | O8: 86.9 | P8: 2.2 | Q8: 51 | R8: 19 | S8: 26 | T8: 25 | U8: 49.7 | V8: MEDIUM | W8: High | X8: Confirmed
A9: ORG-857 | B9: Delta Consumer Plastics Ltd. | C9: Manufacturer | D9: Consumer packaging | E9: Norland | F9: Z02 | G9: SITE-249 | H9: Delta Works | I9: Z02 | J9: Manufacturing | K9: Consumer packaging | O9: 83.7 | P9: 2.2 | R9: 27 | S9: 30 | T9: 24
A10: ORG-786 | B10: Estuary Thermal Systems Ltd. | C10: Manufacturer | D10: Cooling assembly H20 | E10: Talora | F10: Z06 | G10: SITE-046 | H10: Estuary Works | I10: Z06 | J10: Manufacturing | K10: Cooling assembly H20 | M10: 2.53 | N10: 2.67 | O10: 89.7 | P10: 1.8 | Q10: 60 | R10: 67 | S10: 59 | T10: 54 | U10: 48.4 | V10: MEDIUM | W10: High | X10: Confirmed
A11: ORG-287 | B11: ForgeLine Enclosures Ltd. | C11: Manufacturer | D11: Housing H10 | E11: Norland | F11: Z02 | G11: SITE-053 | H11: ForgeLine Works | I11: Z02 | J11: Manufacturing | K11: Housing H10 | M11: 1.94 | N11: 3.67 | O11: 89.8 | P11: -0.3 | Q11: 69 | R11: 27 | S11: 30 | T11: 24 | U11: 45.4 | V11: MEDIUM | W11: High | X11: Confirmed
A12: ORG-103 | B12: Grove Battery Controls Ltd. | C12: Manufacturer | D12: Battery monitor B10 | E12: Estara | F12: Z04 | G12: SITE-060 | H12: Grove Works | I12: Z04 | J12: Manufacturing | K12: Battery monitor B10 | M12: 1.51 | N12: 1.33 | O12: 78.8 | P12: -0.9 | Q12: 18 | R12: 58 | S12: 62 | T12: 52 | U12: 44.6 | V12: LOW | W12: High | X12: Confirmed
A13: ORG-328 | B13: Harbor Freight Services Ltd. | C13: Logistics or intermediary | D13: Freight forwarding | E13: Norland | F13: Z07 | G13: SITE-242 | H13: Harbor Works | I13: Z07 | J13: Office or service | K13: Freight forwarding | M13: 1.68 | N13: 4 | O13: 80.6 | P13: 1.4 | Q13: 72 | R13: 34 | S13: 36 | T13: 30
A14: ORG-176 | B14: HarborSense Electronics Ltd. | C14: Manufacturer | D14: Battery monitor B10 | E14: Westmere | F14: Z05 | G14: SITE-067 | H14: HarborSense Works | I14: Z05 | J14: Manufacturing | K14: Battery monitor B10 | M14: 2.24 | N14: 2.33 | O14: 81.9 | P14: -0.9 | Q14: 27 | R14: 31 | S14: 23 | T14: 19 | U14: 32.5 | V14: LOW | W14: High | X14: Confirmed
A15: ORG-309 | B15: Ion Peak Trading Ltd. | C15: Logistics or intermediary | D15: Trade brokerage | E15: Norland | F15: Z07 | G15: SITE-207 | H15: Ion Works | I15: Z07 | J15: Office or service | K15: Trade brokerage | O15: 82.7 | P15: 2.8 | R15: 34 | S15: 36 | T15: 30
A16: ORG-439 | B16: IonPeak Semiconductor Ltd. | C16: Manufacturer | D16: Power semiconductor dies | E16: Estara | F16: Z01 | G16: SITE-074 | H16: IonPeak Works | I16: Z01 | J16: Manufacturing | K16: Power semiconductor dies | L16: SITE-900 - IonPeak Western Development Center (Research and pilot line, Z05) | M16: 1.8 | N16: 2.4 | O16: 85.2 | P16: -8.8 | Q16: 36 | R16: 82 | S16: 76 | T16: 71 | U16: 79 | V16: CRITICAL | W16: High | X16: Confirmed
A17: ORG-445 | B17: Jade Circuits Holdings Ltd. | C17: Holding company | D17: Holding company | E17: Norland | F17: Z07 | G17: SITE-214 | H17: Jade Works | I17: Z07 | J17: Office or service | K17: Holding company | M17: 2.46 | N17: 3.33 | O17: 85.4 | P17: -0.6 | Q17: 36 | R17: 34 | S17: 36 | T17: 30
A18: ORG-453 | B18: Jade Printed Circuits Ltd. | C18: Manufacturer | D18: Printed circuit substrates | E18: Estara | F18: Z01 | G18: SITE-081 | H18: Jade Works | I18: Z01 | J18: Manufacturing | K18: Printed circuit substrates | L18: SITE-901 - Jade Corporate Office (Headquarters only, Z07) | M18: 1.55 | N18: 3.1 | O18: 86.6 | P18: -6.4 | Q18: 45 | R18: 82 | S18: 76 | T18: 71 | U18: 79 | V18: CRITICAL | W18: High | X18: Confirmed
A19: ORG-728 | B19: Kestrel Microdevices Ltd. | C19: Manufacturer | D19: Microcontrollers | E19: Westmere | F19: Z05 | G19: SITE-088 | H19: Kestrel Works | I19: Z05 | J19: Manufacturing | K19: Microcontrollers | M19: 1.86 | N19: 2 | O19: 87.3 | P19: 1.6 | Q19: 54 | R19: 31 | S19: 23 | T19: 19 | U19: 57.2 | V19: MEDIUM | W19: High | X19: Confirmed
A20: ORG-942 | B20: Lumen Magnetics Ltd. | C20: Manufacturer | D20: Magnetic cores | E20: Estara | F20: Z04 | G20: SITE-095 | H20: Lumen Works | I20: Z04 | J20: Manufacturing | K20: Magnetic cores | M20: 1.37 | N20: 3 | O20: 89.5 | P20: -0.6 | Q20: 63 | R20: 58 | S20: 62 | T20: 52 | U20: 69.4 | V20: HIGH | W20: High | X20: Confirmed
A21: ORG-210 | B21: Meridian Dielectrics Ltd. | C21: Manufacturer | D21: Dielectric film | E21: Westmere | F21: Z03 | G21: SITE-102 | H21: Meridian Works | I21: Z03 | J21: Manufacturing | K21: Dielectric film | M21: 0.62 | N21: 7.2 | O21: 76.4 | P21: -17.6 | Q21: 72 | R21: 19 | S21: 26 | T21: 25 | U21: 83.7 | V21: CRITICAL | W21: High | X21: Confirmed
A22: ORG-849 | B22: Nacre Foils Ltd. | C22: Manufacturer | D22: Aluminum foil | E22: Talora | F22: Z06 | G22: SITE-109 | H22: Nacre Works | I22: Z06 | J22: Manufacturing | K22: Aluminum foil | M22: 1.54 | N22: 1.67 | O22: 79.3 | P22: -3.5 | Q22: 21 | R22: 67 | S22: 59 | T22: 54 | U22: 61.7 | V22: HIGH | W22: High | X22: Confirmed
A23: ORG-708 | B23: Orion Ceramics Ltd. | C23: Manufacturer | D23: Ceramic substrates | E23: Estara | F23: Z01 | G23: SITE-116 | H23: Orion Works | I23: Z01 | J23: Manufacturing | K23: Ceramic substrates | M23: 2.29 | N23: 2.67 | O23: 82.2 | P23: 0.7 | Q23: 30 | R23: 82 | S23: 76 | T23: 71 | U23: 68.8 | V23: HIGH | W23: High | X23: Confirmed
A24: ORG-274 | B24: Pine Thermal Metals Ltd. | C24: Manufacturer | D24: Thermal metals | E24: Talora | F24: Z06 | G24: SITE-123 | H24: Pine Works | I24: Z06 | J24: Manufacturing | K24: Thermal metals | M24: 1.79 | N24: 3.67 | O24: 85.6 | P24: 0.8 | Q24: 39 | R24: 67 | S24: 59 | T24: 54 | U24: 57.3 | V24: MEDIUM | W24: High | X24: Confirmed
A25: ORG-329 | B25: Quartz Alloy Ltd. | C25: Manufacturer | D25: Aluminum alloy | E25: Norland | F25: Z02 | G25: SITE-130 | H25: Quartz Works | I25: Z02 | J25: Manufacturing | K25: Aluminum alloy | M25: 2.43 | N25: 1.33 | O25: 84.6 | P25: -2.1 | Q25: 48 | R25: 27 | S25: 30 | T25: 24 | U25: 39.3 | V25: LOW | W25: High | X25: Confirmed
A26: ORG-469 | B26: Rill Connectors Ltd. | C26: Manufacturer | D26: Connectors | E26: Estara | F26: Z04 | G26: SITE-137 | H26: Rill Works | I26: Z04 | J26: Manufacturing | K26: Connectors | M26: 2.04 | N26: 2.33 | O26: 89.3 | P26: 0.3 | Q26: 57 | R26: 58 | S26: 62 | T26: 52 | U26: 60.9 | V26: HIGH | W26: High | X26: Confirmed
A27: ORG-320 | B27: Solace Optics Ltd. | C27: Manufacturer | D27: Isolation optics | E27: Talora | F27: Z08 | G27: SITE-144 | H27: Solace Works | I27: Z08 | J27: Manufacturing | K27: Isolation optics | O27: 91.7 | P27: -0.3 | R27: 39 | S27: 47 | T27: 41
A28: ORG-455 | B28: Umber Silicon Carbide Ltd. | C28: Manufacturer | D28: Silicon-carbide wafers | E28: Estara | F28: Z01 | G28: SITE-158 | H28: Umber Works | I28: Z01 | J28: Manufacturing | K28: Silicon-carbide wafers | O28: 80.5 | P28: -2.2 | R28: 82 | S28: 76 | T28: 71 | U28: 74.4 | V28: HIGH | W28: Medium | X28: Confirmed | Y28: Tier-3 link via IonPeak (confirmed). Financial and assurance indicators are blank in the case data, so this score is provisional; missing information is not treated as low risk (see 'Supplier Score Build').
A29: ORG-736 | B29: Verdant Process Gases Ltd. | C29: Manufacturer | D29: Process gases | E29: Estara | F29: Z01 | G29: SITE-165 | H29: Verdant Works | I29: Z01 | J29: Manufacturing | K29: Process gases | O29: 81.9 | P29: -0.9 | R29: 82 | S29: 76 | T29: 71 | U29: 73.4 | V29: HIGH | W29: Medium | X29: Inference | Y29: Tier-3 link to IonPeak is an inference, not a confirmed relationship. Financial and assurance indicators are blank in the case data, so this score is provisional; missing information is not treated as low risk (see 'Supplier Score Build').
A30: ORG-873 | B30: Warden Copper Foil Ltd. | C30: Manufacturer | D30: Copper foil | E30: Talora | F30: Z06 | G30: SITE-172 | H30: Warden Works | I30: Z06 | J30: Manufacturing | K30: Copper foil | O30: 87.4 | P30: 1.8 | R30: 67 | S30: 59 | T30: 54 | U30: 64.9 | V30: HIGH | W30: Medium | X30: Confirmed | Y30: Tier-3 link via Jade. Financial and assurance indicators are blank in the case data, so this score is provisional; missing information is not treated as low risk (see 'Supplier Score Build').
A31: ORG-179 | B31: Xenon Resin Ltd. | C31: Manufacturer | D31: Resin | E31: Estara | F31: Z04 | G31: SITE-179 | H31: Xenon Works | I31: Z04 | J31: Manufacturing | K31: Resin | O31: 87.3 | P31: 1.8 | R31: 58 | S31: 62 | T31: 52 | U31: 64.4 | V31: HIGH | W31: Medium | X31: Confirmed | Y31: Tier-3 link via Jade. Financial and assurance indicators are blank in the case data, so this score is provisional; missing information is not treated as low risk (see 'Supplier Score Build').
A32: ORG-520 | B32: Yarrow Specialty Minerals Ltd. | C32: Manufacturer | D32: Specialty minerals | E32: Talora | F32: Z08 | G32: SITE-186 | H32: Yarrow Works | I32: Z08 | J32: Manufacturing | K32: Specialty minerals | O32: 90.1 | P32: -1.2 | R32: 39 | S32: 47 | T32: 41 | U32: 63.5 | V32: HIGH | W32: Medium | X32: Confirmed | Y32: Tier-3 link via Orion. Financial and assurance indicators are blank in the case data, so this score is provisional; missing information is not treated as low risk (see 'Supplier Score Build').
A33: ORG-659 | B33: Zenith Polymer Ltd. | C33: Manufacturer | D33: Polymer | E33: Westmere | F33: Z03 | G33: SITE-193 | H33: Zenith Works | I33: Z03 | J33: Manufacturing | K33: Polymer | O33: 90.9 | P33: -0.9 | R33: 19 | S33: 26 | T33: 25 | U33: 51.6 | V33: MEDIUM | W33: Medium | X33: Confirmed | Y33: Tier-3 link via Meridian. Financial and assurance indicators are blank in the case data, so this score is provisional; missing information is not treated as low risk (see 'Supplier Score Build').

Sheet Supplier Score Build
A1: SUPPLIER SCORE BUILD (explainable cross-check of the headline supplier risk score)
A2: The original supplier-level weights are not documented in the source files and could not be reproduced from the eight raw indicators. This sheet rebuilds an INTRINSIC supplier-condition score from those indicators with stated, editable weights (blue cells). It does not replace the headline score; it shows what the indicators alone explain, and the gap is the part driven by other factors (likely criticality, concentration, network dependence - confirm with the original scorer). Missing pillars default to a prudent 60, never to low risk.
A4: Parameter | B4: Value | C4: Note
A5: Weight - Financial pillar | B5: 0.3 | C5: Current ratio and Net Debt/EBITDA
A6: Weight - Operational pillar | B6: 0.25 | C6: Shipment timeliness level and Jan-to-latest change
A7: Weight - Location pillar | B7: 0.3 | C7: Average of Physical Hazard, Logistics Friction and Infrastructure indices (already 0-100)
A8: Weight - Assurance pillar | B8: 0.15 | C8: Assurance Gap Index (0-100)
A9: Weights check (must equal 1) | B9: =SUM(B5:B8) -> 1 | C9: Formula
A10: Current ratio - best (0 risk) | B10: 2.5 | C10: Assumption; at or above this scores 0
A11: Current ratio - worst (100 risk) | B11: 0.8 | C11: Assumption; at or below this scores 100
A12: Net Debt/EBITDA - best (0 risk) | B12: 1 | C12: Assumption
A13: Net Debt/EBITDA - worst (100 risk) | B13: 7 | C13: Assumption
A14: Timeliness % - best (0 risk) | B14: 92 | C14: Assumption
A15: Timeliness % - worst (100 risk) | B15: 76 | C15: Assumption
A16: Timeliness change pp - best (0 risk) | B16: 3 | C16: Assumption
A17: Timeliness change pp - worst (100 risk) | B17: -18 | C17: Assumption
A18: Missing-pillar default score | B18: 60 | C18: Missing information is NOT treated as low risk; a blank pillar takes this value and is flagged
A20: Legend: blue = editable assumption; green = pulled from another sheet; black = formula. Weights and anchors are analyst assumptions for transparency, not values from the case.
A22: Entity ID | B22: Legal Name | C22: Current Ratio | D22: Net Debt / EBITDA | E22: Timeliness 3M Avg (%) | F22: Timeliness Change (pp) | G22: Assurance Gap Index | H22: Physical Hazard Index | I22: Logistics Friction Index | J22: Infrastructure Index | K22: Financial pillar (0-100) | L22: Operational pillar (0-100) | M22: Location pillar (0-100) | N22: Assurance pillar (0-100) | O22: Missing pillars (count) | P22: Data completeness | Q22: Intrinsic indicator score | R22: Headline supplier risk score | S22: Headline risk band | T22: Gap: headline minus intrinsic | U22: Rank - headline | V22: Rank - intrinsic
A23: ORG-247 | B23: Aster Power Assemblies Ltd. | C23: =IF(INDEX('Supplier Universe & Risk'!$M$4:$M$33,MATCH($A23,'Supplier Universe & Risk'!$A$4:$A$33,0))="","",INDEX('Supplier Universe & Risk'!$M$4:$M$33,MATCH($A23,'Supplier Universe & Risk'!$A$4:$A$33,0))) -> 2.13 | D23: =IF(INDEX('Supplier Universe & Risk'!$N$4:$N$33,MATCH($A23,'Supplier Universe & Risk'!$A$4:$A$33,0))="","",INDEX('Supplier Universe & Risk'!$N$4:$N$33,MATCH($A23,'Supplier Universe & Risk'!$A$4:$A$33,0))) -> 2 | E23: =IF(INDEX('Supplier Universe & Risk'!$O$4:$O$33,MATCH($A23,'Supplier Universe & Risk'!$A$4:$A$33,0))="","",INDEX('Supplier Universe & Risk'!$O$4:$O$33,MATCH($A23,'Supplier Universe & Risk'!$A$4:$A$33,0))) -> 80.9 | F23: =IF(INDEX('Supplier Universe & Risk'!$P$4:$P$33,MATCH($A23,'Supplier Universe & Risk'!$A$4:$A$33,0))="","",INDEX('Supplier Universe & Risk'!$P$4:$P$33,MATCH($A23,'Supplier Universe & Risk'!$A$4:$A$33,0))) -> 2.3 | G23: =IF(INDEX('Supplier Universe & Risk'!$Q$4:$Q$33,MATCH($A23,'Supplier Universe & Risk'!$A$4:$A$33,0))="","",INDEX('Supplier Universe & Risk'!$Q$4:$Q$33,MATCH($A23,'Supplier Universe & Risk'!$A$4:$A$33,0))) -> 24 | H23: =IF(INDEX('Supplier Universe & Risk'!$R$4:$R$33,MATCH($A23,'Supplier Universe & Risk'!$A$4:$A$33,0))="","",INDEX('Supplier Universe & Risk'!$R$4:$R$33,MATCH($A23,'Supplier Universe & Risk'!$A$4:$A$33,0))) -> 27 | I23: =IF(INDEX('Supplier Universe & Risk'!$S$4:$S$33,MATCH($A23,'Supplier Universe & Risk'!$A$4:$A$33,0))="","",INDEX('Supplier Universe & Risk'!$S$4:$S$33,MATCH($A23,'Supplier Universe & Risk'!$A$4:$A$33,0))) -> 30 | J23: =IF(INDEX('Supplier Universe & Risk'!$T$4:$T$33,MATCH($A23,'Supplier Universe & Risk'!$A$4:$A$33,0))="","",INDEX('Supplier Universe & Risk'!$T$4:$T$33,MATCH($A23,'Supplier Universe & Risk'!$A$4:$A$33,0))) -> 24 | K23: =IF(OR(C23="",D23=""),"",(MAX(0,MIN(1,($B$10-C23)/($B$10-$B$11)))*100+MAX(0,MIN(1,(D23-$B$12)/($B$13-$B$12)))*100)/2) -> 19.215686 | L23: =IF(OR(E23="",F23=""),"",(MAX(0,MIN(1,($B$14-E23)/($B$14-$B$15)))*100+MAX(0,MIN(1,($B$16-F23)/($B$16-$B$17)))*100)/2) -> 36.354167 | M23: =IF(COUNT(H23:J23)=3,AVERAGE(H23:J23),"") -> 27 | N23: =IF(G23="","",G23) -> 24 | O23: =(K23="")+(L23="")+(M23="")+(N23="") -> 0 | P23: =IF(O23=0,"Complete",IF(O23=1,"Partial - 1 pillar defaulted","Limited - "&O23&" pillars defaulted")) -> Complete | Q23: =$B$5*IF(K23="",$B$18,K23)+$B$6*IF(L23="",$B$18,L23)+$B$7*IF(M23="",$B$18,M23)+$B$8*IF(N23="",$B$18,N23) -> 26.553248 | R23: =IF(INDEX('Supplier Universe & Risk'!$U$4:$U$33,MATCH($A23,'Supplier Universe & Risk'!$A$4:$A$33,0))="","",INDEX('Supplier Universe & Risk'!$U$4:$U$33,MATCH($A23,'Supplier Universe & Risk'!$A$4:$A$33,0))) -> 51.8 | S23: =IF(INDEX('Supplier Universe & Risk'!$V$4:$V$33,MATCH($A23,'Supplier Universe & Risk'!$A$4:$A$33,0))="","",INDEX('Supplier Universe & Risk'!$V$4:$V$33,MATCH($A23,'Supplier Universe & Risk'!$A$4:$A$33,0))) -> MEDIUM | T23: =R23-Q23 -> 25.246752 | U23: =RANK(R23,$R$23:$R$46) -> 17 | V23: =RANK(Q23,$Q$23:$Q$46) -> 23
A24: ORG-725 | B24: Boreal Power Systems Ltd. | C24: =IF(INDEX('Supplier Universe & Risk'!$M$4:$M$33,MATCH($A24,'Supplier Universe & Risk'!$A$4:$A$33,0))="","",INDEX('Supplier Universe & Risk'!$M$4:$M$33,MATCH($A24,'Supplier Universe & Risk'!$A$4:$A$33,0))) -> 1.54 | D24: =IF(INDEX('Supplier Universe & Risk'!$N$4:$N$33,MATCH($A24,'Supplier Universe & Risk'!$A$4:$A$33,0))="","",INDEX('Supplier Universe & Risk'!$N$4:$N$33,MATCH($A24,'Supplier Universe & Risk'!$A$4:$A$33,0))) -> 3 | E24: =IF(INDEX('Supplier Universe & Risk'!$O$4:$O$33,MATCH($A24,'Supplier Universe & Risk'!$A$4:$A$33,0))="","",INDEX('Supplier Universe & Risk'!$O$4:$O$33,MATCH($A24,'Supplier Universe & Risk'!$A$4:$A$33,0))) -> 83.1 | F24: =IF(INDEX('Supplier Universe & Risk'!$P$4:$P$33,MATCH($A24,'Supplier Universe & Risk'!$A$4:$A$33,0))="","",INDEX('Supplier Universe & Risk'!$P$4:$P$33,MATCH($A24,'Supplier Universe & Risk'!$A$4:$A$33,0))) -> 2.2 | G24: =IF(INDEX('Supplier Universe & Risk'!$Q$4:$Q$33,MATCH($A24,'Supplier Universe & Risk'!$A$4:$A$33,0))="","",INDEX('Supplier Universe & Risk'!$Q$4:$Q$33,MATCH($A24,'Supplier Universe & Risk'!$A$4:$A$33,0))) -> 33 | H24: =IF(INDEX('Supplier Universe & Risk'!$R$4:$R$33,MATCH($A24,'Supplier Universe & Risk'!$A$4:$A$33,0))="","",INDEX('Supplier Universe & Risk'!$R$4:$R$33,MATCH($A24,'Supplier Universe & Risk'!$A$4:$A$33,0))) -> 31 | I24: =IF(INDEX('Supplier Universe & Risk'!$S$4:$S$33,MATCH($A24,'Supplier Universe & Risk'!$A$4:$A$33,0))="","",INDEX('Supplier Universe & Risk'!$S$4:$S$33,MATCH($A24,'Supplier Universe & Risk'!$A$4:$A$33,0))) -> 23 | J24: =IF(INDEX('Supplier Universe & Risk'!$T$4:$T$33,MATCH($A24,'Supplier Universe & Risk'!$A$4:$A$33,0))="","",INDEX('Supplier Universe & Risk'!$T$4:$T$33,MATCH($A24,'Supplier Universe & Risk'!$A$4:$A$33,0))) -> 19 | K24: =IF(OR(C24="",D24=""),"",(MAX(0,MIN(1,($B$10-C24)/($B$10-$B$11)))*100+MAX(0,MIN(1,(D24-$B$12)/($B$13-$B$12)))*100)/2) -> 44.901961 | L24: =IF(OR(E24="",F24=""),"",(MAX(0,MIN(1,($B$14-E24)/($B$14-$B$15)))*100+MAX(0,MIN(1,($B$16-F24)/($B$16-$B$17)))*100)/2) -> 29.717262 | M24: =IF(COUNT(H24:J24)=3,AVERAGE(H24:J24),"") -> 24.333333 | N24: =IF(G24="","",G24) -> 33 | O24: =(K24="")+(L24="")+(M24="")+(N24="") -> 0 | P24: =IF(O24=0,"Complete",IF(O24=1,"Partial - 1 pillar defaulted","Limited - "&O24&" pillars defaulted")) -> Complete | Q24: =$B$5*IF(K24="",$B$18,K24)+$B$6*IF(L24="",$B$18,L24)+$B$7*IF(M24="",$B$18,M24)+$B$8*IF(N24="",$B$18,N24) -> 33.149904 | R24: =IF(INDEX('Supplier Universe & Risk'!$U$4:$U$33,MATCH($A24,'Supplier Universe & Risk'!$A$4:$A$33,0))="","",INDEX('Supplier Universe & Risk'!$U$4:$U$33,MATCH($A24,'Supplier Universe & Risk'!$A$4:$A$33,0))) -> 52.7 | S24: =IF(INDEX('Supplier Universe & Risk'!$V$4:$V$33,MATCH($A24,'Supplier Universe & Risk'!$A$4:$A$33,0))="","",INDEX('Supplier Universe & Risk'!$V$4:$V$33,MATCH($A24,'Supplier Universe & Risk'!$A$4:$A$33,0))) -> MEDIUM | T24: =R24-Q24 -> 19.550096 | U24: =RANK(R24,$R$23:$R$46) -> 16 | V24: =RANK(Q24,$Q$23:$Q$46) -> 19
A25: ORG-119 | B25: Cobalt Control Electronics Ltd. | C25: =IF(INDEX('Supplier Universe & Risk'!$M$4:$M$33,MATCH($A25,'Supplier Universe & Risk'!$A$4:$A$33,0))="","",INDEX('Supplier Universe & Risk'!$M$4:$M$33,MATCH($A25,'Supplier Universe & Risk'!$A$4:$A$33,0))) -> 2.34 | D25: =IF(INDEX('Supplier Universe & Risk'!$N$4:$N$33,MATCH($A25,'Supplier Universe & Risk'!$A$4:$A$33,0))="","",INDEX('Supplier Universe & Risk'!$N$4:$N$33,MATCH($A25,'Supplier Universe & Risk'!$A$4:$A$33,0))) -> 4 | E25: =IF(INDEX('Supplier Universe & Risk'!$O$4:$O$33,MATCH($A25,'Supplier Universe & Risk'!$A$4:$A$33,0))="","",INDEX('Supplier Universe & Risk'!$O$4:$O$33,MATCH($A25,'Supplier Universe & Risk'!$A$4:$A$33,0))) -> 83.3 | F25: =IF(INDEX('Supplier Universe & Risk'!$P$4:$P$33,MATCH($A25,'Supplier Universe & Risk'!$A$4:$A$33,0))="","",INDEX('Supplier Universe & Risk'!$P$4:$P$33,MATCH($A25,'Supplier Universe & Risk'!$A$4:$A$33,0))) -> -2.3 | G25: =IF(INDEX('Supplier Universe & Risk'!$Q$4:$Q$33,MATCH($A25,'Supplier Universe & Risk'!$A$4:$A$33,0))="","",INDEX('Supplier Universe & Risk'!$Q$4:$Q$33,MATCH($A25,'Supplier Universe & Risk'!$A$4:$A$33,0))) -> 42 | H25: =IF(INDEX('Supplier Universe & Risk'!$R$4:$R$33,MATCH($A25,'Supplier Universe & Risk'!$A$4:$A$33,0))="","",INDEX('Supplier Universe & Risk'!$R$4:$R$33,MATCH($A25,'Supplier Universe & Risk'!$A$4:$A$33,0))) -> 58 | I25: =IF(INDEX('Supplier Universe & Risk'!$S$4:$S$33,MATCH($A25,'Supplier Universe & Risk'!$A$4:$A$33,0))="","",INDEX('Supplier Universe & Risk'!$S$4:$S$33,MATCH($A25,'Supplier Universe & Risk'!$A$4:$A$33,0))) -> 62 | J25: =IF(INDEX('Supplier Universe & Risk'!$T$4:$T$33,MATCH($A25,'Supplier Universe & Risk'!$A$4:$A$33,0))="","",INDEX('Supplier Universe & Risk'!$T$4:$T$33,MATCH($A25,'Supplier Universe & Risk'!$A$4:$A$33,0))) -> 52 | K25: =IF(OR(C25="",D25=""),"",(MAX(0,MIN(1,($B$10-C25)/($B$10-$B$11)))*100+MAX(0,MIN(1,(D25-$B$12)/($B$13-$B$12)))*100)/2) -> 29.705882 | L25: =IF(OR(E25="",F25=""),"",(MAX(0,MIN(1,($B$14-E25)/($B$14-$B$15)))*100+MAX(0,MIN(1,($B$16-F25)/($B$16-$B$17)))*100)/2) -> 39.806548 | M25: =IF(COUNT(H25:J25)=3,AVERAGE(H25:J25),"") -> 57.333333 | N25: =IF(G25="","",G25) -> 42 | O25: =(K25="")+(L25="")+(M25="")+(N25="") -> 0 | P25: =IF(O25=0,"Complete",IF(O25=1,"Partial - 1 pillar defaulted","Limited - "&O25&" pillars defaulted")) -> Complete | Q25: =$B$5*IF(K25="",$B$18,K25)+$B$6*IF(L25="",$B$18,L25)+$B$7*IF(M25="",$B$18,M25)+$B$8*IF(N25="",$B$18,N25) -> 42.363402 | R25: =IF(INDEX('Supplier Universe & Risk'!$U$4:$U$33,MATCH($A25,'Supplier Universe & Risk'!$A$4:$A$33,0))="","",INDEX('Supplier Universe & Risk'!$U$4:$U$33,MATCH($A25,'Supplier Universe & Risk'!$A$4:$A$33,0))) -> 69 | S25: =IF(INDEX('Supplier Universe & Risk'!$V$4:$V$33,MATCH($A25,'Supplier Universe & Risk'!$A$4:$A$33,0))="","",INDEX('Supplier Universe & Risk'!$V$4:$V$33,MATCH($A25,'Supplier Universe & Risk'!$A$4:$A$33,0))) -> HIGH | T25: =R25-Q25 -> 26.636598 | U25: =RANK(R25,$R$23:$R$46) -> 7 | V25: =RANK(Q25,$Q$23:$Q$46) -> 13
A26: ORG-922 | B26: Delta Capacitor Works Ltd. | C26: =IF(INDEX('Supplier Universe & Risk'!$M$4:$M$33,MATCH($A26,'Supplier Universe & Risk'!$A$4:$A$33,0))="","",INDEX('Supplier Universe & Risk'!$M$4:$M$33,MATCH($A26,'Supplier Universe & Risk'!$A$4:$A$33,0))) -> 1.82 | D26: =IF(INDEX('Supplier Universe & Risk'!$N$4:$N$33,MATCH($A26,'Supplier Universe & Risk'!$A$4:$A$33,0))="","",INDEX('Supplier Universe & Risk'!$N$4:$N$33,MATCH($A26,'Supplier Universe & Risk'!$A$4:$A$33,0))) -> 1.67 | E26: =IF(INDEX('Supplier Universe & Risk'!$O$4:$O$33,MATCH($A26,'Supplier Universe & Risk'!$A$4:$A$33,0))="","",INDEX('Supplier Universe & Risk'!$O$4:$O$33,MATCH($A26,'Supplier Universe & Risk'!$A$4:$A$33,0))) -> 86.9 | F26: =IF(INDEX('Supplier Universe & Risk'!$P$4:$P$33,MATCH($A26,'Supplier Universe & Risk'!$A$4:$A$33,0))="","",INDEX('Supplier Universe & Risk'!$P$4:$P$33,MATCH($A26,'Supplier Universe & Risk'!$A$4:$A$33,0))) -> 2.2 | G26: =IF(INDEX('Supplier Universe & Risk'!$Q$4:$Q$33,MATCH($A26,'Supplier Universe & Risk'!$A$4:$A$33,0))="","",INDEX('Supplier Universe & Risk'!$Q$4:$Q$33,MATCH($A26,'Supplier Universe & Risk'!$A$4:$A$33,0))) -> 51 | H26: =IF(INDEX('Supplier Universe & Risk'!$R$4:$R$33,MATCH($A26,'Supplier Universe & Risk'!$A$4:$A$33,0))="","",INDEX('Supplier Universe & Risk'!$R$4:$R$33,MATCH($A26,'Supplier Universe & Risk'!$A$4:$A$33,0))) -> 19 | I26: =IF(INDEX('Supplier Universe & Risk'!$S$4:$S$33,MATCH($A26,'Supplier Universe & Risk'!$A$4:$A$33,0))="","",INDEX('Supplier Universe & Risk'!$S$4:$S$33,MATCH($A26,'Supplier Universe & Risk'!$A$4:$A$33,0))) -> 26 | J26: =IF(INDEX('Supplier Universe & Risk'!$T$4:$T$33,MATCH($A26,'Supplier Universe & Risk'!$A$4:$A$33,0))="","",INDEX('Supplier Universe & Risk'!$T$4:$T$33,MATCH($A26,'Supplier Universe & Risk'!$A$4:$A$33,0))) -> 25 | K26: =IF(OR(C26="",D26=""),"",(MAX(0,MIN(1,($B$10-C26)/($B$10-$B$11)))*100+MAX(0,MIN(1,(D26-$B$12)/($B$13-$B$12)))*100)/2) -> 25.583333 | L26: =IF(OR(E26="",F26=""),"",(MAX(0,MIN(1,($B$14-E26)/($B$14-$B$15)))*100+MAX(0,MIN(1,($B$16-F26)/($B$16-$B$17)))*100)/2) -> 17.842262 | M26: =IF(COUNT(H26:J26)=3,AVERAGE(H26:J26),"") -> 23.333333 | N26: =IF(G26="","",G26) -> 51 | O26: =(K26="")+(L26="")+(M26="")+(N26="") -> 0 | P26: =IF(O26=0,"Complete",IF(O26=1,"Partial - 1 pillar defaulted","Limited - "&O26&" pillars defaulted")) -> Complete | Q26: =$B$5*IF(K26="",$B$18,K26)+$B$6*IF(L26="",$B$18,L26)+$B$7*IF(M26="",$B$18,M26)+$B$8*IF(N26="",$B$18,N26) -> 26.785565 | R26: =IF(INDEX('Supplier Universe & Risk'!$U$4:$U$33,MATCH($A26,'Supplier Universe & Risk'!$A$4:$A$33,0))="","",INDEX('Supplier Universe & Risk'!$U$4:$U$33,MATCH($A26,'Supplier Universe & Risk'!$A$4:$A$33,0))) -> 49.7 | S26: =IF(INDEX('Supplier Universe & Risk'!$V$4:$V$33,MATCH($A26,'Supplier Universe & Risk'!$A$4:$A$33,0))="","",INDEX('Supplier Universe & Risk'!$V$4:$V$33,MATCH($A26,'Supplier Universe & Risk'!$A$4:$A$33,0))) -> MEDIUM | T26: =R26-Q26 -> 22.914435 | U26: =RANK(R26,$R$23:$R$46) -> 19 | V26: =RANK(Q26,$Q$23:$Q$46) -> 22
A27: ORG-786 | B27: Estuary Thermal Systems Ltd. | C27: =IF(INDEX('Supplier Universe & Risk'!$M$4:$M$33,MATCH($A27,'Supplier Universe & Risk'!$A$4:$A$33,0))="","",INDEX('Supplier Universe & Risk'!$M$4:$M$33,MATCH($A27,'Supplier Universe & Risk'!$A$4:$A$33,0))) -> 2.53 | D27: =IF(INDEX('Supplier Universe & Risk'!$N$4:$N$33,MATCH($A27,'Supplier Universe & Risk'!$A$4:$A$33,0))="","",INDEX('Supplier Universe & Risk'!$N$4:$N$33,MATCH($A27,'Supplier Universe & Risk'!$A$4:$A$33,0))) -> 2.67 | E27: =IF(INDEX('Supplier Universe & Risk'!$O$4:$O$33,MATCH($A27,'Supplier Universe & Risk'!$A$4:$A$33,0))="","",INDEX('Supplier Universe & Risk'!$O$4:$O$33,MATCH($A27,'Supplier Universe & Risk'!$A$4:$A$33,0))) -> 89.7 | F27: =IF(INDEX('Supplier Universe & Risk'!$P$4:$P$33,MATCH($A27,'Supplier Universe & Risk'!$A$4:$A$33,0))="","",INDEX('Supplier Universe & Risk'!$P$4:$P$33,MATCH($A27,'Supplier Universe & Risk'!$A$4:$A$33,0))) -> 1.8 | G27: =IF(INDEX('Supplier Universe & Risk'!$Q$4:$Q$33,MATCH($A27,'Supplier Universe & Risk'!$A$4:$A$33,0))="","",INDEX('Supplier Universe & Risk'!$Q$4:$Q$33,MATCH($A27,'Supplier Universe & Risk'!$A$4:$A$33,0))) -> 60 | H27: =IF(INDEX('Supplier Universe & Risk'!$R$4:$R$33,MATCH($A27,'Supplier Universe & Risk'!$A$4:$A$33,0))="","",INDEX('Supplier Universe & Risk'!$R$4:$R$33,MATCH($A27,'Supplier Universe & Risk'!$A$4:$A$33,0))) -> 67 | I27: =IF(INDEX('Supplier Universe & Risk'!$S$4:$S$33,MATCH($A27,'Supplier Universe & Risk'!$A$4:$A$33,0))="","",INDEX('Supplier Universe & Risk'!$S$4:$S$33,MATCH($A27,'Supplier Universe & Risk'!$A$4:$A$33,0))) -> 59 | J27: =IF(INDEX('Supplier Universe & Risk'!$T$4:$T$33,MATCH($A27,'Supplier Universe & Risk'!$A$4:$A$33,0))="","",INDEX('Supplier Universe & Risk'!$T$4:$T$33,MATCH($A27,'Supplier Universe & Risk'!$A$4:$A$33,0))) -> 54 | K27: =IF(OR(C27="",D27=""),"",(MAX(0,MIN(1,($B$10-C27)/($B$10-$B$11)))*100+MAX(0,MIN(1,(D27-$B$12)/($B$13-$B$12)))*100)/2) -> 13.916667 | L27: =IF(OR(E27="",F27=""),"",(MAX(0,MIN(1,($B$14-E27)/($B$14-$B$15)))*100+MAX(0,MIN(1,($B$16-F27)/($B$16-$B$17)))*100)/2) -> 10.044643 | M27: =IF(COUNT(H27:J27)=3,AVERAGE(H27:J27),"") -> 60 | N27: =IF(G27="","",G27) -> 60 | O27: =(K27="")+(L27="")+(M27="")+(N27="") -> 0 | P27: =IF(O27=0,"Complete",IF(O27=1,"Partial - 1 pillar defaulted","Limited - "&O27&" pillars defaulted")) -> Complete | Q27: =$B$5*IF(K27="",$B$18,K27)+$B$6*IF(L27="",$B$18,L27)+$B$7*IF(M27="",$B$18,M27)+$B$8*IF(N27="",$B$18,N27) -> 33.686161 | R27: =IF(INDEX('Supplier Universe & Risk'!$U$4:$U$33,MATCH($A27,'Supplier Universe & Risk'!$A$4:$A$33,0))="","",INDEX('Supplier Universe & Risk'!$U$4:$U$33,MATCH($A27,'Supplier Universe & Risk'!$A$4:$A$33,0))) -> 48.4 | S27: =IF(INDEX('Supplier Universe & Risk'!$V$4:$V$33,MATCH($A27,'Supplier Universe & Risk'!$A$4:$A$33,0))="","",INDEX('Supplier Universe & Risk'!$V$4:$V$33,MATCH($A27,'Supplier Universe & Risk'!$A$4:$A$33,0))) -> MEDIUM | T27: =R27-Q27 -> 14.713839 | U27: =RANK(R27,$R$23:$R$46) -> 20 | V27: =RANK(Q27,$Q$23:$Q$46) -> 18
A28: ORG-287 | B28: ForgeLine Enclosures Ltd. | C28: =IF(INDEX('Supplier Universe & Risk'!$M$4:$M$33,MATCH($A28,'Supplier Universe & Risk'!$A$4:$A$33,0))="","",INDEX('Supplier Universe & Risk'!$M$4:$M$33,MATCH($A28,'Supplier Universe & Risk'!$A$4:$A$33,0))) -> 1.94 | D28: =IF(INDEX('Supplier Universe & Risk'!$N$4:$N$33,MATCH($A28,'Supplier Universe & Risk'!$A$4:$A$33,0))="","",INDEX('Supplier Universe & Risk'!$N$4:$N$33,MATCH($A28,'Supplier Universe & Risk'!$A$4:$A$33,0))) -> 3.67 | E28: =IF(INDEX('Supplier Universe & Risk'!$O$4:$O$33,MATCH($A28,'Supplier Universe & Risk'!$A$4:$A$33,0))="","",INDEX('Supplier Universe & Risk'!$O$4:$O$33,MATCH($A28,'Supplier Universe & Risk'!$A$4:$A$33,0))) -> 89.8 | F28: =IF(INDEX('Supplier Universe & Risk'!$P$4:$P$33,MATCH($A28,'Supplier Universe & Risk'!$A$4:$A$33,0))="","",INDEX('Supplier Universe & Risk'!$P$4:$P$33,MATCH($A28,'Supplier Universe & Risk'!$A$4:$A$33,0))) -> -0.3 | G28: =IF(INDEX('Supplier Universe & Risk'!$Q$4:$Q$33,MATCH($A28,'Supplier Universe & Risk'!$A$4:$A$33,0))="","",INDEX('Supplier Universe & Risk'!$Q$4:$Q$33,MATCH($A28,'Supplier Universe & Risk'!$A$4:$A$33,0))) -> 69 | H28: =IF(INDEX('Supplier Universe & Risk'!$R$4:$R$33,MATCH($A28,'Supplier Universe & Risk'!$A$4:$A$33,0))="","",INDEX('Supplier Universe & Risk'!$R$4:$R$33,MATCH($A28,'Supplier Universe & Risk'!$A$4:$A$33,0))) -> 27 | I28: =IF(INDEX('Supplier Universe & Risk'!$S$4:$S$33,MATCH($A28,'Supplier Universe & Risk'!$A$4:$A$33,0))="","",INDEX('Supplier Universe & Risk'!$S$4:$S$33,MATCH($A28,'Supplier Universe & Risk'!$A$4:$A$33,0))) -> 30 | J28: =IF(INDEX('Supplier Universe & Risk'!$T$4:$T$33,MATCH($A28,'Supplier Universe & Risk'!$A$4:$A$33,0))="","",INDEX('Supplier Universe & Risk'!$T$4:$T$33,MATCH($A28,'Supplier Universe & Risk'!$A$4:$A$33,0))) -> 24 | K28: =IF(OR(C28="",D28=""),"",(MAX(0,MIN(1,($B$10-C28)/($B$10-$B$11)))*100+MAX(0,MIN(1,(D28-$B$12)/($B$13-$B$12)))*100)/2) -> 38.720588 | L28: =IF(OR(E28="",F28=""),"",(MAX(0,MIN(1,($B$14-E28)/($B$14-$B$15)))*100+MAX(0,MIN(1,($B$16-F28)/($B$16-$B$17)))*100)/2) -> 14.732143 | M28: =IF(COUNT(H28:J28)=3,AVERAGE(H28:J28),"") -> 27 | N28: =IF(G28="","",G28) -> 69 | O28: =(K28="")+(L28="")+(M28="")+(N28="") -> 0 | P28: =IF(O28=0,"Complete",IF(O28=1,"Partial - 1 pillar defaulted","Limited - "&O28&" pillars defaulted")) -> Complete | Q28: =$B$5*IF(K28="",$B$18,K28)+$B$6*IF(L28="",$B$18,L28)+$B$7*IF(M28="",$B$18,M28)+$B$8*IF(N28="",$B$18,N28) -> 33.749212 | R28: =IF(INDEX('Supplier Universe & Risk'!$U$4:$U$33,MATCH($A28,'Supplier Universe & Risk'!$A$4:$A$33,0))="","",INDEX('Supplier Universe & Risk'!$U$4:$U$33,MATCH($A28,'Supplier Universe & Risk'!$A$4:$A$33,0))) -> 45.4 | S28: =IF(INDEX('Supplier Universe & Risk'!$V$4:$V$33,MATCH($A28,'Supplier Universe & Risk'!$A$4:$A$33,0))="","",INDEX('Supplier Universe & Risk'!$V$4:$V$33,MATCH($A28,'Supplier Universe & Risk'!$A$4:$A$33,0))) -> MEDIUM | T28: =R28-Q28 -> 11.650788 | U28: =RANK(R28,$R$23:$R$46) -> 21 | V28: =RANK(Q28,$Q$23:$Q$46) -> 17
A29: ORG-103 | B29: Grove Battery Controls Ltd. | C29: =IF(INDEX('Supplier Universe & Risk'!$M$4:$M$33,MATCH($A29,'Supplier Universe & Risk'!$A$4:$A$33,0))="","",INDEX('Supplier Universe & Risk'!$M$4:$M$33,MATCH($A29,'Supplier Universe & Risk'!$A$4:$A$33,0))) -> 1.51 | D29: =IF(INDEX('Supplier Universe & Risk'!$N$4:$N$33,MATCH($A29,'Supplier Universe & Risk'!$A$4:$A$33,0))="","",INDEX('Supplier Universe & Risk'!$N$4:$N$33,MATCH($A29,'Supplier Universe & Risk'!$A$4:$A$33,0))) -> 1.33 | E29: =IF(INDEX('Supplier Universe & Risk'!$O$4:$O$33,MATCH($A29,'Supplier Universe & Risk'!$A$4:$A$33,0))="","",INDEX('Supplier Universe & Risk'!$O$4:$O$33,MATCH($A29,'Supplier Universe & Risk'!$A$4:$A$33,0))) -> 78.8 | F29: =IF(INDEX('Supplier Universe & Risk'!$P$4:$P$33,MATCH($A29,'Supplier Universe & Risk'!$A$4:$A$33,0))="","",INDEX('Supplier Universe & Risk'!$P$4:$P$33,MATCH($A29,'Supplier Universe & Risk'!$A$4:$A$33,0))) -> -0.9 | G29: =IF(INDEX('Supplier Universe & Risk'!$Q$4:$Q$33,MATCH($A29,'Supplier Universe & Risk'!$A$4:$A$33,0))="","",INDEX('Supplier Universe & Risk'!$Q$4:$Q$33,MATCH($A29,'Supplier Universe & Risk'!$A$4:$A$33,0))) -> 18 | H29: =IF(INDEX('Supplier Universe & Risk'!$R$4:$R$33,MATCH($A29,'Supplier Universe & Risk'!$A$4:$A$33,0))="","",INDEX('Supplier Universe & Risk'!$R$4:$R$33,MATCH($A29,'Supplier Universe & Risk'!$A$4:$A$33,0))) -> 58 | I29: =IF(INDEX('Supplier Universe & Risk'!$S$4:$S$33,MATCH($A29,'Supplier Universe & Risk'!$A$4:$A$33,0))="","",INDEX('Supplier Universe & Risk'!$S$4:$S$33,MATCH($A29,'Supplier Universe & Risk'!$A$4:$A$33,0))) -> 62 | J29: =IF(INDEX('Supplier Universe & Risk'!$T$4:$T$33,MATCH($A29,'Supplier Universe & Risk'!$A$4:$A$33,0))="","",INDEX('Supplier Universe & Risk'!$T$4:$T$33,MATCH($A29,'Supplier Universe & Risk'!$A$4:$A$33,0))) -> 52 | K29: =IF(OR(C29="",D29=""),"",(MAX(0,MIN(1,($B$10-C29)/($B$10-$B$11)))*100+MAX(0,MIN(1,(D29-$B$12)/($B$13-$B$12)))*100)/2) -> 31.867647 | L29: =IF(OR(E29="",F29=""),"",(MAX(0,MIN(1,($B$14-E29)/($B$14-$B$15)))*100+MAX(0,MIN(1,($B$16-F29)/($B$16-$B$17)))*100)/2) -> 50.535714 | M29: =IF(COUNT(H29:J29)=3,AVERAGE(H29:J29),"") -> 57.333333 | N29: =IF(G29="","",G29) -> 18 | O29: =(K29="")+(L29="")+(M29="")+(N29="") -> 0 | P29: =IF(O29=0,"Complete",IF(O29=1,"Partial - 1 pillar defaulted","Limited - "&O29&" pillars defaulted")) -> Complete | Q29: =$B$5*IF(K29="",$B$18,K29)+$B$6*IF(L29="",$B$18,L29)+$B$7*IF(M29="",$B$18,M29)+$B$8*IF(N29="",$B$18,N29) -> 42.094223 | R29: =IF(INDEX('Supplier Universe & Risk'!$U$4:$U$33,MATCH($A29,'Supplier Universe & Risk'!$A$4:$A$33,0))="","",INDEX('Supplier Universe & Risk'!$U$4:$U$33,MATCH($A29,'Supplier Universe & Risk'!$A$4:$A$33,0))) -> 44.6 | S29: =IF(INDEX('Supplier Universe & Risk'!$V$4:$V$33,MATCH($A29,'Supplier Universe & Risk'!$A$4:$A$33,0))="","",INDEX('Supplier Universe & Risk'!$V$4:$V$33,MATCH($A29,'Supplier Universe & Risk'!$A$4:$A$33,0))) -> LOW | T29: =R29-Q29 -> 2.5057773 | U29: =RANK(R29,$R$23:$R$46) -> 22 | V29: =RANK(Q29,$Q$23:$Q$46) -> 14
A30: ORG-176 | B30: HarborSense Electronics Ltd. | C30: =IF(INDEX('Supplier Universe & Risk'!$M$4:$M$33,MATCH($A30,'Supplier Universe & Risk'!$A$4:$A$33,0))="","",INDEX('Supplier Universe & Risk'!$M$4:$M$33,MATCH($A30,'Supplier Universe & Risk'!$A$4:$A$33,0))) -> 2.24 | D30: =IF(INDEX('Supplier Universe & Risk'!$N$4:$N$33,MATCH($A30,'Supplier Universe & Risk'!$A$4:$A$33,0))="","",INDEX('Supplier Universe & Risk'!$N$4:$N$33,MATCH($A30,'Supplier Universe & Risk'!$A$4:$A$33,0))) -> 2.33 | E30: =IF(INDEX('Supplier Universe & Risk'!$O$4:$O$33,MATCH($A30,'Supplier Universe & Risk'!$A$4:$A$33,0))="","",INDEX('Supplier Universe & Risk'!$O$4:$O$33,MATCH($A30,'Supplier Universe & Risk'!$A$4:$A$33,0))) -> 81.9 | F30: =IF(INDEX('Supplier Universe & Risk'!$P$4:$P$33,MATCH($A30,'Supplier Universe & Risk'!$A$4:$A$33,0))="","",INDEX('Supplier Universe & Risk'!$P$4:$P$33,MATCH($A30,'Supplier Universe & Risk'!$A$4:$A$33,0))) -> -0.9 | G30: =IF(INDEX('Supplier Universe & Risk'!$Q$4:$Q$33,MATCH($A30,'Supplier Universe & Risk'!$A$4:$A$33,0))="","",INDEX('Supplier Universe & Risk'!$Q$4:$Q$33,MATCH($A30,'Supplier Universe & Risk'!$A$4:$A$33,0))) -> 27 | H30: =IF(INDEX('Supplier Universe & Risk'!$R$4:$R$33,MATCH($A30,'Supplier Universe & Risk'!$A$4:$A$33,0))="","",INDEX('Supplier Universe & Risk'!$R$4:$R$33,MATCH($A30,'Supplier Universe & Risk'!$A$4:$A$33,0))) -> 31 | I30: =IF(INDEX('Supplier Universe & Risk'!$S$4:$S$33,MATCH($A30,'Supplier Universe & Risk'!$A$4:$A$33,0))="","",INDEX('Supplier Universe & Risk'!$S$4:$S$33,MATCH($A30,'Supplier Universe & Risk'!$A$4:$A$33,0))) -> 23 | J30: =IF(INDEX('Supplier Universe & Risk'!$T$4:$T$33,MATCH($A30,'Supplier Universe & Risk'!$A$4:$A$33,0))="","",INDEX('Supplier Universe & Risk'!$T$4:$T$33,MATCH($A30,'Supplier Universe & Risk'!$A$4:$A$33,0))) -> 19 | K30: =IF(OR(C30="",D30=""),"",(MAX(0,MIN(1,($B$10-C30)/($B$10-$B$11)))*100+MAX(0,MIN(1,(D30-$B$12)/($B$13-$B$12)))*100)/2) -> 18.730392 | L30: =IF(OR(E30="",F30=""),"",(MAX(0,MIN(1,($B$14-E30)/($B$14-$B$15)))*100+MAX(0,MIN(1,($B$16-F30)/($B$16-$B$17)))*100)/2) -> 40.848214 | M30: =IF(COUNT(H30:J30)=3,AVERAGE(H30:J30),"") -> 24.333333 | N30: =IF(G30="","",G30) -> 27 | O30: =(K30="")+(L30="")+(M30="")+(N30="") -> 0 | P30: =IF(O30=0,"Complete",IF(O30=1,"Partial - 1 pillar defaulted","Limited - "&O30&" pillars defaulted")) -> Complete | Q30: =$B$5*IF(K30="",$B$18,K30)+$B$6*IF(L30="",$B$18,L30)+$B$7*IF(M30="",$B$18,M30)+$B$8*IF(N30="",$B$18,N30) -> 27.181171 | R30: =IF(INDEX('Supplier Universe & Risk'!$U$4:$U$33,MATCH($A30,'Supplier Universe & Risk'!$A$4:$A$33,0))="","",INDEX('Supplier Universe & Risk'!$U$4:$U$33,MATCH($A30,'Supplier Universe & Risk'!$A$4:$A$33,0))) -> 32.5 | S30: =IF(INDEX('Supplier Universe & Risk'!$V$4:$V$33,MATCH($A30,'Supplier Universe & Risk'!$A$4:$A$33,0))="","",INDEX('Supplier Universe & Risk'!$V$4:$V$33,MATCH($A30,'Supplier Universe & Risk'!$A$4:$A$33,0))) -> LOW | T30: =R30-Q30 -> 5.3188288 | U30: =RANK(R30,$R$23:$R$46) -> 24 | V30: =RANK(Q30,$Q$23:$Q$46) -> 21
A31: ORG-439 | B31: IonPeak Semiconductor Ltd. | C31: =IF(INDEX('Supplier Universe & Risk'!$M$4:$M$33,MATCH($A31,'Supplier Universe & Risk'!$A$4:$A$33,0))="","",INDEX('Supplier Universe & Risk'!$M$4:$M$33,MATCH($A31,'Supplier Universe & Risk'!$A$4:$A$33,0))) -> 1.8 | D31: =IF(INDEX('Supplier Universe & Risk'!$N$4:$N$33,MATCH($A31,'Supplier Universe & Risk'!$A$4:$A$33,0))="","",INDEX('Supplier Universe & Risk'!$N$4:$N$33,MATCH($A31,'Supplier Universe & Risk'!$A$4:$A$33,0))) -> 2.4 | E31: =IF(INDEX('Supplier Universe & Risk'!$O$4:$O$33,MATCH($A31,'Supplier Universe & Risk'!$A$4:$A$33,0))="","",INDEX('Supplier Universe & Risk'!$O$4:$O$33,MATCH($A31,'Supplier Universe & Risk'!$A$4:$A$33,0))) -> 85.2 | F31: =IF(INDEX('Supplier Universe & Risk'!$P$4:$P$33,MATCH($A31,'Supplier Universe & Risk'!$A$4:$A$33,0))="","",INDEX('Supplier Universe & Risk'!$P$4:$P$33,MATCH($A31,'Supplier Universe & Risk'!$A$4:$A$33,0))) -> -8.8 | G31: =IF(INDEX('Supplier Universe & Risk'!$Q$4:$Q$33,MATCH($A31,'Supplier Universe & Risk'!$A$4:$A$33,0))="","",INDEX('Supplier Universe & Risk'!$Q$4:$Q$33,MATCH($A31,'Supplier Universe & Risk'!$A$4:$A$33,0))) -> 36 | H31: =IF(INDEX('Supplier Universe & Risk'!$R$4:$R$33,MATCH($A31,'Supplier Universe & Risk'!$A$4:$A$33,0))="","",INDEX('Supplier Universe & Risk'!$R$4:$R$33,MATCH($A31,'Supplier Universe & Risk'!$A$4:$A$33,0))) -> 82 | I31: =IF(INDEX('Supplier Universe & Risk'!$S$4:$S$33,MATCH($A31,'Supplier Universe & Risk'!$A$4:$A$33,0))="","",INDEX('Supplier Universe & Risk'!$S$4:$S$33,MATCH($A31,'Supplier Universe & Risk'!$A$4:$A$33,0))) -> 76 | J31: =IF(INDEX('Supplier Universe & Risk'!$T$4:$T$33,MATCH($A31,'Supplier Universe & Risk'!$A$4:$A$33,0))="","",INDEX('Supplier Universe & Risk'!$T$4:$T$33,MATCH($A31,'Supplier Universe & Risk'!$A$4:$A$33,0))) -> 71 | K31: =IF(OR(C31="",D31=""),"",(MAX(0,MIN(1,($B$10-C31)/($B$10-$B$11)))*100+MAX(0,MIN(1,(D31-$B$12)/($B$13-$B$12)))*100)/2) -> 32.254902 | L31: =IF(OR(E31="",F31=""),"",(MAX(0,MIN(1,($B$14-E31)/($B$14-$B$15)))*100+MAX(0,MIN(1,($B$16-F31)/($B$16-$B$17)))*100)/2) -> 49.345238 | M31: =IF(COUNT(H31:J31)=3,AVERAGE(H31:J31),"") -> 76.333333 | N31: =IF(G31="","",G31) -> 36 | O31: =(K31="")+(L31="")+(M31="")+(N31="") -> 0 | P31: =IF(O31=0,"Complete",IF(O31=1,"Partial - 1 pillar defaulted","Limited - "&O31&" pillars defaulted")) -> Complete | Q31: =$B$5*IF(K31="",$B$18,K31)+$B$6*IF(L31="",$B$18,L31)+$B$7*IF(M31="",$B$18,M31)+$B$8*IF(N31="",$B$18,N31) -> 50.31278 | R31: =IF(INDEX('Supplier Universe & Risk'!$U$4:$U$33,MATCH($A31,'Supplier Universe & Risk'!$A$4:$A$33,0))="","",INDEX('Supplier Universe & Risk'!$U$4:$U$33,MATCH($A31,'Supplier Universe & Risk'!$A$4:$A$33,0))) -> 79 | S31: =IF(INDEX('Supplier Universe & Risk'!$V$4:$V$33,MATCH($A31,'Supplier Universe & Risk'!$A$4:$A$33,0))="","",INDEX('Supplier Universe & Risk'!$V$4:$V$33,MATCH($A31,'Supplier Universe & Risk'!$A$4:$A$33,0))) -> CRITICAL | T31: =R31-Q31 -> 28.68722 | U31: =RANK(R31,$R$23:$R$46) -> 2 | V31: =RANK(Q31,$Q$23:$Q$46) -> 5
A32: ORG-453 | B32: Jade Printed Circuits Ltd. | C32: =IF(INDEX('Supplier Universe & Risk'!$M$4:$M$33,MATCH($A32,'Supplier Universe & Risk'!$A$4:$A$33,0))="","",INDEX('Supplier Universe & Risk'!$M$4:$M$33,MATCH($A32,'Supplier Universe & Risk'!$A$4:$A$33,0))) -> 1.55 | D32: =IF(INDEX('Supplier Universe & Risk'!$N$4:$N$33,MATCH($A32,'Supplier Universe & Risk'!$A$4:$A$33,0))="","",INDEX('Supplier Universe & Risk'!$N$4:$N$33,MATCH($A32,'Supplier Universe & Risk'!$A$4:$A$33,0))) -> 3.1 | E32: =IF(INDEX('Supplier Universe & Risk'!$O$4:$O$33,MATCH($A32,'Supplier Universe & Risk'!$A$4:$A$33,0))="","",INDEX('Supplier Universe & Risk'!$O$4:$O$33,MATCH($A32,'Supplier Universe & Risk'!$A$4:$A$33,0))) -> 86.6 | F32: =IF(INDEX('Supplier Universe & Risk'!$P$4:$P$33,MATCH($A32,'Supplier Universe & Risk'!$A$4:$A$33,0))="","",INDEX('Supplier Universe & Risk'!$P$4:$P$33,MATCH($A32,'Supplier Universe & Risk'!$A$4:$A$33,0))) -> -6.4 | G32: =IF(INDEX('Supplier Universe & Risk'!$Q$4:$Q$33,MATCH($A32,'Supplier Universe & Risk'!$A$4:$A$33,0))="","",INDEX('Supplier Universe & Risk'!$Q$4:$Q$33,MATCH($A32,'Supplier Universe & Risk'!$A$4:$A$33,0))) -> 45 | H32: =IF(INDEX('Supplier Universe & Risk'!$R$4:$R$33,MATCH($A32,'Supplier Universe & Risk'!$A$4:$A$33,0))="","",INDEX('Supplier Universe & Risk'!$R$4:$R$33,MATCH($A32,'Supplier Universe & Risk'!$A$4:$A$33,0))) -> 82 | I32: =IF(INDEX('Supplier Universe & Risk'!$S$4:$S$33,MATCH($A32,'Supplier Universe & Risk'!$A$4:$A$33,0))="","",INDEX('Supplier Universe & Risk'!$S$4:$S$33,MATCH($A32,'Supplier Universe & Risk'!$A$4:$A$33,0))) -> 76 | J32: =IF(INDEX('Supplier Universe & Risk'!$T$4:$T$33,MATCH($A32,'Supplier Universe & Risk'!$A$4:$A$33,0))="","",INDEX('Supplier Universe & Risk'!$T$4:$T$33,MATCH($A32,'Supplier Universe & Risk'!$A$4:$A$33,0))) -> 71 | K32: =IF(OR(C32="",D32=""),"",(MAX(0,MIN(1,($B$10-C32)/($B$10-$B$11)))*100+MAX(0,MIN(1,(D32-$B$12)/($B$13-$B$12)))*100)/2) -> 45.441176 | L32: =IF(OR(E32="",F32=""),"",(MAX(0,MIN(1,($B$14-E32)/($B$14-$B$15)))*100+MAX(0,MIN(1,($B$16-F32)/($B$16-$B$17)))*100)/2) -> 39.255952 | M32: =IF(COUNT(H32:J32)=3,AVERAGE(H32:J32),"") -> 76.333333 | N32: =IF(G32="","",G32) -> 45 | O32: =(K32="")+(L32="")+(M32="")+(N32="") -> 0 | P32: =IF(O32=0,"Complete",IF(O32=1,"Partial - 1 pillar defaulted","Limited - "&O32&" pillars defaulted")) -> Complete | Q32: =$B$5*IF(K32="",$B$18,K32)+$B$6*IF(L32="",$B$18,L32)+$B$7*IF(M32="",$B$18,M32)+$B$8*IF(N32="",$B$18,N32) -> 53.096341 | R32: =IF(INDEX('Supplier Universe & Risk'!$U$4:$U$33,MATCH($A32,'Supplier Universe & Risk'!$A$4:$A$33,0))="","",INDEX('Supplier Universe & Risk'!$U$4:$U$33,MATCH($A32,'Supplier Universe & Risk'!$A$4:$A$33,0))) -> 79 | S32: =IF(INDEX('Supplier Universe & Risk'!$V$4:$V$33,MATCH($A32,'Supplier Universe & Risk'!$A$4:$A$33,0))="","",INDEX('Supplier Universe & Risk'!$V$4:$V$33,MATCH($A32,'Supplier Universe & Risk'!$A$4:$A$33,0))) -> CRITICAL | T32: =R32-Q32 -> 25.903659 | U32: =RANK(R32,$R$23:$R$46) -> 2 | V32: =RANK(Q32,$Q$23:$Q$46) -> 4
A33: ORG-728 | B33: Kestrel Microdevices Ltd. | C33: =IF(INDEX('Supplier Universe & Risk'!$M$4:$M$33,MATCH($A33,'Supplier Universe & Risk'!$A$4:$A$33,0))="","",INDEX('Supplier Universe & Risk'!$M$4:$M$33,MATCH($A33,'Supplier Universe & Risk'!$A$4:$A$33,0))) -> 1.86 | D33: =IF(INDEX('Supplier Universe & Risk'!$N$4:$N$33,MATCH($A33,'Supplier Universe & Risk'!$A$4:$A$33,0))="","",INDEX('Supplier Universe & Risk'!$N$4:$N$33,MATCH($A33,'Supplier Universe & Risk'!$A$4:$A$33,0))) -> 2 | E33: =IF(INDEX('Supplier Universe & Risk'!$O$4:$O$33,MATCH($A33,'Supplier Universe & Risk'!$A$4:$A$33,0))="","",INDEX('Supplier Universe & Risk'!$O$4:$O$33,MATCH($A33,'Supplier Universe & Risk'!$A$4:$A$33,0))) -> 87.3 | F33: =IF(INDEX('Supplier Universe & Risk'!$P$4:$P$33,MATCH($A33,'Supplier Universe & Risk'!$A$4:$A$33,0))="","",INDEX('Supplier Universe & Risk'!$P$4:$P$33,MATCH($A33,'Supplier Universe & Risk'!$A$4:$A$33,0))) -> 1.6 | G33: =IF(INDEX('Supplier Universe & Risk'!$Q$4:$Q$33,MATCH($A33,'Supplier Universe & Risk'!$A$4:$A$33,0))="","",INDEX('Supplier Universe & Risk'!$Q$4:$Q$33,MATCH($A33,'Supplier Universe & Risk'!$A$4:$A$33,0))) -> 54 | H33: =IF(INDEX('Supplier Universe & Risk'!$R$4:$R$33,MATCH($A33,'Supplier Universe & Risk'!$A$4:$A$33,0))="","",INDEX('Supplier Universe & Risk'!$R$4:$R$33,MATCH($A33,'Supplier Universe & Risk'!$A$4:$A$33,0))) -> 31 | I33: =IF(INDEX('Supplier Universe & Risk'!$S$4:$S$33,MATCH($A33,'Supplier Universe & Risk'!$A$4:$A$33,0))="","",INDEX('Supplier Universe & Risk'!$S$4:$S$33,MATCH($A33,'Supplier Universe & Risk'!$A$4:$A$33,0))) -> 23 | J33: =IF(INDEX('Supplier Universe & Risk'!$T$4:$T$33,MATCH($A33,'Supplier Universe & Risk'!$A$4:$A$33,0))="","",INDEX('Supplier Universe & Risk'!$T$4:$T$33,MATCH($A33,'Supplier Universe & Risk'!$A$4:$A$33,0))) -> 19 | K33: =IF(OR(C33="",D33=""),"",(MAX(0,MIN(1,($B$10-C33)/($B$10-$B$11)))*100+MAX(0,MIN(1,(D33-$B$12)/($B$13-$B$12)))*100)/2) -> 27.156863 | L33: =IF(OR(E33="",F33=""),"",(MAX(0,MIN(1,($B$14-E33)/($B$14-$B$15)))*100+MAX(0,MIN(1,($B$16-F33)/($B$16-$B$17)))*100)/2) -> 18.020833 | M33: =IF(COUNT(H33:J33)=3,AVERAGE(H33:J33),"") -> 24.333333 | N33: =IF(G33="","",G33) -> 54 | O33: =(K33="")+(L33="")+(M33="")+(N33="") -> 0 | P33: =IF(O33=0,"Complete",IF(O33=1,"Partial - 1 pillar defaulted","Limited - "&O33&" pillars defaulted")) -> Complete | Q33: =$B$5*IF(K33="",$B$18,K33)+$B$6*IF(L33="",$B$18,L33)+$B$7*IF(M33="",$B$18,M33)+$B$8*IF(N33="",$B$18,N33) -> 28.052267 | R33: =IF(INDEX('Supplier Universe & Risk'!$U$4:$U$33,MATCH($A33,'Supplier Universe & Risk'!$A$4:$A$33,0))="","",INDEX('Supplier Universe & Risk'!$U$4:$U$33,MATCH($A33,'Supplier Universe & Risk'!$A$4:$A$33,0))) -> 57.2 | S33: =IF(INDEX('Supplier Universe & Risk'!$V$4:$V$33,MATCH($A33,'Supplier Universe & Risk'!$A$4:$A$33,0))="","",INDEX('Supplier Universe & Risk'!$V$4:$V$33,MATCH($A33,'Supplier Universe & Risk'!$A$4:$A$33,0))) -> MEDIUM | T33: =R33-Q33 -> 29.147733 | U33: =RANK(R33,$R$23:$R$46) -> 15 | V33: =RANK(Q33,$Q$23:$Q$46) -> 20
A34: ORG-942 | B34: Lumen Magnetics Ltd. | C34: =IF(INDEX('Supplier Universe & Risk'!$M$4:$M$33,MATCH($A34,'Supplier Universe & Risk'!$A$4:$A$33,0))="","",INDEX('Supplier Universe & Risk'!$M$4:$M$33,MATCH($A34,'Supplier Universe & Risk'!$A$4:$A$33,0))) -> 1.37 | D34: =IF(INDEX('Supplier Universe & Risk'!$N$4:$N$33,MATCH($A34,'Supplier Universe & Risk'!$A$4:$A$33,0))="","",INDEX('Supplier Universe & Risk'!$N$4:$N$33,MATCH($A34,'Supplier Universe & Risk'!$A$4:$A$33,0))) -> 3 | E34: =IF(INDEX('Supplier Universe & Risk'!$O$4:$O$33,MATCH($A34,'Supplier Universe & Risk'!$A$4:$A$33,0))="","",INDEX('Supplier Universe & Risk'!$O$4:$O$33,MATCH($A34,'Supplier Universe & Risk'!$A$4:$A$33,0))) -> 89.5 | F34: =IF(INDEX('Supplier Universe & Risk'!$P$4:$P$33,MATCH($A34,'Supplier Universe & Risk'!$A$4:$A$33,0))="","",INDEX('Supplier Universe & Risk'!$P$4:$P$33,MATCH($A34,'Supplier Universe & Risk'!$A$4:$A$33,0))) -> -0.6 | G34: =IF(INDEX('Supplier Universe & Risk'!$Q$4:$Q$33,MATCH($A34,'Supplier Universe & Risk'!$A$4:$A$33,0))="","",INDEX('Supplier Universe & Risk'!$Q$4:$Q$33,MATCH($A34,'Supplier Universe & Risk'!$A$4:$A$33,0))) -> 63 | H34: =IF(INDEX('Supplier Universe & Risk'!$R$4:$R$33,MATCH($A34,'Supplier Universe & Risk'!$A$4:$A$33,0))="","",INDEX('Supplier Universe & Risk'!$R$4:$R$33,MATCH($A34,'Supplier Universe & Risk'!$A$4:$A$33,0))) -> 58 | I34: =IF(INDEX('Supplier Universe & Risk'!$S$4:$S$33,MATCH($A34,'Supplier Universe & Risk'!$A$4:$A$33,0))="","",INDEX('Supplier Universe & Risk'!$S$4:$S$33,MATCH($A34,'Supplier Universe & Risk'!$A$4:$A$33,0))) -> 62 | J34: =IF(INDEX('Supplier Universe & Risk'!$T$4:$T$33,MATCH($A34,'Supplier Universe & Risk'!$A$4:$A$33,0))="","",INDEX('Supplier Universe & Risk'!$T$4:$T$33,MATCH($A34,'Supplier Universe & Risk'!$A$4:$A$33,0))) -> 52 | K34: =IF(OR(C34="",D34=""),"",(MAX(0,MIN(1,($B$10-C34)/($B$10-$B$11)))*100+MAX(0,MIN(1,(D34-$B$12)/($B$13-$B$12)))*100)/2) -> 49.901961 | L34: =IF(OR(E34="",F34=""),"",(MAX(0,MIN(1,($B$14-E34)/($B$14-$B$15)))*100+MAX(0,MIN(1,($B$16-F34)/($B$16-$B$17)))*100)/2) -> 16.383929 | M34: =IF(COUNT(H34:J34)=3,AVERAGE(H34:J34),"") -> 57.333333 | N34: =IF(G34="","",G34) -> 63 | O34: =(K34="")+(L34="")+(M34="")+(N34="") -> 0 | P34: =IF(O34=0,"Complete",IF(O34=1,"Partial - 1 pillar defaulted","Limited - "&O34&" pillars defaulted")) -> Complete | Q34: =$B$5*IF(K34="",$B$18,K34)+$B$6*IF(L34="",$B$18,L34)+$B$7*IF(M34="",$B$18,M34)+$B$8*IF(N34="",$B$18,N34) -> 45.71657 | R34: =IF(INDEX('Supplier Universe & Risk'!$U$4:$U$33,MATCH($A34,'Supplier Universe & Risk'!$A$4:$A$33,0))="","",INDEX('Supplier Universe & Risk'!$U$4:$U$33,MATCH($A34,'Supplier Universe & Risk'!$A$4:$A$33,0))) -> 69.4 | S34: =IF(INDEX('Supplier Universe & Risk'!$V$4:$V$33,MATCH($A34,'Supplier Universe & Risk'!$A$4:$A$33,0))="","",INDEX('Supplier Universe & Risk'!$V$4:$V$33,MATCH($A34,'Supplier Universe & Risk'!$A$4:$A$33,0))) -> HIGH | T34: =R34-Q34 -> 23.68343 | U34: =RANK(R34,$R$23:$R$46) -> 6 | V34: =RANK(Q34,$Q$23:$Q$46) -> 8
... A46: ORG-659 | B46: Zenith Polymer Ltd. | C46: =IF(INDEX('Supplier Universe & Risk'!$M$4:$M$33,MATCH($A46,'Supplier Universe & Risk'!$A$4:$A$33,0))="","",INDEX('Supplier Universe & Risk'!$M$4:$M$33,MATCH($A46,'Supplier Universe & Risk'!$A$4:$A$33,0))) | D46: =IF(INDEX('Supplier Universe & Risk'!$N$4:$N$33,MATCH($A46,'Supplier Universe & Risk'!$A$4:$A$33,0))="","",INDEX('Supplier Universe & Risk'!$N$4:$N$33,MATCH($A46,'Supplier Universe & Risk'!$A$4:$A$33,0))) | E46: =IF(INDEX('Supplier Universe & Risk'!$O$4:$O$33,MATCH($A46,'Supplier Universe & Risk'!$A$4:$A$33,0))="","",INDEX('Supplier Universe & Risk'!$O$4:$O$33,MATCH($A46,'Supplier Universe & Risk'!$A$4:$A$33,0))) -> 90.9 | F46: =IF(INDEX('Supplier Universe & Risk'!$P$4:$P$33,MATCH($A46,'Supplier Universe & Risk'!$A$4:$A$33,0))="","",INDEX('Supplier Universe & Risk'!$P$4:$P$33,MATCH($A46,'Supplier Universe & Risk'!$A$4:$A$33,0))) -> -0.9 | G46: =IF(INDEX('Supplier Universe & Risk'!$Q$4:$Q$33,MATCH($A46,'Supplier Universe & Risk'!$A$4:$A$33,0))="","",INDEX('Supplier Universe & Risk'!$Q$4:$Q$33,MATCH($A46,'Supplier Universe & Risk'!$A$4:$A$33,0))) | H46: =IF(INDEX('Supplier Universe & Risk'!$R$4:$R$33,MATCH($A46,'Supplier Universe & Risk'!$A$4:$A$33,0))="","",INDEX('Supplier Universe & Risk'!$R$4:$R$33,MATCH($A46,'Supplier Universe & Risk'!$A$4:$A$33,0))) -> 19 | I46: =IF(INDEX('Supplier Universe & Risk'!$S$4:$S$33,MATCH($A46,'Supplier Universe & Risk'!$A$4:$A$33,0))="","",INDEX('Supplier Universe & Risk'!$S$4:$S$33,MATCH($A46,'Supplier Universe & Risk'!$A$4:$A$33,0))) -> 26 | J46: =IF(INDEX('Supplier Universe & Risk'!$T$4:$T$33,MATCH($A46,'Supplier Universe & Risk'!$A$4:$A$33,0))="","",INDEX('Supplier Universe & Risk'!$T$4:$T$33,MATCH($A46,'Supplier Universe & Risk'!$A$4:$A$33,0))) -> 25 | K46: =IF(OR(C46="",D46=""),"",(MAX(0,MIN(1,($B$10-C46)/($B$10-$B$11)))*100+MAX(0,MIN(1,(D46-$B$12)/($B$13-$B$12)))*100)/2) | L46: =IF(OR(E46="",F46=""),"",(MAX(0,MIN(1,($B$14-E46)/($B$14-$B$15)))*100+MAX(0,MIN(1,($B$16-F46)/($B$16-$B$17)))*100)/2) -> 12.723214 | M46: =IF(COUNT(H46:J46)=3,AVERAGE(H46:J46),"") -> 23.333333 | N46: =IF(G46="","",G46) | O46: =(K46="")+(L46="")+(M46="")+(N46="") -> 2 | P46: =IF(O46=0,"Complete",IF(O46=1,"Partial - 1 pillar defaulted","Limited - "&O46&" pillars defaulted")) -> Limited - 2 pillars defaulted | Q46: =$B$5*IF(K46="",$B$18,K46)+$B$6*IF(L46="",$B$18,L46)+$B$7*IF(M46="",$B$18,M46)+$B$8*IF(N46="",$B$18,N46) -> 37.180804 | R46: =IF(INDEX('Supplier Universe & Risk'!$U$4:$U$33,MATCH($A46,'Supplier Universe & Risk'!$A$4:$A$33,0))="","",INDEX('Supplier Universe & Risk'!$U$4:$U$33,MATCH($A46,'Supplier Universe & Risk'!$A$4:$A$33,0))) -> 51.6 | S46: =IF(INDEX('Supplier Universe & Risk'!$V$4:$V$33,MATCH($A46,'Supplier Universe & Risk'!$A$4:$A$33,0))="","",INDEX('Supplier Universe & Risk'!$V$4:$V$33,MATCH($A46,'Supplier Universe & Risk'!$A$4:$A$33,0))) -> MEDIUM | T46: =R46-Q46 -> 14.419196 | U46: =RANK(R46,$R$23:$R$46) -> 18 | V46: =RANK(Q46,$Q$23:$Q$46) -> 15
A48: Summary checks
A49: Correlation: headline vs intrinsic score | C49: =CORREL(Q23:Q46,R23:R46) -> 0.84183549
A50: Rank correlation (Spearman-style) | C50: =CORREL(U23:U46,V23:V46) -> 0.86858222
A51: Average gap (headline minus intrinsic) | C51: =AVERAGE(T23:T46) -> 18.071241
A52: Suppliers with at least one defaulted pillar | C52: =COUNTIF(O23:O46,">0") -> 6
A53: Headline-CRITICAL suppliers also in intrinsic top 5 | C53: =SUMPRODUCT((S23:S46="CRITICAL")*(V23:V46<=5)) -> 3
A55: Reading: high rank agreement means the headline ordering is broadly supported by the raw indicators. The large positive gap shows the headline carries factors beyond these eight columns. Suppliers with blank financial / assurance data (Umber, Verdant, Warden, Xenon, Yarrow, Zenith) are scored on available pillars plus the default, so their scores are provisional.

Sheet Supplier Network
A1: RECONSTRUCTED COMPONENT SUPPLIER NETWORK
A2: One row per component-supplier-tier relationship. Relationship status, allocation, evidence IDs, and caveats are retained. Inferred and unresolved links must not be treated as confirmed. CommonSpan control rows added in v2 (ownership overlay: Aster and Boreal share one owner). Excluded / mismatched entities are listed in 'Excluded & Mismatches'.
A3: Component ID | B3: Component Name | C3: Product(s) | D3: Tier | E3: Supplier / Entity | F3: Supplies To | G3: Allocation (if known) | H3: Facility / Site | I3: Relationship Status | J3: Supplier Risk Score | K3: Risk Category | L3: Evidence / Source IDs | M3: Network Interpretation / Caveat
A4: M10 | B4: Standard power assembly | C4: P1, P3 | D4: Tier 1 | E4: Aster Power Assemblies | F4: NovaDrive Technologies | G4: 60% | H4: SITE-018 | I4: Confirmed | J4: 51.8 | K4: MEDIUM | L4: DOC-001, DOC-002, SHP-00002 | M4: Allocation is planned/contracted, not actual purchase share. Both Tier-1 suppliers are controlled by CommonSpan Holdings (DOC-075), so this split sits inside one ownership group.
A5: M10 | B5: Standard power assembly | C5: P1, P3 | D5: Tier 1 | E5: Boreal Power Systems | F5: NovaDrive Technologies | G5: 40% | H5: SITE-025 | I5: Confirmed | J5: 52.7 | K5: MEDIUM | L5: DOC-005, DOC-006, SHP-00025 | M5: Allocation is planned/contracted, not actual purchase share. Both Tier-1 suppliers are controlled by CommonSpan Holdings (DOC-075), so this split sits inside one ownership group.
A6: M10 | B6: Standard power assembly | C6: P1, P3 | D6: Parent (control) | E6: CommonSpan Holdings | F6: Controls Aster and Boreal (no direct supply role) | G6: M10 requirement 100% under common control (Aster 60% + Boreal 40%) | H6: SITE-221 (office / service) | I6: Confirmed (ownership only) | K6: Unscored (holding company) | L6: DOC-075 | M6: Ownership statement, not a supply statement. Tier-1 diversification for this component is brand-level only: both assemblers share one owner and the same IonPeak die source (DOC-078). Treat as one common-control node for concentration and escalation.
A7: M20 | B7: High-voltage power assembly | C7: P2 | D7: Tier 1 | E7: Aster Power Assemblies | F7: NovaDrive Technologies | G7: 70% | H7: SITE-018 | I7: Confirmed | J7: 51.8 | K7: MEDIUM | L7: DOC-003, DOC-004 | M7: Allocation is planned/contracted, not actual purchase share. Both Tier-1 suppliers are controlled by CommonSpan Holdings (DOC-075), so this split sits inside one ownership group.
A8: M20 | B8: High-voltage power assembly | C8: P2 | D8: Tier 1 | E8: Boreal Power Systems | F8: NovaDrive Technologies | G8: 30% | H8: SITE-025 | I8: Confirmed | J8: 52.7 | K8: MEDIUM | L8: DOC-007, DOC-008 | M8: Allocation is planned/contracted, not actual purchase share. Both Tier-1 suppliers are controlled by CommonSpan Holdings (DOC-075), so this split sits inside one ownership group.
A9: M20 | B9: High-voltage power assembly | C9: P2 | D9: Parent (control) | E9: CommonSpan Holdings | F9: Controls Aster and Boreal (no direct supply role) | G9: M20 requirement 100% under common control (Aster 70% + Boreal 30%) | H9: SITE-221 (office / service) | I9: Confirmed (ownership only) | K9: Unscored (holding company) | L9: DOC-075 | M9: Ownership statement, not a supply statement. Tier-1 diversification for this component is brand-level only: both assemblers share one owner and the same IonPeak die source (DOC-078). Treat as one common-control node for concentration and escalation.
A10: C10 | B10: Control board | C10: P1, P2, P3 | D10: Tier 1 | E10: Cobalt Control Electronics | F10: NovaDrive Technologies | G10: 100% | H10: SITE-032 | I10: Confirmed | J10: 69 | K10: HIGH | L10: DOC-009, DOC-010 | M10: Single direct supplier per relationship evidence.
A11: C20 | B11: DC-link capacitor | C11: P1, P2 | D11: Tier 1 | E11: Delta Capacitor Works | F11: NovaDrive Technologies | G11: 100% | H11: SITE-039 | I11: Confirmed | J11: 49.7 | K11: MEDIUM | L11: DOC-011, DOC-012 | M11: Single direct supplier per relationship evidence.
A12: H10 | B12: Protective housing | C12: P1 | D12: Tier 1 | E12: ForgeLine Enclosures | F12: NovaDrive Technologies | G12: 100% | H12: SITE-053 | I12: Confirmed | J12: 45.4 | K12: MEDIUM | L12: DOC-015, DOC-016 | M12: Single direct supplier per relationship evidence.
A13: H20 | B13: Cooling assembly | C13: P2, P3 | D13: Tier 1 | E13: Estuary Thermal Systems | F13: NovaDrive Technologies | G13: 100% | H13: SITE-046 | I13: Confirmed | J13: 48.4 | K13: MEDIUM | L13: DOC-013, DOC-014 | M13: Current production supplier and qualification; allocation is planning signal, not actual deliveries.
A14: B10 | B14: Battery-monitoring board | C14: P3 | D14: Tier 1 | E14: Grove Battery Controls | F14: NovaDrive Technologies | G14: 80% | H14: SITE-060 | I14: Confirmed | J14: 44.6 | K14: LOW | L14: DOC-017, DOC-018 | M14: Allocation is planned/contracted, not actual purchase share.
A15: B10 | B15: Battery-monitoring board | C15: P3 | D15: Tier 1 | E15: HarborSense Electronics | F15: NovaDrive Technologies | G15: 20% | H15: SITE-067 | I15: Confirmed | J15: 32.5 | K15: LOW | L15: DOC-019, DOC-020 | M15: Allocation is planned/contracted, not actual purchase share.
A16: M10 | B16: Standard power assembly | C16: P1, P3 | D16: Tier 2 | E16: IonPeak Semiconductor | F16: Aster and Boreal | G16: Not stated | H16: SITE-074 | I16: Confirmed | J16: 79 | K16: CRITICAL | L16: DOC-021, DOC-023, DOC-077, DOC-078 | M16: Shared upstream dependency for M10/M20; do not confuse with Ion Peak Trading Ltd.
A17: M10 | B17: Standard power assembly | C17: P1, P3 | D17: Tier 2 | E17: Lumen Magnetics | F17: Aster and Boreal | G17: Not stated | H17: SITE-095 | I17: Confirmed | J17: 69.4 | K17: HIGH | L17: DOC-035, DOC-037 | M17: Shared upstream dependency for M10/M20.
A18: M10 | B18: Standard power assembly | C18: P1, P3 | D18: Tier 2 | E18: Orion Ceramics | F18: Aster and Boreal | G18: Not stated | H18: SITE-116 | I18: Confirmed | J18: 68.8 | K18: HIGH | L18: DOC-043, DOC-045 | M18: Shared upstream dependency for M10/M20.
A19: M20 | B19: High-voltage power assembly | C19: P2 | D19: Tier 2 | E19: IonPeak Semiconductor | F19: Aster and Boreal | G19: Not stated | H19: SITE-074 | I19: Confirmed | J19: 79 | K19: CRITICAL | L19: DOC-021, DOC-023, DOC-077, DOC-078 | M19: Shared upstream dependency for M10/M20.
A20: M20 | B20: High-voltage power assembly | C20: P2 | D20: Tier 2 | E20: Lumen Magnetics | F20: Aster and Boreal | G20: Not stated | H20: SITE-095 | I20: Confirmed | J20: 69.4 | K20: HIGH | L20: DOC-035, DOC-037 | M20: Shared upstream dependency for M10/M20.
A21: M20 | B21: High-voltage power assembly | C21: P2 | D21: Tier 2 | E21: Orion Ceramics | F21: Aster and Boreal | G21: Not stated | H21: SITE-116 | I21: Confirmed | J21: 68.8 | K21: HIGH | L21: DOC-043, DOC-045 | M21: Shared upstream dependency for M10/M20.
... A41: B10 | B41: Battery-monitoring board | C41: P3 | D41: Tier 3 | E41: Xenon Resin | F41: Jade Printed Circuits | G41: Not stated | H41: SITE-179 | I41: Confirmed | J41: 64.4 | K41: HIGH | L41: DOC-064 | M41: Shared Tier-3 dependency with C10 via Jade.
A42: B10 | B42: Battery-monitoring board | C42: P3 | D42: Tier 3 | E42: Solace Optics | F42: Grove Battery Controls | G42: Not stated | H42: Not established | I42: Unresolved hypothesis | K42: Unscored | L42: DOC-085 | M42: Do not include as confirmed supply-chain exposure pending verification.
A43: H10 | B43: Protective housing | C43: P1 | D43: Tier 3 | E43: Alder Bauxite | F43: Quartz Alloy | G43: Not stated | H43: Not established | I43: Unresolved hypothesis | K43: Unscored | L43: DOC-074, DOC-086 | M43: Do not include as confirmed supply-chain exposure pending verification.

Sheet Excluded & Mismatches
A1: EXCLUDED, MISMATCHED AND DOWNGRADED ITEMS
A2: Name look-alikes, role mix-ups, expired awards and unvalidated leads that must not be counted as supplier-network exposure. Kept visible so a reviewer can see what was considered and rejected, and why.
A3: # | B3: Item / entity | C3: Why it can look related | D3: Why it is excluded or downgraded | E3: Evidence IDs | F3: Treatment in this workbook | G3: Status
A4: 1 | B4: Delta Consumer Plastics (ORG-857) | C4: Shares the word "Delta" with Delta Capacitor Works (ORG-922). | D4: Trial retail-packaging memo in 2024 that never became a supply award; ships packaging to an unrelated customer. Different legal entity, site (SITE-249) and product. | E4: DOC-084; SHP-00438; EV-009 | F4: Not in network. EV-009 rejected as a false positive. | G4: Excluded / mismatch
A5: 2 | B5: Ion Peak Trading Ltd (ORG-309, REG-NO-4128) | C5: Near-identical name to IonPeak Semiconductor (ORG-439). | D5: Unrelated Harbor District broker, not a subsidiary of IonPeak Semiconductor. Not a manufacturer. | E5: DOC-077; EV-004 | F5: Not in network. EV-004 insolvency filing rejected; no supplier alert raised. | G5: Excluded / mismatch
A6: 3 | B6: Harbor Freight Services (ORG-328) | C6: Named as shipper on SHP-00125 carrying power dies to Aster. | D6: Freight consolidator / notify party, not a manufacturer. The shipment is consistent with the IonPeak-to-Aster die flow but does not make Harbor Freight a supplier. | E6: DOC-083; SHP-00125 | F6: Logistics intermediary only; not a supplier node. | G6: Excluded / mismatch
A7: 4 | B7: OceanLink Ports | C7: Appears in port-congestion event EV-010 and manifests. | D7: Terminal operator, not a component manufacturer. | E7: DOC-083; EV-010 | F7: Not in network. Route relevance to Estuary stays unconfirmed. | G7: Excluded / mismatch
A8: 5 | B8: Delta Capacitor Works as H10 housing supplier | C8: 2022 pilot supplied housings to NovaDrive. | D8: Housing programme ended 31 Dec 2023. The current Delta award is for C20 capacitors only. H10 is ForgeLine (100%). | E8: DOC-080 | F8: Expired; not an H10 link. | G8: Excluded (expired)
A9: 6 | B9: Jade Circuits Holdings (ORG-445) and SITE-901 HQ (Z07) | C9: Same group as Jade Printed Circuits; EV-007 reports an HQ relocation. | D9: Accounting parent and registered HQ only. Substrates are made at SITE-081 in Z01. HQ move does not change production. | E9: DOC-076; EV-007 | F9: Use SITE-081 / Z01 for location risk and events. EV-007 kept as low / monitor. | G9: Excluded (wrong facility)
A10: 7 | B10: IonPeak SITE-900, Western Ridge (Z05) | C10: Second IonPeak site that might look like a fallback. | D10: Research and pilot line on a different process; not a qualified replacement for the production dies made at SITE-074 (Z01). | E10: DOC-077 | F10: Not a fallback site. Z01 exposure at SITE-074 is not mitigated by SITE-900. | G10: Excluded (not qualified)
A11: 8 | B11: Alder Bauxite to Quartz Alloy | C11: Both appear in the same trade-association directory. | D11: Co-listing only; no purchase, award, product or facility link stated. Quartz does not name its bauxite sources. | E11: DOC-074; DOC-086 | F11: Research lead only; excluded from confirmed exposure. | G11: Unresolved hypothesis
A12: 9 | B12: Solace Optics to Grove Battery Controls (B10) | C12: Sample evaluation completed with Grove. | D12: No serial-production award announced; no current B10 production link substantiated. | E12: DOC-085 | F12: Held as hypothesis; not scored; not counted as exposure. | G12: Unresolved hypothesis
A13: 10 | B13: Verdant Process Gases to IonPeak (Tier-3) | C13: Listed IonPeak among industrial customers; index mentions M10/M20. | D13: Does not allocate purchases or identify the receiving line; product and continuity scope need validation. | E13: DOC-058 | F13: Retained in network as Inference with caveat; included in Z01 exposure map as inferred. | G13: Inference (retained)
A14: 11 | B14: CommonSpan Holdings (ORG-268) | C14: Appears in Supplier Universe like a supplier. | D14: Holding company with no supply role. Relevant only because it controls Aster and Boreal. | E14: DOC-075 | F14: Shown as ownership overlay (Parent / control) in Supplier Network, unscored. | G14: Included as control node

Sheet Relationship Evidence
A1: RAW RELATIONSHIP EVIDENCE
A2: Source-level evidence from the case dataset. Use Evidence ID and Source Family ID to trace network claims and avoid double-counting repeated evidence.
A3: Evidence ID | B3: Evidence Date | C3: Evidence Type | D3: Source Family ID | E3: Title / Parties | F3: Evidence Detail | G3: Record Status | H3: Source Locator
A4: DOC-001 | B4: 2025-08-14 | C4: Company program disclosure | D4: PROG-001 | E4: Aster Power Assemblies / NovaDrive Technologies program disclosure | F4: Aster Power Assemblies Ltd. has been named a production supplier to NovaDrive Technologies for component M10, used in P1, P3. Production takes place at SITE-018. The award is effective from 1 January 2025 through 31 December 2026. The disclosed contracted allocation is approximately 60% of NovaDrive requirements for this component; this is a planning allocation, not a purchase ledger or guarantee of realized deliveries. | G4: Current disclosure | H4: synthetic://evidence/DOC-001
A5: DOC-002 | B5: 2025-06-12 | C5: Qualification register | D5: QUAL-001 | E5: Production qualification: Aster Power Assemblies to NovaDrive Technologies | F5: A separate production qualification register names Aster Power Assemblies Ltd., site SITE-018, as qualified for NovaDrive Technologies Ltd. in the M10 program. Serial production approval was granted on 12 June 2025. The qualification remains current at the case cut-off. Registration confirms the approved relationship and site, but is not itself evidence of exclusive supply. | G5: Current disclosure | H5: synthetic://evidence/DOC-002
A6: DOC-003 | B6: 2025-08-14 | C6: Company program disclosure | D6: PROG-002 | E6: Aster Power Assemblies / NovaDrive Technologies program disclosure | F6: Aster Power Assemblies Ltd. has been named a production supplier to NovaDrive Technologies for component M20, used in P2. Production takes place at SITE-018. The award is effective from 1 January 2025 through 31 December 2026. The disclosed contracted allocation is approximately 70% of NovaDrive requirements for this component; this is a planning allocation, not a purchase ledger or guarantee of realized deliveries. | G6: Current disclosure | H6: synthetic://evidence/DOC-003
A7: DOC-004 | B7: 2025-06-12 | C7: Qualification register | D7: QUAL-002 | E7: Production qualification: Aster Power Assemblies to NovaDrive Technologies | F7: A separate production qualification register names Aster Power Assemblies Ltd., site SITE-018, as qualified for NovaDrive Technologies Ltd. in the M20 program. Serial production approval was granted on 12 June 2025. The qualification remains current at the case cut-off. Registration confirms the approved relationship and site, but is not itself evidence of exclusive supply. | G7: Current disclosure | H7: synthetic://evidence/DOC-004
A8: DOC-005 | B8: 2025-08-14 | C8: Company program disclosure | D8: PROG-003 | E8: Boreal Power Systems / NovaDrive Technologies program disclosure | F8: Boreal Power Systems Ltd. has been named a production supplier to NovaDrive Technologies for component M10, used in P1, P3. Production takes place at SITE-025. The award is effective from 1 January 2025 through 31 December 2026. The disclosed contracted allocation is approximately 40% of NovaDrive requirements for this component; this is a planning allocation, not a purchase ledger or guarantee of realized deliveries. | G8: Current disclosure | H8: synthetic://evidence/DOC-005
A9: DOC-006 | B9: 2025-06-12 | C9: Qualification register | D9: QUAL-003 | E9: Production qualification: Boreal Power Systems to NovaDrive Technologies | F9: A separate production qualification register names Boreal Power Systems Ltd., site SITE-025, as qualified for NovaDrive Technologies Ltd. in the M10 program. Serial production approval was granted on 12 June 2025. The qualification remains current at the case cut-off. Registration confirms the approved relationship and site, but is not itself evidence of exclusive supply. | G9: Current disclosure | H9: synthetic://evidence/DOC-006
A10: DOC-007 | B10: 2025-08-14 | C10: Company program disclosure | D10: PROG-004 | E10: Boreal Power Systems / NovaDrive Technologies program disclosure | F10: Boreal Power Systems Ltd. has been named a production supplier to NovaDrive Technologies for component M20, used in P2. Production takes place at SITE-025. The award is effective from 1 January 2025 through 31 December 2026. The disclosed contracted allocation is approximately 30% of NovaDrive requirements for this component; this is a planning allocation, not a purchase ledger or guarantee of realized deliveries. | G10: Current disclosure | H10: synthetic://evidence/DOC-007
A11: DOC-008 | B11: 2025-06-12 | C11: Qualification register | D11: QUAL-004 | E11: Production qualification: Boreal Power Systems to NovaDrive Technologies | F11: A separate production qualification register names Boreal Power Systems Ltd., site SITE-025, as qualified for NovaDrive Technologies Ltd. in the M20 program. Serial production approval was granted on 12 June 2025. The qualification remains current at the case cut-off. Registration confirms the approved relationship and site, but is not itself evidence of exclusive supply. | G11: Current disclosure | H11: synthetic://evidence/DOC-008
A12: DOC-009 | B12: 2025-08-14 | C12: Company program disclosure | D12: PROG-005 | E12: Cobalt Control Electronics / NovaDrive Technologies program disclosure | F12: Cobalt Control Electronics Ltd. has been named a production supplier to NovaDrive Technologies for component C10, used in P1, P2, P3. Production takes place at SITE-032. The award is effective from 1 January 2025 through 31 December 2026. The disclosed contracted allocation is approximately 100% of NovaDrive requirements for this component; this is a planning allocation, not a purchase ledger or guarantee of realized deliveries. | G12: Current disclosure | H12: synthetic://evidence/DOC-009
A13: DOC-010 | B13: 2025-06-12 | C13: Qualification register | D13: QUAL-005 | E13: Production qualification: Cobalt Control Electronics to NovaDrive Technologies | F13: A separate production qualification register names Cobalt Control Electronics Ltd., site SITE-032, as qualified for NovaDrive Technologies Ltd. in the C10 program. Serial production approval was granted on 12 June 2025. The qualification remains current at the case cut-off. Registration confirms the approved relationship and site, but is not itself evidence of exclusive supply. | G13: Current disclosure | H13: synthetic://evidence/DOC-010
A14: DOC-011 | B14: 2025-08-14 | C14: Company program disclosure | D14: PROG-006 | E14: Delta Capacitor Works / NovaDrive Technologies program disclosure | F14: Delta Capacitor Works Ltd. has been named a production supplier to NovaDrive Technologies for component C20, used in P1, P2. Production takes place at SITE-039. The award is effective from 1 January 2025 through 31 December 2026. The disclosed contracted allocation is approximately 100% of NovaDrive requirements for this component; this is a planning allocation, not a purchase ledger or guarantee of realized deliveries. | G14: Current disclosure | H14: synthetic://evidence/DOC-011
... A62: SHP-00125 | B62: 2025-04-07 | C62: Shipment observation | D62: MANIFEST-BOL-00125 | E62: HARBOR FREIGHT SERVICES -> Aster Power Assemblies LTD | F62: Shipment observation: shipper 'HARBOR FREIGHT SERVICES' to consignee 'Aster Power Assemblies LTD', origin Consolidation terminal, goods 'M10;M20 / Power semiconductor dies', mode Ocean. Weight/cartons are not purchase shares and this extract is partial. | G62: Observed record | H62: synthetic://shipments/SHP-00125

Sheet Component Risk
A1: COMPONENT / NETWORK RISK SCORECARD
A2: Derived component-level screening scores and management interpretation. Scores are prioritization indicators, not statistically validated disruption probabilities.
A3: Component ID | B3: Component | C3: Products Affected | D3: Tier-1 Suppliers / Allocation | E3: Tier-1 Weighted Risk Score | F3: Tier-2 Suppliers | G3: Highest Tier-2 Risk Score | H3: Tier-3 Suppliers / Relationship Status | I3: Highest Tier-3 Risk Score | J3: Concentration / Dependency Score | K3: Event Exposure Score | L3: Calculated Component Network Risk Score | M3: Risk Category | N3: Evidence Confidence | O3: Relevant Event IDs | P3: Event / Exposure Interpretation | Q3: Key Shared Dependency | R3: Qualification Lead Time (weeks) | S3: Recommended Management Action | T3: Evidence IDs / Traceability | U3: Scoring Interpretation | V3: Revenue Dependent (USD m) | W3: Share of Total Revenue | X3: Risk-Weighted Revenue Index (USD m) | Y3: Priority Rank (revenue-weighted)
A4: M10 | B4: Standard power assembly | C4: P1, P3 | D4: Aster Power Assemblies (60%); Boreal Power Systems (40%) | E4: 52.2 | F4: IonPeak Semiconductor; Lumen Magnetics; Orion Ceramics | G4: 79 | H4: Umber Silicon Carbide (via IonPeak); Yarrow Specialty Minerals (via Orion); Verdant Process Gases (via IonPeak; inferred) | I4: 74.4 | J4: 80 | K4: 55 | L4: 66.7 | M4: HIGH | N4: High for named links; Medium for Verdant inference | O4: EV-001 / EV-002 (same source family; duplicate signal) | P4: East Delta flood watch for Z01 overlaps FOUR mapped facilities in this chain: IonPeak (SITE-074), Orion (SITE-116), Umber Silicon Carbide (SITE-158, Tier-3) and Verdant Process Gases (SITE-165, Tier-3, inferred link). A fifth Z01 facility, Jade (SITE-081), sits behind C10/B10. No factory damage or shutdown confirmed; no second die source or alternate IonPeak site is qualified (DOC-077, DOC-078). | Q4: IonPeak, Lumen, Orion shared with M20; upstream exposure can affect P1/P2/P3 across network Aster and Boreal are both controlled by CommonSpan Holdings (DOC-075), so Tier-1 diversification is brand-level only. | R4: 16 | S4: Verify current site status and inventory cover at IonPeak/Orion; validate inferred Verdant link; prepare a shared M10/M20 upstream continuity plan. | T4: DOC-001, DOC-002, SHP-00002; DOC-005, DOC-006, SHP-00025; DOC-021, DOC-023, DOC-035, DOC-037, DOC-043, DOC-045, DOC-056, DOC-066; DOC-058 (inference) | U4: Score = weighted average of available indicators: Tier-1 risk 35%, highest Tier-2 risk 25%, highest Tier-3 risk 15%, concentration 15%, event exposure 10%. Missing Tier-3 score weight is redistributed proportionally across available indicators. This is a transparent screening score, not a statistically validated loss probability. | V4: =SUMPRODUCT(ISNUMBER(SEARCH('Business & Components'!$A$3:$A$5,$C4))*'Business & Components'!$C$3:$C$5) -> 1040 | W4: =V4/SUM('Business & Components'!$C$3:$C$5) -> 0.66666667 | X4: =L4/100*V4 -> 693.68 | Y4: =RANK(X4,$X$4:$X$10) -> 3
A5: M20 | B5: High-voltage power assembly | C5: P2 | D5: Aster Power Assemblies (70%); Boreal Power Systems (30%) | E5: 52.1 | F5: IonPeak Semiconductor; Lumen Magnetics; Orion Ceramics | G5: 79 | H5: Umber Silicon Carbide (via IonPeak); Yarrow Specialty Minerals (via Orion); Verdant Process Gases (via IonPeak; inferred) | I5: 74.4 | J5: 80 | K5: 55 | L5: 66.6 | M5: HIGH | N5: High for named links; Medium for Verdant inference | O5: EV-001 / EV-002 (same source family; duplicate signal) | P5: Same Z01 flood-watch exposure across IonPeak, Orion, Umber and Verdant (inferred) facilities; no production interruption confirmed; no second die source or alternate IonPeak site is qualified (DOC-077, DOC-078). | Q5: IonPeak, Lumen, Orion shared with M10; upstream exposure can affect P1/P2/P3 across network Aster and Boreal are both controlled by CommonSpan Holdings (DOC-075), so Tier-1 diversification is brand-level only. | R5: 16 | S5: Check M20 safety stock and supplier continuity plans; assess alternate assembly route and upstream semiconductor contingency. Qualification lead time is long. | T5: DOC-003, DOC-004; DOC-007, DOC-008; DOC-021, DOC-023, DOC-035, DOC-037, DOC-043, DOC-045, DOC-056, DOC-066; DOC-058 (inference) | U5: Score = weighted average of available indicators: Tier-1 risk 35%, highest Tier-2 risk 25%, highest Tier-3 risk 15%, concentration 15%, event exposure 10%. Missing Tier-3 score weight is redistributed proportionally across available indicators. This is a transparent screening score, not a statistically validated loss probability. | V5: =SUMPRODUCT(ISNUMBER(SEARCH('Business & Components'!$A$3:$A$5,$C5))*'Business & Components'!$C$3:$C$5) -> 520 | W5: =V5/SUM('Business & Components'!$C$3:$C$5) -> 0.33333333 | X5: =L5/100*V5 -> 346.32 | Y5: =RANK(X5,$X$4:$X$10) -> 5
A6: C10 | B6: Control board | C6: P1, P2, P3 | D6: Cobalt Control Electronics (100%) | E6: 69 | F6: Jade Printed Circuits; Kestrel Microdevices; Rill Connectors | G6: 79 | H6: Warden Copper Foil (via Jade); Xenon Resin (via Jade) | I6: 64.9 | J6: 90 | K6: 55 | L6: 72.6 | M6: HIGH | N6: High for named links | O6: EV-001 / EV-002; EV-007 (HQ move is not production disruption) | P6: Jade production site is in the flood-watch zone; no damage/shutdown confirmed. Jade HQ relocation is administrative and production remains at East Delta. | Q6: Jade also supports B10, creating cross-component common-mode exposure | R6: 12 | S6: Build continuity plan for Cobalt and Jade; verify Jade facility status and inventory; initiate alternate PCB/PCBA feasibility review. | T6: DOC-009, DOC-010, DOC-025, DOC-031, DOC-051, DOC-060, DOC-064, DOC-079 | U6: Score = weighted average of available indicators: Tier-1 risk 35%, highest Tier-2 risk 25%, highest Tier-3 risk 15%, concentration 15%, event exposure 10%. Missing Tier-3 score weight is redistributed proportionally across available indicators. This is a transparent screening score, not a statistically validated loss probability. | V6: =SUMPRODUCT(ISNUMBER(SEARCH('Business & Components'!$A$3:$A$5,$C6))*'Business & Components'!$C$3:$C$5) -> 1560 | W6: =V6/SUM('Business & Components'!$C$3:$C$5) -> 1 | X6: =L6/100*V6 -> 1132.56 | Y6: =RANK(X6,$X$4:$X$10) -> 1
A7: C20 | B7: DC-link capacitor | C7: P1, P2 | D7: Delta Capacitor Works (100%) | E7: 49.7 | F7: Meridian Dielectrics; Nacre Foils | G7: 83.7 | H7: Zenith Polymer (via Meridian) | I7: 51.6 | J7: 100 | K7: 75 | L7: 68.6 | M7: HIGH | N7: High for named links | O7: EV-003; EV-009 excluded as wrong entity | P7: Meridian reported covenant negotiations and delayed payments to two trade creditors; production continues. EV-009 concerns Delta Consumer Plastics, not Delta Capacitor Works. | Q7: Meridian and Zenith are upstream of a single direct supplier pathway | R7: 8 | S7: Escalate Meridian financial monitoring; verify production, payment terms, allocation and inventory; confirm Delta’s contingency plan and screen alternate capacitor sources. | T7: DOC-011, DOC-012, DOC-039, DOC-041, DOC-070 | U7: Score = weighted average of available indicators: Tier-1 risk 35%, highest Tier-2 risk 25%, highest Tier-3 risk 15%, concentration 15%, event exposure 10%. Missing Tier-3 score weight is redistributed proportionally across available indicators. This is a transparent screening score, not a statistically validated loss probability. | V7: =SUMPRODUCT(ISNUMBER(SEARCH('Business & Components'!$A$3:$A$5,$C7))*'Business & Components'!$C$3:$C$5) -> 1144 | W7: =V7/SUM('Business & Components'!$C$3:$C$5) -> 0.73333333 | X7: =L7/100*V7 -> 784.784 | Y7: =RANK(X7,$X$4:$X$10) -> 2
A8: H10 | B8: Protective housing | C8: P1 | D8: ForgeLine Enclosures (100%) | E8: 45.4 | F8: Quartz Alloy | G8: 39.3 | H8: Alder Bauxite (unresolved hypothesis only; not included in confirmed network) | J8: 100 | K8: 0 | L8: 47.9 | M8: MEDIUM | N8: High for ForgeLine/Quartz links; Low/Unresolved for Alder hypothesis | O8: No relevant current event established; EV-009 is a different entity | P8: No direct event-to-production impact established. Alder Bauxite link remains unresolved and must not be treated as confirmed. | Q8: Single direct source ForgeLine; no confirmed Tier-3 relationship | R8: 4 | S8: Verify capacity, tooling ownership, recovery options and alternate fabricators; do not include Alder Bauxite in confirmed exposure until evidence is found. | T8: DOC-015, DOC-016, DOC-049; DOC-074, DOC-086 (unresolved hypothesis) | U8: Score = weighted average of available indicators: Tier-1 risk 35%, highest Tier-2 risk 25%, highest Tier-3 risk 15%, concentration 15%, event exposure 10%. Missing Tier-3 score weight is redistributed proportionally across available indicators. This is a transparent screening score, not a statistically validated loss probability. | V8: =SUMPRODUCT(ISNUMBER(SEARCH('Business & Components'!$A$3:$A$5,$C8))*'Business & Components'!$C$3:$C$5) -> 624 | W8: =V8/SUM('Business & Components'!$C$3:$C$5) -> 0.4 | X8: =L8/100*V8 -> 298.896 | Y8: =RANK(X8,$X$4:$X$10) -> 6
A9: H20 | B9: Cooling assembly | C9: P2, P3 | D9: Estuary Thermal Systems (100%) | E9: 48.4 | F9: Pine Thermal Metals | G9: 57.3 | J9: 100 | K9: 35 | L9: 58.5 | M9: MEDIUM | N9: High for named links | O9: EV-010 (route exposure unconfirmed) | P9: Gulf Arc departures have average terminal delays of three days; shipment-specific exposure and connection to Estuary are not assessed. | Q9: Single direct source Estuary; route exposure from EV-010 is unverified | R9: 6 | S9: Check Estuary shipping lanes, open orders, buffer stock and route alternatives; assess second-source feasibility. Do not assume EV-010 affects Estuary until route evidence is checked. | T9: DOC-013, DOC-014, DOC-047 | U9: Score = weighted average of available indicators: Tier-1 risk 35%, highest Tier-2 risk 25%, highest Tier-3 risk 15%, concentration 15%, event exposure 10%. Missing Tier-3 score weight is redistributed proportionally across available indicators. This is a transparent screening score, not a statistically validated loss probability. | V9: =SUMPRODUCT(ISNUMBER(SEARCH('Business & Components'!$A$3:$A$5,$C9))*'Business & Components'!$C$3:$C$5) -> 936 | W9: =V9/SUM('Business & Components'!$C$3:$C$5) -> 0.6 | X9: =L9/100*V9 -> 547.56 | Y9: =RANK(X9,$X$4:$X$10) -> 4
A10: B10 | B10: Battery-monitoring board | C10: P3 | D10: Grove Battery Controls (80%); HarborSense Electronics (20%) | E10: 42.2 | F10: Jade Printed Circuits (via Grove and HarborSense); Kestrel Microdevices (via Grove) | G10: 79 | H10: Warden Copper Foil (via Jade); Xenon Resin (via Jade); Solace Optics (unresolved hypothesis via Grove) | I10: 64.9 | J10: 85 | K10: 55 | L10: 62.5 | M10: HIGH | N10: High for named links; Low/Unresolved for Solace hypothesis | O10: EV-001 / EV-002; EV-007 (HQ relocation only) | P10: Both direct suppliers rely on Jade for PCB substrates, creating a common upstream dependency; Jade’s production site is in Z01 flood-watch area, with no damage/shutdown confirmed. | Q10: Jade is shared with C10 and is used by both Grove and HarborSense | R10: 12 | S10: Treat Jade as common-mode exposure across C10 and B10; verify PCB substrate cover and alternatives; validate Solace before including it in the confirmed network. | T10: DOC-017, DOC-018, DOC-019, DOC-020, DOC-027, DOC-029, DOC-033, DOC-060, DOC-064, DOC-079; DOC-085 (unresolved hypothesis) | U10: Score = weighted average of available indicators: Tier-1 risk 35%, highest Tier-2 risk 25%, highest Tier-3 risk 15%, concentration 15%, event exposure 10%. Missing Tier-3 score weight is redistributed proportionally across available indicators. This is a transparent screening score, not a statistically validated loss probability. | V10: =SUMPRODUCT(ISNUMBER(SEARCH('Business & Components'!$A$3:$A$5,$C10))*'Business & Components'!$C$3:$C$5) -> 416 | W10: =V10/SUM('Business & Components'!$C$3:$C$5) -> 0.26666667 | X10: =L10/100*V10 -> 260 | Y10: =RANK(X10,$X$4:$X$10) -> 7
A12: Revenue criticality (added v2): Revenue Dependent = product revenue (Business & Components) of every product that uses the component. Risk-Weighted Revenue Index = network risk score / 100 x revenue dependent. It is a prioritisation index that blends exposure with business criticality, not an expected loss, because no supplier spend or purchase data is provided. The network risk score in column L is unchanged.

Sheet Node Criticality
A1: NODE CRITICALITY (which entities carry the most revenue and risk)
A2: Every entity in the reconstructed network, with the products it ultimately reaches and the product revenue that depends on it (revenue pulled from Business & Components). Risk-weighted index = supplier risk score / 100 x revenue dependent: a prioritisation aid, not a loss estimate (no supplier spend is available). Unresolved hypotheses and excluded entities are not included.
A3: Entity ID | B3: Entity | C3: Network role | D3: Components fed | E3: Products reached | F3: Revenue dependent (USD m) | G3: Share of total revenue | H3: Supplier risk score | I3: Risk band | J3: Relationship status | K3: Risk-weighted revenue index (USD m) | L3: Rank | M3: Reading
A4: ORG-439 | B4: IonPeak Semiconductor | C4: Tier 2 | D4: M10, M20 | E4: P1, P2, P3 | F4: =SUMPRODUCT(ISNUMBER(SEARCH('Business & Components'!$A$3:$A$5,$E4))*'Business & Components'!$C$3:$C$5) -> 1560 | G4: =F4/SUM('Business & Components'!$C$3:$C$5) -> 1 | H4: =IF(INDEX('Supplier Universe & Risk'!$U$4:$U$33,MATCH($A4,'Supplier Universe & Risk'!$A$4:$A$33,0))="","n/a",INDEX('Supplier Universe & Risk'!$U$4:$U$33,MATCH($A4,'Supplier Universe & Risk'!$A$4:$A$33,0))) -> 79 | I4: =IF(INDEX('Supplier Universe & Risk'!$V$4:$V$33,MATCH($A4,'Supplier Universe & Risk'!$A$4:$A$33,0))="","n/a",INDEX('Supplier Universe & Risk'!$V$4:$V$33,MATCH($A4,'Supplier Universe & Risk'!$A$4:$A$33,0))) -> CRITICAL | J4: Confirmed | K4: =IF(ISNUMBER(H4),H4/100*F4,"n/a") -> 1232.4 | L4: =IF(ISNUMBER(K4),RANK(K4,$K$4:$K$28),"n/a") -> 1 | M4: Sole qualified die source for both Aster and Boreal; Z01 exposure; revenue reach is all three products. No alternate die source or site is qualified.
A5: ORG-453 | B5: Jade Printed Circuits | C5: Tier 2 | D5: C10, B10 | E5: P1, P2, P3 | F5: =SUMPRODUCT(ISNUMBER(SEARCH('Business & Components'!$A$3:$A$5,$E5))*'Business & Components'!$C$3:$C$5) -> 1560 | G5: =F5/SUM('Business & Components'!$C$3:$C$5) -> 1 | H5: =IF(INDEX('Supplier Universe & Risk'!$U$4:$U$33,MATCH($A5,'Supplier Universe & Risk'!$A$4:$A$33,0))="","n/a",INDEX('Supplier Universe & Risk'!$U$4:$U$33,MATCH($A5,'Supplier Universe & Risk'!$A$4:$A$33,0))) -> 79 | I5: =IF(INDEX('Supplier Universe & Risk'!$V$4:$V$33,MATCH($A5,'Supplier Universe & Risk'!$A$4:$A$33,0))="","n/a",INDEX('Supplier Universe & Risk'!$V$4:$V$33,MATCH($A5,'Supplier Universe & Risk'!$A$4:$A$33,0))) -> CRITICAL | J5: Confirmed | K5: =IF(ISNUMBER(H5),H5/100*F5,"n/a") -> 1232.4 | L5: =IF(ISNUMBER(K5),RANK(K5,$K$4:$K$28),"n/a") -> 1 | M5: Single substrate source behind C10 (all products) and both B10 suppliers; Z01 plant; no qualified independent substrate.
A6: ORG-455 | B6: Umber Silicon Carbide | C6: Tier 3 | D6: M10, M20 | E6: P1, P2, P3 | F6: =SUMPRODUCT(ISNUMBER(SEARCH('Business & Components'!$A$3:$A$5,$E6))*'Business & Components'!$C$3:$C$5) -> 1560 | G6: =F6/SUM('Business & Components'!$C$3:$C$5) -> 1 | H6: =IF(INDEX('Supplier Universe & Risk'!$U$4:$U$33,MATCH($A6,'Supplier Universe & Risk'!$A$4:$A$33,0))="","n/a",INDEX('Supplier Universe & Risk'!$U$4:$U$33,MATCH($A6,'Supplier Universe & Risk'!$A$4:$A$33,0))) -> 74.4 | I6: =IF(INDEX('Supplier Universe & Risk'!$V$4:$V$33,MATCH($A6,'Supplier Universe & Risk'!$A$4:$A$33,0))="","n/a",INDEX('Supplier Universe & Risk'!$V$4:$V$33,MATCH($A6,'Supplier Universe & Risk'!$A$4:$A$33,0))) -> HIGH | J6: Confirmed | K6: =IF(ISNUMBER(H6),H6/100*F6,"n/a") -> 1160.64 | L6: =IF(ISNUMBER(K6),RANK(K6,$K$4:$K$28),"n/a") -> 3 | M6: Tier-3 behind IonPeak; Z01; financial data blank (provisional score).
A7: ORG-736 | B7: Verdant Process Gases | C7: Tier 3 | D7: M10, M20 | E7: P1, P2, P3 | F7: =SUMPRODUCT(ISNUMBER(SEARCH('Business & Components'!$A$3:$A$5,$E7))*'Business & Components'!$C$3:$C$5) -> 1560 | G7: =F7/SUM('Business & Components'!$C$3:$C$5) -> 1 | H7: =IF(INDEX('Supplier Universe & Risk'!$U$4:$U$33,MATCH($A7,'Supplier Universe & Risk'!$A$4:$A$33,0))="","n/a",INDEX('Supplier Universe & Risk'!$U$4:$U$33,MATCH($A7,'Supplier Universe & Risk'!$A$4:$A$33,0))) -> 73.4 | I7: =IF(INDEX('Supplier Universe & Risk'!$V$4:$V$33,MATCH($A7,'Supplier Universe & Risk'!$A$4:$A$33,0))="","n/a",INDEX('Supplier Universe & Risk'!$V$4:$V$33,MATCH($A7,'Supplier Universe & Risk'!$A$4:$A$33,0))) -> HIGH | J7: Inference | K7: =IF(ISNUMBER(H7),H7/100*F7,"n/a") -> 1145.04 | L7: =IF(ISNUMBER(K7),RANK(K7,$K$4:$K$28),"n/a") -> 4 | M7: Inferred link only (DOC-058); Z01; validate before relying on it.
A8: ORG-942 | B8: Lumen Magnetics | C8: Tier 2 | D8: M10, M20 | E8: P1, P2, P3 | F8: =SUMPRODUCT(ISNUMBER(SEARCH('Business & Components'!$A$3:$A$5,$E8))*'Business & Components'!$C$3:$C$5) -> 1560 | G8: =F8/SUM('Business & Components'!$C$3:$C$5) -> 1 | H8: =IF(INDEX('Supplier Universe & Risk'!$U$4:$U$33,MATCH($A8,'Supplier Universe & Risk'!$A$4:$A$33,0))="","n/a",INDEX('Supplier Universe & Risk'!$U$4:$U$33,MATCH($A8,'Supplier Universe & Risk'!$A$4:$A$33,0))) -> 69.4 | I8: =IF(INDEX('Supplier Universe & Risk'!$V$4:$V$33,MATCH($A8,'Supplier Universe & Risk'!$A$4:$A$33,0))="","n/a",INDEX('Supplier Universe & Risk'!$V$4:$V$33,MATCH($A8,'Supplier Universe & Risk'!$A$4:$A$33,0))) -> HIGH | J8: Confirmed | K8: =IF(ISNUMBER(H8),H8/100*F8,"n/a") -> 1082.64 | L8: =IF(ISNUMBER(K8),RANK(K8,$K$4:$K$28),"n/a") -> 5
A9: ORG-119 | B9: Cobalt Control Electronics | C9: Tier 1 | D9: C10 | E9: P1, P2, P3 | F9: =SUMPRODUCT(ISNUMBER(SEARCH('Business & Components'!$A$3:$A$5,$E9))*'Business & Components'!$C$3:$C$5) -> 1560 | G9: =F9/SUM('Business & Components'!$C$3:$C$5) -> 1 | H9: =IF(INDEX('Supplier Universe & Risk'!$U$4:$U$33,MATCH($A9,'Supplier Universe & Risk'!$A$4:$A$33,0))="","n/a",INDEX('Supplier Universe & Risk'!$U$4:$U$33,MATCH($A9,'Supplier Universe & Risk'!$A$4:$A$33,0))) -> 69 | I9: =IF(INDEX('Supplier Universe & Risk'!$V$4:$V$33,MATCH($A9,'Supplier Universe & Risk'!$A$4:$A$33,0))="","n/a",INDEX('Supplier Universe & Risk'!$V$4:$V$33,MATCH($A9,'Supplier Universe & Risk'!$A$4:$A$33,0))) -> HIGH | J9: Confirmed | K9: =IF(ISNUMBER(H9),H9/100*F9,"n/a") -> 1076.4 | L9: =IF(ISNUMBER(K9),RANK(K9,$K$4:$K$28),"n/a") -> 6 | M9: 100% single source for C10 across all three products.
A10: ORG-708 | B10: Orion Ceramics | C10: Tier 2 | D10: M10, M20 | E10: P1, P2, P3 | F10: =SUMPRODUCT(ISNUMBER(SEARCH('Business & Components'!$A$3:$A$5,$E10))*'Business & Components'!$C$3:$C$5) -> 1560 | G10: =F10/SUM('Business & Components'!$C$3:$C$5) -> 1 | H10: =IF(INDEX('Supplier Universe & Risk'!$U$4:$U$33,MATCH($A10,'Supplier Universe & Risk'!$A$4:$A$33,0))="","n/a",INDEX('Supplier Universe & Risk'!$U$4:$U$33,MATCH($A10,'Supplier Universe & Risk'!$A$4:$A$33,0))) -> 68.8 | I10: =IF(INDEX('Supplier Universe & Risk'!$V$4:$V$33,MATCH($A10,'Supplier Universe & Risk'!$A$4:$A$33,0))="","n/a",INDEX('Supplier Universe & Risk'!$V$4:$V$33,MATCH($A10,'Supplier Universe & Risk'!$A$4:$A$33,0))) -> HIGH | J10: Confirmed | K10: =IF(ISNUMBER(H10),H10/100*F10,"n/a") -> 1073.28 | L10: =IF(ISNUMBER(K10),RANK(K10,$K$4:$K$28),"n/a") -> 7
A11: ORG-873 | B11: Warden Copper Foil | C11: Tier 3 | D11: C10, B10 | E11: P1, P2, P3 | F11: =SUMPRODUCT(ISNUMBER(SEARCH('Business & Components'!$A$3:$A$5,$E11))*'Business & Components'!$C$3:$C$5) -> 1560 | G11: =F11/SUM('Business & Components'!$C$3:$C$5) -> 1 | H11: =IF(INDEX('Supplier Universe & Risk'!$U$4:$U$33,MATCH($A11,'Supplier Universe & Risk'!$A$4:$A$33,0))="","n/a",INDEX('Supplier Universe & Risk'!$U$4:$U$33,MATCH($A11,'Supplier Universe & Risk'!$A$4:$A$33,0))) -> 64.9 | I11: =IF(INDEX('Supplier Universe & Risk'!$V$4:$V$33,MATCH($A11,'Supplier Universe & Risk'!$A$4:$A$33,0))="","n/a",INDEX('Supplier Universe & Risk'!$V$4:$V$33,MATCH($A11,'Supplier Universe & Risk'!$A$4:$A$33,0))) -> HIGH | J11: Confirmed | K11: =IF(ISNUMBER(H11),H11/100*F11,"n/a") -> 1012.44 | L11: =IF(ISNUMBER(K11),RANK(K11,$K$4:$K$28),"n/a") -> 8
A12: ORG-179 | B12: Xenon Resin | C12: Tier 3 | D12: C10, B10 | E12: P1, P2, P3 | F12: =SUMPRODUCT(ISNUMBER(SEARCH('Business & Components'!$A$3:$A$5,$E12))*'Business & Components'!$C$3:$C$5) -> 1560 | G12: =F12/SUM('Business & Components'!$C$3:$C$5) -> 1 | H12: =IF(INDEX('Supplier Universe & Risk'!$U$4:$U$33,MATCH($A12,'Supplier Universe & Risk'!$A$4:$A$33,0))="","n/a",INDEX('Supplier Universe & Risk'!$U$4:$U$33,MATCH($A12,'Supplier Universe & Risk'!$A$4:$A$33,0))) -> 64.4 | I12: =IF(INDEX('Supplier Universe & Risk'!$V$4:$V$33,MATCH($A12,'Supplier Universe & Risk'!$A$4:$A$33,0))="","n/a",INDEX('Supplier Universe & Risk'!$V$4:$V$33,MATCH($A12,'Supplier Universe & Risk'!$A$4:$A$33,0))) -> HIGH | J12: Confirmed | K12: =IF(ISNUMBER(H12),H12/100*F12,"n/a") -> 1004.64 | L12: =IF(ISNUMBER(K12),RANK(K12,$K$4:$K$28),"n/a") -> 9
A13: ORG-520 | B13: Yarrow Specialty Minerals | C13: Tier 3 | D13: M10, M20 | E13: P1, P2, P3 | F13: =SUMPRODUCT(ISNUMBER(SEARCH('Business & Components'!$A$3:$A$5,$E13))*'Business & Components'!$C$3:$C$5) -> 1560 | G13: =F13/SUM('Business & Components'!$C$3:$C$5) -> 1 | H13: =IF(INDEX('Supplier Universe & Risk'!$U$4:$U$33,MATCH($A13,'Supplier Universe & Risk'!$A$4:$A$33,0))="","n/a",INDEX('Supplier Universe & Risk'!$U$4:$U$33,MATCH($A13,'Supplier Universe & Risk'!$A$4:$A$33,0))) -> 63.5 | I13: =IF(INDEX('Supplier Universe & Risk'!$V$4:$V$33,MATCH($A13,'Supplier Universe & Risk'!$A$4:$A$33,0))="","n/a",INDEX('Supplier Universe & Risk'!$V$4:$V$33,MATCH($A13,'Supplier Universe & Risk'!$A$4:$A$33,0))) -> HIGH | J13: Confirmed | K13: =IF(ISNUMBER(H13),H13/100*F13,"n/a") -> 990.6 | L13: =IF(ISNUMBER(K13),RANK(K13,$K$4:$K$28),"n/a") -> 10
A14: ORG-210 | B14: Meridian Dielectrics | C14: Tier 2 | D14: C20 | E14: P1, P2 | F14: =SUMPRODUCT(ISNUMBER(SEARCH('Business & Components'!$A$3:$A$5,$E14))*'Business & Components'!$C$3:$C$5) -> 1144 | G14: =F14/SUM('Business & Components'!$C$3:$C$5) -> 0.73333333 | H14: =IF(INDEX('Supplier Universe & Risk'!$U$4:$U$33,MATCH($A14,'Supplier Universe & Risk'!$A$4:$A$33,0))="","n/a",INDEX('Supplier Universe & Risk'!$U$4:$U$33,MATCH($A14,'Supplier Universe & Risk'!$A$4:$A$33,0))) -> 83.7 | I14: =IF(INDEX('Supplier Universe & Risk'!$V$4:$V$33,MATCH($A14,'Supplier Universe & Risk'!$A$4:$A$33,0))="","n/a",INDEX('Supplier Universe & Risk'!$V$4:$V$33,MATCH($A14,'Supplier Universe & Risk'!$A$4:$A$33,0))) -> CRITICAL | J14: Confirmed | K14: =IF(ISNUMBER(H14),H14/100*F14,"n/a") -> 957.528 | L14: =IF(ISNUMBER(K14),RANK(K14,$K$4:$K$28),"n/a") -> 11 | M14: Highest supplier risk in the network (financial stress); sole film route for C20; production reported continuing (EV-003).
A15: ORG-469 | B15: Rill Connectors | C15: Tier 2 | D15: C10 | E15: P1, P2, P3 | F15: =SUMPRODUCT(ISNUMBER(SEARCH('Business & Components'!$A$3:$A$5,$E15))*'Business & Components'!$C$3:$C$5) -> 1560 | G15: =F15/SUM('Business & Components'!$C$3:$C$5) -> 1 | H15: =IF(INDEX('Supplier Universe & Risk'!$U$4:$U$33,MATCH($A15,'Supplier Universe & Risk'!$A$4:$A$33,0))="","n/a",INDEX('Supplier Universe & Risk'!$U$4:$U$33,MATCH($A15,'Supplier Universe & Risk'!$A$4:$A$33,0))) -> 60.9 | I15: =IF(INDEX('Supplier Universe & Risk'!$V$4:$V$33,MATCH($A15,'Supplier Universe & Risk'!$A$4:$A$33,0))="","n/a",INDEX('Supplier Universe & Risk'!$V$4:$V$33,MATCH($A15,'Supplier Universe & Risk'!$A$4:$A$33,0))) -> HIGH | J15: Confirmed | K15: =IF(ISNUMBER(H15),H15/100*F15,"n/a") -> 950.04 | L15: =IF(ISNUMBER(K15),RANK(K15,$K$4:$K$28),"n/a") -> 12
A16: ORG-728 | B16: Kestrel Microdevices | C16: Tier 2 | D16: C10, B10 | E16: P1, P2, P3 | F16: =SUMPRODUCT(ISNUMBER(SEARCH('Business & Components'!$A$3:$A$5,$E16))*'Business & Components'!$C$3:$C$5) -> 1560 | G16: =F16/SUM('Business & Components'!$C$3:$C$5) -> 1 | H16: =IF(INDEX('Supplier Universe & Risk'!$U$4:$U$33,MATCH($A16,'Supplier Universe & Risk'!$A$4:$A$33,0))="","n/a",INDEX('Supplier Universe & Risk'!$U$4:$U$33,MATCH($A16,'Supplier Universe & Risk'!$A$4:$A$33,0))) -> 57.2 | I16: =IF(INDEX('Supplier Universe & Risk'!$V$4:$V$33,MATCH($A16,'Supplier Universe & Risk'!$A$4:$A$33,0))="","n/a",INDEX('Supplier Universe & Risk'!$V$4:$V$33,MATCH($A16,'Supplier Universe & Risk'!$A$4:$A$33,0))) -> MEDIUM | J16: Confirmed | K16: =IF(ISNUMBER(H16),H16/100*F16,"n/a") -> 892.32 | L16: =IF(ISNUMBER(K16),RANK(K16,$K$4:$K$28),"n/a") -> 13
A17: ORG-725 | B17: Boreal Power Systems | C17: Tier 1 | D17: M10, M20 | E17: P1, P2, P3 | F17: =SUMPRODUCT(ISNUMBER(SEARCH('Business & Components'!$A$3:$A$5,$E17))*'Business & Components'!$C$3:$C$5) -> 1560 | G17: =F17/SUM('Business & Components'!$C$3:$C$5) -> 1 | H17: =IF(INDEX('Supplier Universe & Risk'!$U$4:$U$33,MATCH($A17,'Supplier Universe & Risk'!$A$4:$A$33,0))="","n/a",INDEX('Supplier Universe & Risk'!$U$4:$U$33,MATCH($A17,'Supplier Universe & Risk'!$A$4:$A$33,0))) -> 52.7 | I17: =IF(INDEX('Supplier Universe & Risk'!$V$4:$V$33,MATCH($A17,'Supplier Universe & Risk'!$A$4:$A$33,0))="","n/a",INDEX('Supplier Universe & Risk'!$V$4:$V$33,MATCH($A17,'Supplier Universe & Risk'!$A$4:$A$33,0))) -> MEDIUM | J17: Confirmed | K17: =IF(ISNUMBER(H17),H17/100*F17,"n/a") -> 822.12 | L17: =IF(ISNUMBER(K17),RANK(K17,$K$4:$K$28),"n/a") -> 14 | M17: 40% / 30% of M10 / M20 planning allocation.
A18: ORG-247 | B18: Aster Power Assemblies | C18: Tier 1 | D18: M10, M20 | E18: P1, P2, P3 | F18: =SUMPRODUCT(ISNUMBER(SEARCH('Business & Components'!$A$3:$A$5,$E18))*'Business & Components'!$C$3:$C$5) -> 1560 | G18: =F18/SUM('Business & Components'!$C$3:$C$5) -> 1 | H18: =IF(INDEX('Supplier Universe & Risk'!$U$4:$U$33,MATCH($A18,'Supplier Universe & Risk'!$A$4:$A$33,0))="","n/a",INDEX('Supplier Universe & Risk'!$U$4:$U$33,MATCH($A18,'Supplier Universe & Risk'!$A$4:$A$33,0))) -> 51.8 | I18: =IF(INDEX('Supplier Universe & Risk'!$V$4:$V$33,MATCH($A18,'Supplier Universe & Risk'!$A$4:$A$33,0))="","n/a",INDEX('Supplier Universe & Risk'!$V$4:$V$33,MATCH($A18,'Supplier Universe & Risk'!$A$4:$A$33,0))) -> MEDIUM | J18: Confirmed | K18: =IF(ISNUMBER(H18),H18/100*F18,"n/a") -> 808.08 | L18: =IF(ISNUMBER(K18),RANK(K18,$K$4:$K$28),"n/a") -> 15 | M18: 60% / 70% of M10 / M20 planning allocation.
A19: ORG-849 | B19: Nacre Foils | C19: Tier 2 | D19: C20 | E19: P1, P2 | F19: =SUMPRODUCT(ISNUMBER(SEARCH('Business & Components'!$A$3:$A$5,$E19))*'Business & Components'!$C$3:$C$5) -> 1144 | G19: =F19/SUM('Business & Components'!$C$3:$C$5) -> 0.73333333 | H19: =IF(INDEX('Supplier Universe & Risk'!$U$4:$U$33,MATCH($A19,'Supplier Universe & Risk'!$A$4:$A$33,0))="","n/a",INDEX('Supplier Universe & Risk'!$U$4:$U$33,MATCH($A19,'Supplier Universe & Risk'!$A$4:$A$33,0))) -> 61.7 | I19: =IF(INDEX('Supplier Universe & Risk'!$V$4:$V$33,MATCH($A19,'Supplier Universe & Risk'!$A$4:$A$33,0))="","n/a",INDEX('Supplier Universe & Risk'!$V$4:$V$33,MATCH($A19,'Supplier Universe & Risk'!$A$4:$A$33,0))) -> HIGH | J19: Confirmed | K19: =IF(ISNUMBER(H19),H19/100*F19,"n/a") -> 705.848 | L19: =IF(ISNUMBER(K19),RANK(K19,$K$4:$K$28),"n/a") -> 16
A20: ORG-659 | B20: Zenith Polymer | C20: Tier 3 | D20: C20 | E20: P1, P2 | F20: =SUMPRODUCT(ISNUMBER(SEARCH('Business & Components'!$A$3:$A$5,$E20))*'Business & Components'!$C$3:$C$5) -> 1144 | G20: =F20/SUM('Business & Components'!$C$3:$C$5) -> 0.73333333 | H20: =IF(INDEX('Supplier Universe & Risk'!$U$4:$U$33,MATCH($A20,'Supplier Universe & Risk'!$A$4:$A$33,0))="","n/a",INDEX('Supplier Universe & Risk'!$U$4:$U$33,MATCH($A20,'Supplier Universe & Risk'!$A$4:$A$33,0))) -> 51.6 | I20: =IF(INDEX('Supplier Universe & Risk'!$V$4:$V$33,MATCH($A20,'Supplier Universe & Risk'!$A$4:$A$33,0))="","n/a",INDEX('Supplier Universe & Risk'!$V$4:$V$33,MATCH($A20,'Supplier Universe & Risk'!$A$4:$A$33,0))) -> MEDIUM | J20: Confirmed | K20: =IF(ISNUMBER(H20),H20/100*F20,"n/a") -> 590.304 | L20: =IF(ISNUMBER(K20),RANK(K20,$K$4:$K$28),"n/a") -> 17
A21: ORG-922 | B21: Delta Capacitor Works | C21: Tier 1 | D21: C20 | E21: P1, P2 | F21: =SUMPRODUCT(ISNUMBER(SEARCH('Business & Components'!$A$3:$A$5,$E21))*'Business & Components'!$C$3:$C$5) -> 1144 | G21: =F21/SUM('Business & Components'!$C$3:$C$5) -> 0.73333333 | H21: =IF(INDEX('Supplier Universe & Risk'!$U$4:$U$33,MATCH($A21,'Supplier Universe & Risk'!$A$4:$A$33,0))="","n/a",INDEX('Supplier Universe & Risk'!$U$4:$U$33,MATCH($A21,'Supplier Universe & Risk'!$A$4:$A$33,0))) -> 49.7 | I21: =IF(INDEX('Supplier Universe & Risk'!$V$4:$V$33,MATCH($A21,'Supplier Universe & Risk'!$A$4:$A$33,0))="","n/a",INDEX('Supplier Universe & Risk'!$V$4:$V$33,MATCH($A21,'Supplier Universe & Risk'!$A$4:$A$33,0))) -> MEDIUM | J21: Confirmed | K21: =IF(ISNUMBER(H21),H21/100*F21,"n/a") -> 568.568 | L21: =IF(ISNUMBER(K21),RANK(K21,$K$4:$K$28),"n/a") -> 18
A22: ORG-274 | B22: Pine Thermal Metals | C22: Tier 2 | D22: H20 | E22: P2, P3 | F22: =SUMPRODUCT(ISNUMBER(SEARCH('Business & Components'!$A$3:$A$5,$E22))*'Business & Components'!$C$3:$C$5) -> 936 | G22: =F22/SUM('Business & Components'!$C$3:$C$5) -> 0.6 | H22: =IF(INDEX('Supplier Universe & Risk'!$U$4:$U$33,MATCH($A22,'Supplier Universe & Risk'!$A$4:$A$33,0))="","n/a",INDEX('Supplier Universe & Risk'!$U$4:$U$33,MATCH($A22,'Supplier Universe & Risk'!$A$4:$A$33,0))) -> 57.3 | I22: =IF(INDEX('Supplier Universe & Risk'!$V$4:$V$33,MATCH($A22,'Supplier Universe & Risk'!$A$4:$A$33,0))="","n/a",INDEX('Supplier Universe & Risk'!$V$4:$V$33,MATCH($A22,'Supplier Universe & Risk'!$A$4:$A$33,0))) -> MEDIUM | J22: Confirmed | K22: =IF(ISNUMBER(H22),H22/100*F22,"n/a") -> 536.328 | L22: =IF(ISNUMBER(K22),RANK(K22,$K$4:$K$28),"n/a") -> 19
A23: ORG-786 | B23: Estuary Thermal Systems | C23: Tier 1 | D23: H20 | E23: P2, P3 | F23: =SUMPRODUCT(ISNUMBER(SEARCH('Business & Components'!$A$3:$A$5,$E23))*'Business & Components'!$C$3:$C$5) -> 936 | G23: =F23/SUM('Business & Components'!$C$3:$C$5) -> 0.6 | H23: =IF(INDEX('Supplier Universe & Risk'!$U$4:$U$33,MATCH($A23,'Supplier Universe & Risk'!$A$4:$A$33,0))="","n/a",INDEX('Supplier Universe & Risk'!$U$4:$U$33,MATCH($A23,'Supplier Universe & Risk'!$A$4:$A$33,0))) -> 48.4 | I23: =IF(INDEX('Supplier Universe & Risk'!$V$4:$V$33,MATCH($A23,'Supplier Universe & Risk'!$A$4:$A$33,0))="","n/a",INDEX('Supplier Universe & Risk'!$V$4:$V$33,MATCH($A23,'Supplier Universe & Risk'!$A$4:$A$33,0))) -> MEDIUM | J23: Confirmed | K23: =IF(ISNUMBER(H23),H23/100*F23,"n/a") -> 453.024 | L23: =IF(ISNUMBER(K23),RANK(K23,$K$4:$K$28),"n/a") -> 20
A24: ORG-287 | B24: ForgeLine Enclosures | C24: Tier 1 | D24: H10 | E24: P1 | F24: =SUMPRODUCT(ISNUMBER(SEARCH('Business & Components'!$A$3:$A$5,$E24))*'Business & Components'!$C$3:$C$5) -> 624 | G24: =F24/SUM('Business & Components'!$C$3:$C$5) -> 0.4 | H24: =IF(INDEX('Supplier Universe & Risk'!$U$4:$U$33,MATCH($A24,'Supplier Universe & Risk'!$A$4:$A$33,0))="","n/a",INDEX('Supplier Universe & Risk'!$U$4:$U$33,MATCH($A24,'Supplier Universe & Risk'!$A$4:$A$33,0))) -> 45.4 | I24: =IF(INDEX('Supplier Universe & Risk'!$V$4:$V$33,MATCH($A24,'Supplier Universe & Risk'!$A$4:$A$33,0))="","n/a",INDEX('Supplier Universe & Risk'!$V$4:$V$33,MATCH($A24,'Supplier Universe & Risk'!$A$4:$A$33,0))) -> MEDIUM | J24: Confirmed | K24: =IF(ISNUMBER(H24),H24/100*F24,"n/a") -> 283.296 | L24: =IF(ISNUMBER(K24),RANK(K24,$K$4:$K$28),"n/a") -> 21
A25: ORG-329 | B25: Quartz Alloy | C25: Tier 2 | D25: H10 | E25: P1 | F25: =SUMPRODUCT(ISNUMBER(SEARCH('Business & Components'!$A$3:$A$5,$E25))*'Business & Components'!$C$3:$C$5) -> 624 | G25: =F25/SUM('Business & Components'!$C$3:$C$5) -> 0.4 | H25: =IF(INDEX('Supplier Universe & Risk'!$U$4:$U$33,MATCH($A25,'Supplier Universe & Risk'!$A$4:$A$33,0))="","n/a",INDEX('Supplier Universe & Risk'!$U$4:$U$33,MATCH($A25,'Supplier Universe & Risk'!$A$4:$A$33,0))) -> 39.3 | I25: =IF(INDEX('Supplier Universe & Risk'!$V$4:$V$33,MATCH($A25,'Supplier Universe & Risk'!$A$4:$A$33,0))="","n/a",INDEX('Supplier Universe & Risk'!$V$4:$V$33,MATCH($A25,'Supplier Universe & Risk'!$A$4:$A$33,0))) -> LOW | J25: Confirmed | K25: =IF(ISNUMBER(H25),H25/100*F25,"n/a") -> 245.232 | L25: =IF(ISNUMBER(K25),RANK(K25,$K$4:$K$28),"n/a") -> 22
A26: ORG-103 | B26: Grove Battery Controls | C26: Tier 1 | D26: B10 | E26: P3 | F26: =SUMPRODUCT(ISNUMBER(SEARCH('Business & Components'!$A$3:$A$5,$E26))*'Business & Components'!$C$3:$C$5) -> 416 | G26: =F26/SUM('Business & Components'!$C$3:$C$5) -> 0.26666667 | H26: =IF(INDEX('Supplier Universe & Risk'!$U$4:$U$33,MATCH($A26,'Supplier Universe & Risk'!$A$4:$A$33,0))="","n/a",INDEX('Supplier Universe & Risk'!$U$4:$U$33,MATCH($A26,'Supplier Universe & Risk'!$A$4:$A$33,0))) -> 44.6 | I26: =IF(INDEX('Supplier Universe & Risk'!$V$4:$V$33,MATCH($A26,'Supplier Universe & Risk'!$A$4:$A$33,0))="","n/a",INDEX('Supplier Universe & Risk'!$V$4:$V$33,MATCH($A26,'Supplier Universe & Risk'!$A$4:$A$33,0))) -> LOW | J26: Confirmed | K26: =IF(ISNUMBER(H26),H26/100*F26,"n/a") -> 185.536 | L26: =IF(ISNUMBER(K26),RANK(K26,$K$4:$K$28),"n/a") -> 23
A27: ORG-176 | B27: HarborSense Electronics | C27: Tier 1 | D27: B10 | E27: P3 | F27: =SUMPRODUCT(ISNUMBER(SEARCH('Business & Components'!$A$3:$A$5,$E27))*'Business & Components'!$C$3:$C$5) -> 416 | G27: =F27/SUM('Business & Components'!$C$3:$C$5) -> 0.26666667 | H27: =IF(INDEX('Supplier Universe & Risk'!$U$4:$U$33,MATCH($A27,'Supplier Universe & Risk'!$A$4:$A$33,0))="","n/a",INDEX('Supplier Universe & Risk'!$U$4:$U$33,MATCH($A27,'Supplier Universe & Risk'!$A$4:$A$33,0))) -> 32.5 | I27: =IF(INDEX('Supplier Universe & Risk'!$V$4:$V$33,MATCH($A27,'Supplier Universe & Risk'!$A$4:$A$33,0))="","n/a",INDEX('Supplier Universe & Risk'!$V$4:$V$33,MATCH($A27,'Supplier Universe & Risk'!$A$4:$A$33,0))) -> LOW | J27: Confirmed | K27: =IF(ISNUMBER(H27),H27/100*F27,"n/a") -> 135.2 | L27: =IF(ISNUMBER(K27),RANK(K27,$K$4:$K$28),"n/a") -> 24
A28: ORG-268 | B28: CommonSpan Holdings | C28: Parent (control) | D28: M10, M20 | E28: P1, P2, P3 | F28: =SUMPRODUCT(ISNUMBER(SEARCH('Business & Components'!$A$3:$A$5,$E28))*'Business & Components'!$C$3:$C$5) -> 1560 | G28: =F28/SUM('Business & Components'!$C$3:$C$5) -> 1 | H28: =IF(INDEX('Supplier Universe & Risk'!$U$4:$U$33,MATCH($A28,'Supplier Universe & Risk'!$A$4:$A$33,0))="","n/a",INDEX('Supplier Universe & Risk'!$U$4:$U$33,MATCH($A28,'Supplier Universe & Risk'!$A$4:$A$33,0))) -> n/a | I28: =IF(INDEX('Supplier Universe & Risk'!$V$4:$V$33,MATCH($A28,'Supplier Universe & Risk'!$A$4:$A$33,0))="","n/a",INDEX('Supplier Universe & Risk'!$V$4:$V$33,MATCH($A28,'Supplier Universe & Risk'!$A$4:$A$33,0))) -> n/a | J28: Confirmed (ownership only) | K28: =IF(ISNUMBER(H28),H28/100*F28,"n/a") -> n/a | L28: =IF(ISNUMBER(K28),RANK(K28,$K$4:$K$28),"n/a") -> n/a | M28: Control overlay: owns both M10/M20 assemblers. Unscored holding company.

Sheet Event Feed & Alerts
A1: EVENT FEED + MATCHING / ALERT DISPOSITION
A2: Raw event records combined with relevance matching, component mapping, priority, action, and false-positive/duplicate controls. Use source family and entity/site matching to avoid false alerts.
A3: Event ID | B3: Published At | C3: Effective At | D3: Title | E3: Event Detail | F3: Source Family ID | G3: Source Type | H3: Matched Entity / Geography | I3: Match Result | J3: Affected Component(s) | K3: Affected Product(s) | L3: Alert Priority | M3: Management Alert | N3: Required Verification / Next Action | O3: False Positive / Duplication Control | P3: Alert Source Family ID
A4: EV-001 | B4: 2025-09-23 | C4: 2025-09-23 | D4: East Delta flood watch | E4: The East Delta authority issues a flood watch for Z01. No factory damage or shutdown is confirmed. | F4: WX-0923 | G4: Report | H4: Z01 (East Delta) - five mapped facilities: IonPeak Semiconductor SITE-074; Orion Ceramics SITE-116; Jade Printed Circuits SITE-081; Umber Silicon Carbide SITE-158 (Tier-3 via IonPeak); Verdant Process Gases SITE-165 (Tier-3, inferred link). See 'Z01 Flood Exposure'. | I4: Geographic match on 5 facilities (4 confirmed, 1 inferred); no damage confirmed | J4: M10, M20, C10, B10 | K4: P1, P2, P3 | L4: HIGH | M4: Flood watch overlaps the whole IonPeak die chain (die, SiC wafer and process-gas facilities all sit in Z01) plus Orion (ceramics) and Jade (PCB substrates). Together these sit behind every product in scope (P1, P2, P3: USD 1,560m revenue dependent). No second die source and no qualified alternate IonPeak site exist (DOC-077, DOC-078), and Jade substrates have no qualified independent source (DOC-079), so a site outage could not be absorbed by switching suppliers. No factory damage or shutdown is confirmed; this is a preparedness alert, not a disruption declaration. | N4: Verify each of the five facility locations against Z01; ask IonPeak, Orion and Jade for site status, access, utilities, inventory cover and recovery estimate; ask IonPeak about wafer (Umber) and gas (Verdant) cover; check open-order exposure at Aster, Boreal, Cobalt, Grove and HarborSense. | O4: EV-002 is a republication of the same authority bulletin; count as one signal, not two. | P4: WX-0923
A5: EV-002 | B5: 2025-09-23 | C5: 2025-09-23 | D5: Trade-wire repeats flood watch | E5: This article republishes the same East Delta authority bulletin as EV-001. It adds no independent evidence. | F5: WX-0923 | G5: Report | H5: Same Z01 flood-watch bulletin as EV-001 | I5: Duplicate of EV-001; no incremental evidence | J5: M10, M20, C10, B10 | K5: P1, P2, P3 | L5: INFORMATIONAL / DUPLICATE | M5: No separate alert should be raised. Attach the report to EV-001 as a duplicate supporting mention only. | N5: Link to parent event EV-001 and retain source trail. | O5: Same Source Family ID WX-0923. | P5: WX-0923
A6: EV-003 | B6: 2025-09-24 | C6: 2025-09-24 | D6: Meridian financing pressure | E6: Meridian Dielectrics reports covenant negotiations and delayed payments to two trade creditors; production continues. | F6: MD-FIN-0924 | G6: Report | H6: Meridian Dielectrics | I6: Exact entity match; production reported continuing | J6: C20 | K6: P1, P2 | L6: HIGH | M6: Meridian is a critical upstream supplier for C20. Covenant negotiations and delayed payments could threaten continuity even though production is currently reported to continue. | N6: Escalate supplier financial monitoring; verify production schedule, inventory, credit terms, raw-material cover, allocation and Delta Capacitor Works contingency options. | O6: Do not describe this as a shutdown or insolvency; event says production continues. | P6: MD-FIN-0924
A7: EV-004 | B7: 2025-09-25 | C7: 2025-09-25 | D7: Ion Peak Trading insolvency filing | E7: Ion Peak Trading Ltd., REG-NO-4128, enters restructuring. The company is a broker in Harbor District, not IonPeak Semiconductor. | F7: IPT-0925 | G7: Report | H7: Ion Peak Trading Ltd., REG-NO-4128 | I7: Entity mismatch; not IonPeak Semiconductor | J7: None established | K7: None established | L7: REJECT / FALSE POSITIVE | M7: Do not raise a NovaDrive supplier-risk alert from this event. The named entity is a broker in Harbor District, not the semiconductor supplier in the mapped network. | N7: If needed, verify legal name and registration ID before any future match. | O7: Legal entity disambiguation prevents name-based false positive. | P7: IPT-0925
A8: EV-005 | B8: 2025-09-26 | C8: 2023-11-03 | D8: Archived port strike reposted | E8: An aggregator republishes a port strike from 3 November 2023. The original dispute ended in 2023. No current strike is announced. | F8: OLD-PORT | G8: Report | H8: Historical port strike; no current strike announced | I8: Stale event; no current disruption | J8: None established | K8: None established | L8: REJECT / STALE | M8: Do not treat as a current logistics alert; original dispute ended in 2023. | N8: Retain for audit only; require a current effective date and current operating status before escalation. | O8: Published 2025 but effective 2023; effective date controls currentness. | P8: OLD-PORT
A9: EV-007 | B9: 2025-09-27 | C9: 2025-09-27 | D9: Jade head office relocation | E9: Jade moves its administrative headquarters within Harbor District. Production remains at its East Delta site. | F9: JADE-HQ | G9: Report | H9: Jade Printed Circuits; administrative HQ within Harbor District | I9: Entity match, but facility/function mismatch for production impact | J9: C10, B10 (watch only; no new disruption alert) | K9: P1, P2, P3 | L9: LOW / MONITOR | M9: Jade is a critical shared upstream PCB substrate supplier, but the event explicitly says production remains at East Delta. HQ relocation alone does not indicate production disruption. | N9: Confirm the production site remains operational only if required; do not change risk score based on HQ move alone. | O9: Separate administrative headquarters from production facility. | P9: JADE-HQ
A10: EV-009 | B10: 2025-09-29 | C10: 2025-09-29 | D10: Delta packaging allegation corrected | E10: An allegation concerns Delta Consumer Plastics, not Delta Capacitor Works. No named link to NovaDrive production is established. | F10: DELTA-IDENTITY | G10: Report | H10: Delta Consumer Plastics, not Delta Capacitor Works | I10: Entity mismatch; excluded | J10: None established | K10: None established | L10: REJECT / FALSE POSITIVE | M10: Do not associate the allegation with Delta Capacitor Works or C20. | N10: Keep legal entity names distinct; no NovaDrive production link established. | O10: Name similarity is insufficient for matching. | P10: DELTA-IDENTITY
A11: EV-010 | B11: 2025-09-30 | C11: 2025-09-30 | D11: Gulf Arc port congestion | E11: OceanLink reports average terminal delay of three days for Gulf Arc departures. Shipment-specific impact has not been assessed. | F11: PORT-GULF | G11: Report | H11: Gulf Arc departures; Estuary route link unconfirmed | I11: Geographic/logistics signal; shipment linkage unresolved | J11: H20 (conditional only) | K11: P2, P3 | L11: MEDIUM / VERIFY | M11: Three-day average terminal delay could affect cooling-assembly deliveries only if Estuary shipments use the affected departures. No shipment-specific impact has been assessed. | N11: Check bills of lading, origin/destination, routing, ETAs, open orders and buffer stock; raise priority only if relevant shipments are confirmed. | O11: Do not infer supplier exposure from geography alone. | P11: PORT-GULF

Sheet Z01 Flood Exposure
A1: Z01 FLOOD-WATCH EXPOSURE MAP (EV-001 / EV-002, one signal)
A2: Every facility in the supplier universe located in zone Z01, checked against the reconstructed network. A flood watch is geographic only: no damage or shutdown is confirmed, so this is a preparedness view.
A3: Entity ID | B3: Entity | C3: Facility ID | D3: Facility zone (lookup) | E3: Network tier | F3: Components exposed | G3: Products reached | H3: Revenue dependent (USD m) | I3: Supplier risk score | J3: Relationship status | K3: Qualified alternate in network?
A4: ORG-439 | B4: IonPeak Semiconductor | C4: SITE-074 | D4: =INDEX('Supplier Universe & Risk'!$I$4:$I$33,MATCH($A4,'Supplier Universe & Risk'!$A$4:$A$33,0)) -> Z01 | E4: Tier 2 | F4: M10, M20 | G4: P1, P2, P3 | H4: =SUMPRODUCT(ISNUMBER(SEARCH('Business & Components'!$A$3:$A$5,$G4))*'Business & Components'!$C$3:$C$5) -> 1560 | I4: =INDEX('Supplier Universe & Risk'!$U$4:$U$33,MATCH($A4,'Supplier Universe & Risk'!$A$4:$A$33,0)) -> 79 | J4: Confirmed | K4: No. Sole qualified die source; SITE-900 (Z05) is a pilot line, not a qualified replacement (DOC-077, DOC-078).
A5: ORG-455 | B5: Umber Silicon Carbide | C5: SITE-158 | D5: =INDEX('Supplier Universe & Risk'!$I$4:$I$33,MATCH($A5,'Supplier Universe & Risk'!$A$4:$A$33,0)) -> Z01 | E5: Tier 3 (via IonPeak) | F5: M10, M20 | G5: P1, P2, P3 | H5: =SUMPRODUCT(ISNUMBER(SEARCH('Business & Components'!$A$3:$A$5,$G5))*'Business & Components'!$C$3:$C$5) -> 1560 | I5: =INDEX('Supplier Universe & Risk'!$U$4:$U$33,MATCH($A5,'Supplier Universe & Risk'!$A$4:$A$33,0)) -> 74.4 | J5: Confirmed | K5: Not assessed in source data; upstream wafer source for IonPeak.
A6: ORG-736 | B6: Verdant Process Gases | C6: SITE-165 | D6: =INDEX('Supplier Universe & Risk'!$I$4:$I$33,MATCH($A6,'Supplier Universe & Risk'!$A$4:$A$33,0)) -> Z01 | E6: Tier 3 (via IonPeak) | F6: M10, M20 | G6: P1, P2, P3 | H6: =SUMPRODUCT(ISNUMBER(SEARCH('Business & Components'!$A$3:$A$5,$G6))*'Business & Components'!$C$3:$C$5) -> 1560 | I6: =INDEX('Supplier Universe & Risk'!$U$4:$U$33,MATCH($A6,'Supplier Universe & Risk'!$A$4:$A$33,0)) -> 73.4 | J6: Inference | K6: Not assessed; link is an inference (DOC-058) and needs validation.
A7: ORG-708 | B7: Orion Ceramics | C7: SITE-116 | D7: =INDEX('Supplier Universe & Risk'!$I$4:$I$33,MATCH($A7,'Supplier Universe & Risk'!$A$4:$A$33,0)) -> Z01 | E7: Tier 2 | F7: M10, M20 | G7: P1, P2, P3 | H7: =SUMPRODUCT(ISNUMBER(SEARCH('Business & Components'!$A$3:$A$5,$G7))*'Business & Components'!$C$3:$C$5) -> 1560 | I7: =INDEX('Supplier Universe & Risk'!$U$4:$U$33,MATCH($A7,'Supplier Universe & Risk'!$A$4:$A$33,0)) -> 68.8 | J7: Confirmed | K7: Not assessed in source data; ceramic substrates for both Aster and Boreal.
A8: ORG-453 | B8: Jade Printed Circuits | C8: SITE-081 | D8: =INDEX('Supplier Universe & Risk'!$I$4:$I$33,MATCH($A8,'Supplier Universe & Risk'!$A$4:$A$33,0)) -> Z01 | E8: Tier 2 | F8: C10, B10 | G8: P1, P2, P3 | H8: =SUMPRODUCT(ISNUMBER(SEARCH('Business & Components'!$A$3:$A$5,$G8))*'Business & Components'!$C$3:$C$5) -> 1560 | I8: =INDEX('Supplier Universe & Risk'!$U$4:$U$33,MATCH($A8,'Supplier Universe & Risk'!$A$4:$A$33,0)) -> 79 | J8: Confirmed | K8: No. Substrates are program-specific; no independent qualified source (DOC-079). HQ (SITE-901, Z07) is not the plant (DOC-076).
A10: Reconciliation
A11: Z01 facilities in supplier universe | D11: =COUNTIF('Supplier Universe & Risk'!$I$4:$I$33,"Z01") -> 5
A12: Listed on this sheet | D12: =COUNTA(A4:A8) -> 5
A13: Check (should be 0) | D13: =D11-D12 -> 0

Sheet Alternate Supplier Assessment
A1: ALTERNATE SUPPLIER FITMENT ASSESSMENT
A2: One row per component-candidate pair. Public evidence, weighted criterion ratings, evidence confidence, source URL, verification gaps and status are kept together. Candidate is not approved unless separately validated. v2: weighted score and band are now formulas driven by the weights in 'Scoring & Evidence Rules'; rows added for the three CRITICAL upstream nodes (IonPeak dies, Jade substrates, Meridian dielectric film); date and dependency columns added.
A3: Component | B3: Products affected | C3: Current supplier(s) | D3: Candidate | E3: Technical capability (30%) | F3: Application relevance (20%) | G3: Scale / footprint (15%) | H3: Quality / qualification readiness (15%) | I3: Design-in / substitution ease (10%) | J3: Commercial / supply resilience (10%) | K3: Weighted score / 5 | L3: Screening band | M3: Evidence confidence | N3: Evidence-based assessment | O3: Main verification gaps | P3: Public source URL | Q3: Decision status | R3: Public Evidence Summary | S3: Evidence Type | T3: Shortlist Status | U3: Evidence accessed (date) | V3: Node replaced / tier | W3: Addresses shared upstream dependency?
A4: M10 – Standard power assembly | B4: Industrial inverter power assembly; P1 and P3 | C4: Aster Power Assemblies; Boreal Power Systems | D4: Semikron Danfoss | E4: 3 | F4: 3 | G4: 4 | H4: 2 | I4: 2 | J4: 3 | K4: =IF(COUNT(E4:J4)<6,"n/s",E4*'Scoring & Evidence Rules'!$C$10+F4*'Scoring & Evidence Rules'!$C$11+G4*'Scoring & Evidence Rules'!$C$12+H4*'Scoring & Evidence Rules'!$C$13+I4*'Scoring & Evidence Rules'!$C$14+J4*'Scoring & Evidence Rules'!$C$15) -> 2.9 | L4: =IF(NOT(ISNUMBER(K4)),"Not scored - no public evidence",IF(K4>='Scoring & Evidence Rules'!$C$24,"Promising but gaps remain","Partial / uncertain fit")) -> Partial / uncertain fit | M4: Low | N4: Public portfolio supports power-module capability for industrial power electronics, but not a complete integrated M10 assembly. Global footprint is a positive scale signal; exact plant, capacity and qualification status are unverified. | O4: Confirm turnkey assembly capability versus module-only supply; voltage/current/topology; thermal and mechanical interfaces; manufacturing site; capacity; quality certifications; pricing and lead time. | P4: https://www.semikron-danfoss.com/products/power-modules | Q4: Screen only — not approved | R4: Official portfolio describes IGBT, MOSFET, SiC modules for industrial, renewable and e-mobility applications; global production footprint includes India and multiple other regions. | S4: Official manufacturer product page | T4: Initial screen only | U4: Not recorded in original research - re-verify and enter date | V4: Tier-1 direct supplier (Aster / Boreal) | W4: No. A different module assembler does not give independent die supply (DOC-078). Public reporting shows Semikron sources dice from third parties, so a second die route may exist for it; unverified for M10/M20.
A5: M10 – Standard power assembly | B5: Industrial inverter power assembly; P1 and P3 | C5: Aster Power Assemblies; Boreal Power Systems | D5: Vincotech | E5: 3 | F5: 3 | G5: 3 | H5: 2 | I5: 2 | J5: 3 | K5: =IF(COUNT(E5:J5)<6,"n/s",E5*'Scoring & Evidence Rules'!$C$10+F5*'Scoring & Evidence Rules'!$C$11+G5*'Scoring & Evidence Rules'!$C$12+H5*'Scoring & Evidence Rules'!$C$13+I5*'Scoring & Evidence Rules'!$C$14+J5*'Scoring & Evidence Rules'!$C$15) -> 2.75 | L5: =IF(NOT(ISNUMBER(K5)),"Not scored - no public evidence",IF(K5>='Scoring & Evidence Rules'!$C$24,"Promising but gaps remain","Partial / uncertain fit")) -> Partial / uncertain fit | M5: Low | N5: Industrial-drive power modules are application-relevant upstream components, but public evidence does not establish a full M10 assembly replacement. Exact capacity, quality status and commercial terms are unverified. | O5: Confirm full assembly versus module-only scope; voltage/current/topology; thermal interface; manufacturing site and capacity; qualification evidence; price and lead time. | P5: https://www.vincotech.com/applications/industrial-drives | Q5: Screen only — not approved | R5: Official industrial-drives page describes IGBT, SiC MOSFET and rectifier-based power modules for industrial motor drives. | S5: Official manufacturer application page | T5: Initial screen only | U5: Not recorded in original research - re-verify and enter date | V5: Tier-1 direct supplier (Aster / Boreal) | W5: No. Same die-dependency logic as Semikron Danfoss (DOC-078); die sourcing for M10/M20 unverified.
A6: M20 – High-voltage power assembly | B6: High-voltage power conversion for charging; P2 | C6: Aster Power Assemblies; Boreal Power Systems | D6: Semikron Danfoss | E6: 3 | F6: 3 | G6: 4 | H6: 2 | I6: 2 | J6: 3 | K6: =IF(COUNT(E6:J6)<6,"n/s",E6*'Scoring & Evidence Rules'!$C$10+F6*'Scoring & Evidence Rules'!$C$11+G6*'Scoring & Evidence Rules'!$C$12+H6*'Scoring & Evidence Rules'!$C$13+I6*'Scoring & Evidence Rules'!$C$14+J6*'Scoring & Evidence Rules'!$C$15) -> 2.9 | L6: =IF(NOT(ISNUMBER(K6)),"Not scored - no public evidence",IF(K6>='Scoring & Evidence Rules'!$C$24,"Promising but gaps remain","Partial / uncertain fit")) -> Partial / uncertain fit | M6: Low | N6: Power-module portfolio is relevant to high-voltage power conversion, but exact M20 voltage/current class and complete assembly scope are not demonstrated by the shortlist evidence. | O6: Confirm M20 voltage/current class, topology, insulation/clearance requirements, thermal design, complete assembly integration, plant capacity, quality certifications and qualification timeline. | P6: https://www.semikron-danfoss.com/products/power-modules | Q6: Screen only — not approved | R6: Official module catalogue covers different current ratings, voltage classes, IGBT and SiC technologies. | S6: Official manufacturer product page | T6: Initial screen only | U6: Not recorded in original research - re-verify and enter date | V6: Tier-1 direct supplier (Aster / Boreal) | W6: No. A different module assembler does not give independent die supply (DOC-078). Public reporting shows Semikron sources dice from third parties, so a second die route may exist for it; unverified for M10/M20.
A7: M20 – High-voltage power assembly | B7: High-voltage power conversion for charging; P2 | C7: Aster Power Assemblies; Boreal Power Systems | D7: Vincotech | E7: 3 | F7: 3 | G7: 3 | H7: 2 | I7: 2 | J7: 3 | K7: =IF(COUNT(E7:J7)<6,"n/s",E7*'Scoring & Evidence Rules'!$C$10+F7*'Scoring & Evidence Rules'!$C$11+G7*'Scoring & Evidence Rules'!$C$12+H7*'Scoring & Evidence Rules'!$C$13+I7*'Scoring & Evidence Rules'!$C$14+J7*'Scoring & Evidence Rules'!$C$15) -> 2.75 | L7: =IF(NOT(ISNUMBER(K7)),"Not scored - no public evidence",IF(K7>='Scoring & Evidence Rules'!$C$24,"Promising but gaps remain","Partial / uncertain fit")) -> Partial / uncertain fit | M7: Low | N7: Industrial-drive module capability is adjacent to the application, but exact high-voltage fit and turnkey assembly capability are unverified. | O7: Confirm voltage/current class, topology, insulation, thermal interface, assembly scope, manufacturing site, capacity, qualification and commercial terms. | P7: https://www.vincotech.com/ | Q7: Screen only — not approved | R7: Official product information describes SiC/IGBT modules and scalable charger-related power conversion applications. | S7: Official manufacturer website | T7: Initial screen only | U7: Not recorded in original research - re-verify and enter date | V7: Tier-1 direct supplier (Aster / Boreal) | W7: No. Same die-dependency logic as Semikron Danfoss (DOC-078); die sourcing for M10/M20 unverified.
A8: C10 – Control board | B8: Industrial control PCB/PCBA with embedded microcontroller; P1, P2, P3 | C8: Cobalt Control Electronics | D8: Jabil | E8: 4 | F8: 3 | G8: 5 | H8: 3 | I8: 3 | J8: 3 | K8: =IF(COUNT(E8:J8)<6,"n/s",E8*'Scoring & Evidence Rules'!$C$10+F8*'Scoring & Evidence Rules'!$C$11+G8*'Scoring & Evidence Rules'!$C$12+H8*'Scoring & Evidence Rules'!$C$13+I8*'Scoring & Evidence Rules'!$C$14+J8*'Scoring & Evidence Rules'!$C$15) -> 3.6 | L8: =IF(NOT(ISNUMBER(K8)),"Not scored - no public evidence",IF(K8>='Scoring & Evidence Rules'!$C$24,"Promising but gaps remain","Partial / uncertain fit")) -> Promising but gaps remain | M8: Medium-Low | N8: Public electronics manufacturing capability supports complex PCBA at scale. Specific industrial inverter control-board design, embedded firmware, functional-safety and test compatibility are not established by the shortlist evidence. | O8: Confirm design ownership/DFM support, controller ecosystem, firmware and functional-safety capability, functional test coverage, plant/site, certifications, available capacity, IP protections and commercial terms. | P8: https://www.jabil.com/capability/electronics.html | Q8: Screen only — not approved | R8: Official electronics capability page lists PCBA, engineering services, test development, high-current and high-density board technologies, and box-build integration. | S8: Official manufacturer capability page | T8: Initial screen only | U8: Not recorded in original research - re-verify and enter date | V8: Tier-1 direct supplier (Cobalt) | W8: Only if the alternate board source also avoids Jade substrates; not evidenced. Substrate is program-specific (DOC-079).
A9: C10 – Control board | B9: Industrial control PCB/PCBA with embedded microcontroller; P1, P2, P3 | C9: Cobalt Control Electronics | D9: Sanmina | E9: 4 | F9: 3 | G9: 4 | H9: 3 | I9: 3 | J9: 3 | K9: =IF(COUNT(E9:J9)<6,"n/s",E9*'Scoring & Evidence Rules'!$C$10+F9*'Scoring & Evidence Rules'!$C$11+G9*'Scoring & Evidence Rules'!$C$12+H9*'Scoring & Evidence Rules'!$C$13+I9*'Scoring & Evidence Rules'!$C$14+J9*'Scoring & Evidence Rules'!$C$15) -> 3.45 | L9: =IF(NOT(ISNUMBER(K9)),"Not scored - no public evidence",IF(K9>='Scoring & Evidence Rules'!$C$24,"Promising but gaps remain","Partial / uncertain fit")) -> Promising but gaps remain | M9: Medium-Low | N9: Public PCB assembly capability is directly relevant to board manufacturing, but NovaDrive-specific control functionality and qualification readiness are not established. | O9: Confirm board complexity, embedded-control support, functional safety, test fixtures, exact plant, certifications, capacity, component sourcing, IP controls and lead time. | P9: https://www.sanmina.com/contract-manufacturing-design/pcb-assembly-smt/ | Q9: Screen only — not approved | R9: Official page describes PCB assembly, SMT, prototype to high-volume manufacturing, inspection, electrical testing and test-system development. | S9: Official manufacturer capability page | T9: Initial screen only | U9: Not recorded in original research - re-verify and enter date | V9: Tier-1 direct supplier (Cobalt) | W9: Only if the alternate board source also avoids Jade substrates; not evidenced. Substrate is program-specific (DOC-079).
A10: C20 – DC-link capacitor | B10: High-energy DC-link film capacitor; P1 and P2 | C10: Delta Capacitor Works | D10: TDK / EPCOS | E10: 4 | F10: 4 | G10: 5 | H10: 4 | I10: 3 | J10: 3 | K10: =IF(COUNT(E10:J10)<6,"n/s",E10*'Scoring & Evidence Rules'!$C$10+F10*'Scoring & Evidence Rules'!$C$11+G10*'Scoring & Evidence Rules'!$C$12+H10*'Scoring & Evidence Rules'!$C$13+I10*'Scoring & Evidence Rules'!$C$14+J10*'Scoring & Evidence Rules'!$C$15) -> 3.95 | L10: =IF(NOT(ISNUMBER(K10)),"Not scored - no public evidence",IF(K10>='Scoring & Evidence Rules'!$C$24,"Promising but gaps remain","Partial / uncertain fit")) -> Promising but gaps remain | M10: Medium | N10: Public DC-link film capacitor product family is a direct component-category match. Exact electrical ratings, mechanical fit, lifetime and approved status for NovaDrive remain unverified. | O10: Match capacitance, voltage, ripple current, ESR/ESL, lifetime, temperature, dimensions, terminals, safety approvals and plant availability; complete engineering qualification and commercial review. | P10: https://product.tdk.com/en/products/capacitor/film/dc-link/index.html | Q10: Screen only — not approved | R10: Official portfolio provides DC-link film capacitors with voltage/capacitance ranges and application information for industrial frequency drives and power conversion. | S10: Official manufacturer product page | T10: Initial screen only | U10: Not recorded in original research - re-verify and enter date | V10: Tier-1 direct supplier (Delta Capacitor Works) | W10: Tier-1 swap only; the Tier-2 / Tier-3 dependency behind this component is unchanged and unassessed for this candidate.
A11: C20 – DC-link capacitor | B11: High-energy DC-link film capacitor; P1 and P2 | C11: Delta Capacitor Works | D11: Vishay | E11: 4 | F11: 4 | G11: 5 | H11: 4 | I11: 3 | J11: 3 | K11: =IF(COUNT(E11:J11)<6,"n/s",E11*'Scoring & Evidence Rules'!$C$10+F11*'Scoring & Evidence Rules'!$C$11+G11*'Scoring & Evidence Rules'!$C$12+H11*'Scoring & Evidence Rules'!$C$13+I11*'Scoring & Evidence Rules'!$C$14+J11*'Scoring & Evidence Rules'!$C$15) -> 3.95 | L11: =IF(NOT(ISNUMBER(K11)),"Not scored - no public evidence",IF(K11>='Scoring & Evidence Rules'!$C$24,"Promising but gaps remain","Partial / uncertain fit")) -> Promising but gaps remain | M11: Medium | N11: Public DC-link capacitor product family is a direct category match. Exact part-level equivalence and qualification for NovaDrive are not established. | O11: Match electrical ratings, ripple current, ESR/ESL, lifetime, temperature, dimensions, terminals, certifications, manufacturing location, capacity, price and lead time. | P11: https://www.vishay.com/en/capacitors/film/dc-link/ | Q11: Screen only — not approved | R11: Official catalogue lists DC-link film capacitor families, including industrial-grade products with stated voltage and capacitance ranges. | S11: Official manufacturer product page | T11: Initial screen only | U11: Not recorded in original research - re-verify and enter date | V11: Tier-1 direct supplier (Delta Capacitor Works) | W11: Tier-1 swap only; the Tier-2 / Tier-3 dependency behind this component is unchanged and unassessed for this candidate.
A12: H10 – Protective housing | B12: Machined/fabricated aluminum electronics enclosure; P1 | C12: ForgeLine Enclosures | D12: nVent HOFFMAN | E12: 4 | F12: 4 | G12: 4 | H12: 3 | I12: 3 | J12: 3 | K12: =IF(COUNT(E12:J12)<6,"n/s",E12*'Scoring & Evidence Rules'!$C$10+F12*'Scoring & Evidence Rules'!$C$11+G12*'Scoring & Evidence Rules'!$C$12+H12*'Scoring & Evidence Rules'!$C$13+I12*'Scoring & Evidence Rules'!$C$14+J12*'Scoring & Evidence Rules'!$C$15) -> 3.65 | L12: =IF(NOT(ISNUMBER(K12)),"Not scored - no public evidence",IF(K12>='Scoring & Evidence Rules'!$C$24,"Promising but gaps remain","Partial / uncertain fit")) -> Promising but gaps remain | M12: Medium-Low | N12: Industrial enclosure portfolio is relevant to protective housing needs, but the exact custom geometry, thermal, ingress-protection and EMI requirements are not evidenced as matched. | O12: Confirm material and dimensions, mounting, ingress/IP rating, EMI shielding, corrosion, thermal requirements, tolerances, customization, manufacturing site, test/quality documentation and lead time. | P12: https://www.nvent.com/en-in/hoffman | Q12: Screen only — not approved | R12: Official site describes industrial enclosure customization, special dimensions, machining, holes/cutouts and serial production capability. | S12: Official manufacturer website | T12: Initial screen only | U12: Not recorded in original research - re-verify and enter date | V12: Tier-1 direct supplier (ForgeLine) | W12: Tier-1 swap only; the Tier-2 / Tier-3 dependency behind this component is unchanged and unassessed for this candidate.
A13: H10 – Protective housing | B13: Machined/fabricated aluminum electronics enclosure; P1 | C13: ForgeLine Enclosures | D13: Hammond Manufacturing | E13: 4 | F13: 4 | G13: 3 | H13: 3 | I13: 3 | J13: 3 | K13: =IF(COUNT(E13:J13)<6,"n/s",E13*'Scoring & Evidence Rules'!$C$10+F13*'Scoring & Evidence Rules'!$C$11+G13*'Scoring & Evidence Rules'!$C$12+H13*'Scoring & Evidence Rules'!$C$13+I13*'Scoring & Evidence Rules'!$C$14+J13*'Scoring & Evidence Rules'!$C$15) -> 3.5 | L13: =IF(NOT(ISNUMBER(K13)),"Not scored - no public evidence",IF(K13>='Scoring & Evidence Rules'!$C$24,"Promising but gaps remain","Partial / uncertain fit")) -> Promising but gaps remain | M13: Medium-Low | N13: Aluminum enclosure products provide a relevant product-family match; exact custom housing fit, production scale and NovaDrive qualification are unverified. | O13: Confirm alloy, geometry, machining/customization, IP/EMI requirements, thermal performance, tolerances, finish, production capacity, certifications, price and lead time. | P13: https://www.hammfg.com/electrical/products/aluminum | Q13: Screen only — not approved | R13: Official catalogue includes aluminum enclosures and factory modification services; broad standard enclosure portfolio. | S13: Official manufacturer product page | T13: Initial screen only | U13: Not recorded in original research - re-verify and enter date | V13: Tier-1 direct supplier (ForgeLine) | W13: Tier-1 swap only; the Tier-2 / Tier-3 dependency behind this component is unchanged and unassessed for this candidate.
A14: H20 – Cooling assembly | B14: Thermal-management / liquid-cooling assembly; P2 and P3 | C14: Estuary Thermal Systems | D14: Boyd | E14: 4 | F14: 4 | G14: 4 | H14: 3 | I14: 3 | J14: 3 | K14: =IF(COUNT(E14:J14)<6,"n/s",E14*'Scoring & Evidence Rules'!$C$10+F14*'Scoring & Evidence Rules'!$C$11+G14*'Scoring & Evidence Rules'!$C$12+H14*'Scoring & Evidence Rules'!$C$13+I14*'Scoring & Evidence Rules'!$C$14+J14*'Scoring & Evidence Rules'!$C$15) -> 3.65 | L14: =IF(NOT(ISNUMBER(K14)),"Not scored - no public evidence",IF(K14>='Scoring & Evidence Rules'!$C$24,"Promising but gaps remain","Partial / uncertain fit")) -> Promising but gaps remain | M14: Medium-Low | N14: Public liquid-cooling systems capability is relevant to thermal management, but the exact H20 assembly configuration and its operating envelope are not proven to match. | O14: Validate heat load, coolant, flow/pressure, pressure drop, leakage, materials compatibility, interfaces, vibration/corrosion, test regime, manufacturing site, scale, qualification and serviceability. | P14: https://www.boydcorp.com/thermal/liquid-cooling-systems.html | Q14: Screen only — not approved | R14: Official sources describe liquid cooling systems, custom cold plates, liquid loops, and thermal/flow/leak testing. | S14: Official manufacturer product page | T14: Initial screen only | U14: Not recorded in original research - re-verify and enter date | V14: Tier-1 direct supplier (Estuary) | W14: Tier-1 swap only; the Tier-2 / Tier-3 dependency behind this component is unchanged and unassessed for this candidate.
A15: H20 – Cooling assembly | B15: Thermal-management / liquid-cooling assembly; P2 and P3 | C15: Estuary Thermal Systems | D15: Modine | E15: 4 | F15: 4 | G15: 4 | H15: 3 | I15: 3 | J15: 3 | K15: =IF(COUNT(E15:J15)<6,"n/s",E15*'Scoring & Evidence Rules'!$C$10+F15*'Scoring & Evidence Rules'!$C$11+G15*'Scoring & Evidence Rules'!$C$12+H15*'Scoring & Evidence Rules'!$C$13+I15*'Scoring & Evidence Rules'!$C$14+J15*'Scoring & Evidence Rules'!$C$15) -> 3.65 | L15: =IF(NOT(ISNUMBER(K15)),"Not scored - no public evidence",IF(K15>='Scoring & Evidence Rules'!$C$24,"Promising but gaps remain","Partial / uncertain fit")) -> Promising but gaps remain | M15: Medium-Low | N15: Electronics-cooling capability is application-relevant, but the exact H20 assembly design, interface and operating envelope are unverified. | O15: Confirm thermal load, coolant, flow/pressure, pressure drop, dimensions, interfaces, leak testing, materials, site capacity, qualification documentation, price and lead time. | P15: https://www.modine.com/news/how-it-works-electronics-cooling-package/ | Q15: Screen only — not approved | R15: Official article describes electronics cooling packages for inverter, converter and onboard-charger thermal management, with heat exchanger, fans, harnesses and control options. | S15: Official manufacturer technical article | T15: Initial screen only | U15: Not recorded in original research - re-verify and enter date | V15: Tier-1 direct supplier (Estuary) | W15: Tier-1 swap only; the Tier-2 / Tier-3 dependency behind this component is unchanged and unassessed for this candidate.
... A20: M10 / M20 upstream - Power semiconductor dies (IonPeak node) | B20: P1, P2, P3 (via M10 and M20) | C20: IonPeak Semiconductor, SITE-074 (sole qualified die source, DOC-078) | D20: onsemi | E20: 3 | F20: 4 | G20: 4 | H20: 3 | I20: 2 | J20: 3 | K20: =IF(COUNT(E20:J20)<6,"n/s",E20*'Scoring & Evidence Rules'!$C$10+F20*'Scoring & Evidence Rules'!$C$11+G20*'Scoring & Evidence Rules'!$C$12+H20*'Scoring & Evidence Rules'!$C$13+I20*'Scoring & Evidence Rules'!$C$14+J20*'Scoring & Evidence Rules'!$C$15) -> 3.25 | L20: =IF(NOT(ISNUMBER(K20)),"Not scored - no public evidence",IF(K20>='Scoring & Evidence Rules'!$C$24,"Promising but gaps remain","Partial / uncertain fit")) -> Promising but gaps remain | M20: Medium-Low | N20: Public catalogue lists EliteSiC MOSFET bare dies (1200 V class entries shown as product preview) for traction, DC-DC and off-board chargers, and describes a vertically integrated SiC supply chain. Silicon IGBT die availability and industrial-drive fit not shown in the evidence retrieved. | O20: Product-preview status of listed 1200 V dice; IGBT versus SiC die match to M10/M20; plant and capacity; module requalification; whether the vertically integrated chain gives geographic diversification away from Z01. | P20: https://onsemi.com/products/discrete-power-modules/silicon-carbide-sic/silicon-carbide-sic-mosfets-bare-die | Q20: Screen only — not approved | R20: Official parametric catalogue shows EliteSiC M3e 1200 V bare-die parts (product preview) and a page describing integrated SiC supply for chargers and industrial power. Accessed 2026-10-04. | S20: Official manufacturer product catalogue | T20: Initial screen only | U20: 2026-10-04 | V20: Tier-2 node: IonPeak Semiconductor (power dies) - CRITICAL 79 | W20: Yes in principle - same caveats as above.
A21: M10 / M20 upstream - Power semiconductor dies (IonPeak node) | B21: P1, P2, P3 (via M10 and M20) | C21: IonPeak Semiconductor, SITE-074 (sole qualified die source, DOC-078) | D21: PolarSwitch (case-referenced prospective alternative) | K21: =IF(COUNT(E21:J21)<6,"n/s",E21*'Scoring & Evidence Rules'!$C$10+F21*'Scoring & Evidence Rules'!$C$11+G21*'Scoring & Evidence Rules'!$C$12+H21*'Scoring & Evidence Rules'!$C$13+I21*'Scoring & Evidence Rules'!$C$14+J21*'Scoring & Evidence Rules'!$C$15) -> n/s | L21: =IF(NOT(ISNUMBER(K21)),"Not scored - no public evidence",IF(K21>='Scoring & Evidence Rules'!$C$24,"Promising but gaps remain","Partial / uncertain fit")) -> Not scored - no public evidence | M21: Not assessed | N21: Named in the case evidence (DOC-078) as a prospective alternative only. A public search on 2026-10-04 returned no manufacturer of this name, so no public evidence exists to score. Retained as a lead, not a shortlisted candidate. | O21: Obtain the source behind the DOC-078 reference; confirm legal entity, capability and qualification status before any scoring. | P21: No public source found | Q21: Screen only — not approved | R21: No public evidence retrieved on 2026-10-04; case reference only (DOC-078). | S21: Case evidence only (no public source) | T21: Initial screen only | U21: 2026-10-04 | V21: Tier-2 node: IonPeak Semiconductor (power dies) - CRITICAL 79 | W21: Unknown - cannot be assessed without evidence.
A22: C10 / B10 upstream - Printed circuit substrates (Jade node) | B22: P1, P2, P3 (via C10 and B10) | C22: Jade Printed Circuits, SITE-081 (no qualified independent substrate, DOC-079) | D22: TTM Technologies | E22: 3 | F22: 3 | G22: 5 | H22: 3 | I22: 2 | J22: 3 | K22: =IF(COUNT(E22:J22)<6,"n/s",E22*'Scoring & Evidence Rules'!$C$10+F22*'Scoring & Evidence Rules'!$C$11+G22*'Scoring & Evidence Rules'!$C$12+H22*'Scoring & Evidence Rules'!$C$13+I22*'Scoring & Evidence Rules'!$C$14+J22*'Scoring & Evidence Rules'!$C$15) -> 3.2 | L22: =IF(NOT(ISNUMBER(K22)),"Not scored - no public evidence",IF(K22>='Scoring & Evidence Rules'!$C$24,"Promising but gaps remain","Partial / uncertain fit")) -> Partial / uncertain fit | M22: Medium-Low | N22: Official capability page describes volume PCB fabrication across a global plant footprint with design-for-manufacture and high-reliability support for industrial customers; a third-party directory lists heavy copper and thermal-management boards. Fit to the Jade program-specific substrate is unproven. | O22: Substrate specification and materials; whether the Jade substrate is program-specific tooling; qualification and first-article time against the 12-week C10/B10 lead time; plant location outside Z01; capacity and pricing. | P22: https://www.ttm.com/en/markets-we-serve/industrial-and-instrumentation/capabilities | Q22: Screen only — not approved | R22: Official industrial and instrumentation capability page (undated) describes PCB fabrication for medium and high volume with global facilities; accessed 2026-10-04. | S22: Official manufacturer capability page | T22: Initial screen only | U22: 2026-10-04 | V22: Tier-2 node: Jade Printed Circuits (substrates) - CRITICAL 79 | W22: Yes in principle - removes the single Z01 substrate source shared by C10 and both B10 suppliers, if qualified at Cobalt, Grove and HarborSense.
A23: C10 / B10 upstream - Printed circuit substrates (Jade node) | B23: P1, P2, P3 (via C10 and B10) | C23: Jade Printed Circuits, SITE-081 (no qualified independent substrate, DOC-079) | D23: Wurth Elektronik | E23: 3 | F23: 3 | G23: 3 | H23: 2 | I23: 2 | J23: 3 | K23: =IF(COUNT(E23:J23)<6,"n/s",E23*'Scoring & Evidence Rules'!$C$10+F23*'Scoring & Evidence Rules'!$C$11+G23*'Scoring & Evidence Rules'!$C$12+H23*'Scoring & Evidence Rules'!$C$13+I23*'Scoring & Evidence Rules'!$C$14+J23*'Scoring & Evidence Rules'!$C$15) -> 2.75 | L23: =IF(NOT(ISNUMBER(K23)),"Not scored - no public evidence",IF(K23>='Scoring & Evidence Rules'!$C$24,"Promising but gaps remain","Partial / uncertain fit")) -> Partial / uncertain fit | M23: Low | N23: Company site describes manufacture of printed circuit boards for customer-specific requirements and intelligent power and control systems for demanding conditions. Evidence is a general corporate page; no volume, plant or power-electronics board detail was retrieved. | O23: Plant locations and capacity; heavy-copper or power-board capability; quality certifications; qualification time; commercial terms. Treat as a weak lead until a product-level page is found. | P23: https://www.we-online.com/en/index | Q23: Screen only — not approved | R23: Official corporate homepage describes PCBs, components and power and control systems; no product-level substrate evidence; accessed 2026-10-04. | S23: Official corporate website (general) | T23: Initial screen only | U23: 2026-10-04 | V23: Tier-2 node: Jade Printed Circuits (substrates) - CRITICAL 79 | W23: Possibly - same caveats; weaker evidence than TTM.
A24: C20 upstream - Dielectric film (Meridian node) | B24: P1, P2 (via C20) | C24: Meridian Dielectrics, SITE-102 (financial stress, EV-003) | D24: Toray Industries (TORAYFAN BOPP film) | E24: 4 | F24: 4 | G24: 5 | H24: 3 | I24: 3 | J24: 3 | K24: =IF(COUNT(E24:J24)<6,"n/s",E24*'Scoring & Evidence Rules'!$C$10+F24*'Scoring & Evidence Rules'!$C$11+G24*'Scoring & Evidence Rules'!$C$12+H24*'Scoring & Evidence Rules'!$C$13+I24*'Scoring & Evidence Rules'!$C$14+J24*'Scoring & Evidence Rules'!$C$15) -> 3.8 | L24: =IF(NOT(ISNUMBER(K24)),"Not scored - no public evidence",IF(K24>='Scoring & Evidence Rules'!$C$24,"Promising but gaps remain","Partial / uncertain fit")) -> Promising but gaps remain | M24: Medium | N24: Official page describes biaxially oriented polypropylene film made at industrial scale and used for capacitor applications; a market report names Toray among leading capacitor-grade BOPP producers. BOPP is the standard dielectric for power film capacitors, so this is a direct material-category match. | O24: Film grade, thickness and metallization needed by Delta; whether Meridian supplies base film or metallized film; Delta qualification and capacitor re-test against the 8-week C20 lead time; allocation and pricing; manufacturing region. | P24: https://www.films.toray/en/products/torayfan/ | Q24: Screen only — not approved | R24: Official TORAYFAN page lists capacitor among its applications; a separate application guide states polypropylene is the dielectric most often used for power-electronics DC-link capacitors. Accessed 2026-10-04. | S24: Official manufacturer product page plus industry application guide | T24: Initial screen only | U24: 2026-10-04 | V24: Tier-2 node: Meridian Dielectrics (dielectric film) - CRITICAL 83.7 | W24: Yes in principle - a second film source reduces dependence on a financially stressed single node, subject to Delta qualification.
A25: C20 upstream - Dielectric film (Meridian node) | B25: P1, P2 (via C20) | C25: Meridian Dielectrics, SITE-102 (financial stress, EV-003) | D25: Steiner (Steinerfilm P metallized BOPP) | E25: 4 | F25: 4 | G25: 3 | H25: 3 | I25: 3 | J25: 3 | K25: =IF(COUNT(E25:J25)<6,"n/s",E25*'Scoring & Evidence Rules'!$C$10+F25*'Scoring & Evidence Rules'!$C$11+G25*'Scoring & Evidence Rules'!$C$12+H25*'Scoring & Evidence Rules'!$C$13+I25*'Scoring & Evidence Rules'!$C$14+J25*'Scoring & Evidence Rules'!$C$15) -> 3.5 | L25: =IF(NOT(ISNUMBER(K25)),"Not scored - no public evidence",IF(K25>='Scoring & Evidence Rules'!$C$24,"Promising but gaps remain","Partial / uncertain fit")) -> Promising but gaps remain | M25: Medium | N25: Official page describes metallized BOPP film offered in custom metallizing patterns and slit widths for capacitors, including DC-link applications with high DC voltage and high-frequency ripple. Category match is strong; scale versus the largest producers is not shown. | O25: Capacity and lead time; film grade versus Delta spec; Delta qualification; plant location; financial and continuity review. | P25: https://www.steinerfilm.com/p-bopp | Q25: Screen only — not approved | R25: Official product page for metallized BOPP film aimed at customized capacitors and DC-link use; accessed 2026-10-04. | S25: Official manufacturer product page | T25: Initial screen only | U25: 2026-10-04 | V25: Tier-2 node: Meridian Dielectrics (dielectric film) - CRITICAL 83.7 | W25: Yes in principle - same caveats as above.

Sheet Scoring & Evidence Rules
A1: SCORING METHODOLOGY + EVIDENCE RULES
A2: Compact reference for the dashboard builder. The individual risk and fitment values remain in their respective assessment sheets.
A3: Assessment | B3: Field / Criterion | C3: Weight / Threshold | D3: Definition / Interpretation | E3: Caveat / Evidence Required
A4: Supplier risk | B4: CRITICAL | C4: >=75 | D4: Highest supplier-risk band. | E4: Risk score is a screening indicator; inspect underlying financial, operational, geographic and other indicators.
A5: Supplier risk | B5: HIGH | C5: >=60 and <75 | D5: Elevated supplier risk. | E5: Not a disruption probability.
A6: Supplier risk | B6: MEDIUM | C6: >=45 and <60 | D6: Moderate supplier risk. | E6: Consider criticality, shared dependencies and event context.
A7: Supplier risk | B7: LOW | C7: <45 | D7: Lower relative supplier risk in this scorecard. | E7: Low score does not imply no risk.
A8: Supplier risk | B8: Data completeness / relationship confidence | C8: Separate fields | D8: Completeness/confidence describes evidence quality, not supplier risk level. | E8: Keep confidence separate from risk.
A9: Component risk | B9: Component network risk formula | C9: T1 35%; highest T2 25%; highest T3 15%; concentration 15%; event exposure 10% | D9: Weighted average of available indicators; missing Tier-3 score weight is redistributed proportionally across available indicators. | E9: Transparent screening score, not statistically validated loss probability.
A10: Alternate fitment | B10: Technical capability match | C10: 0.3 | D10: Can candidate make the same component type and meet electrical, thermal, mechanical or board requirements? | E10: Datasheets, drawings, process capability, engineering review and test results.
A11: Alternate fitment | B11: Application relevance | C11: 0.2 | D11: Experience with industrial drives, charging power conversion, energy storage electronics, enclosure or cooling application. | E11: Public application/product pages and relevant references.
A12: Alternate fitment | B12: Manufacturing scale / footprint | C12: 0.15 | D12: Ability to support required volume and workable manufacturing/shipping footprint. | E12: Footprint is a proxy only; confirm actual plant, capacity, line time and route.
A13: Alternate fitment | B13: Quality / qualification readiness | C13: 0.15 | D13: Quality systems, traceability, reliability testing and relevant approvals. | E13: Certificates, audit, process documentation and qualification evidence.
A14: Alternate fitment | B14: Design-in / substitution ease | C14: 0.1 | D14: Expected engineering change, tooling, firmware, interface or validation effort. | E14: Exact interchangeability is not proven; design comparison and testing required.
A15: Alternate fitment | B15: Commercial / supply resilience | C15: 0.1 | D15: Plausible capacity, lead time, continuity, pricing and dependency diversification. | E15: RFQ, capacity reservation, financial/continuity review and alternate-site options.
A16: Alternate fitment | B16: Rating scale | C16: 1 to 5 | D16: 1 = weak/no evidence; 3 = plausible but important unknowns; 5 = strong documented fit. | E16: Do not award high scores based only on generic marketing claims.
A17: Network evidence | B17: Allocation values | C17: Planning / contracted | D17: Allocations are planning/contracted signals from evidence. | E17: Not purchase ledger data or guarantee of realized deliveries.
A18: Event handling | B18: Duplicate control | C18: EV-001 / EV-002 | D18: Same source family and same flood-watch bulletin. | E18: Count as one signal, not two independent events.
A19: Event handling | B19: Entity mismatch control | C19: EV-004 / EV-009 | D19: Ion Peak Trading is not IonPeak Semiconductor; Delta Consumer Plastics is not Delta Capacitor Works. | E19: Do not create supplier alerts based on name similarity alone.
A20: Event handling | B20: Stale / administrative / conditional events | C20: EV-005 / EV-007 / EV-010 | D20: EV-005 is historical; EV-007 is HQ relocation with production continuing at East Delta; EV-010 route exposure to Estuary is unconfirmed. | E20: Do not infer current disruption without current, entity/site-specific evidence.
A21: Supplier risk | B21: Supplier-level score build | C21: Financial 30% / Operational 25% / Location 30% / Assurance 15% | D21: See 'Supplier Score Build'. Intrinsic score from eight raw indicators with editable weights; missing pillars default to 60 and are flagged, never treated as low risk. | E21: The original headline supplier weights are undocumented in the source files. The build is a cross-check; the headline score is unchanged.
A22: Component risk | B22: Revenue criticality | C22: Revenue dependent = sum of revenue of products using the component | D22: Risk-weighted revenue index = network risk score / 100 x revenue dependent (Component Risk cols V-Y; Node Criticality). | E22: Prioritisation aid only. No supplier spend or purchase data is provided, so it is not an expected-loss figure.
A23: Network evidence | B23: Common control | C23: Aster and Boreal share owner CommonSpan (DOC-075) | D23: M10 / M20 Tier-1 split is treated as one ownership group for concentration and escalation. | E23: Ownership evidence only; the concentration score in Component Risk is left as originally set (80) and should be reviewed.
A24: Alternate fitment | B24: Screening band threshold | C24: 3.25 | D24: Weighted score >= threshold = 'Promising but gaps remain'; below = 'Partial / uncertain fit'. If fewer than six criterion ratings exist the candidate is 'Not scored'. | E24: Threshold inferred from the bands already used in this sheet (2.75-2.90 partial; 3.35-3.95 promising). Analyst judgement, not a case-provided cut-off.
A25: Event handling | B25: Facility-level matching | C25: EV-001 matched to every facility in zone Z01 | D25: Five mapped Z01 facilities: IonPeak, Orion, Jade, Umber, Verdant (inferred). See 'Z01 Flood Exposure'. | E25: Geographic match only; no damage or shutdown confirmed. Matching uses facility zone, not company name.
A26: Alternate fitment | B26: Upstream-node candidates | C26: Candidates for IonPeak dies, Jade substrates, Meridian film | D26: Added for the three CRITICAL upstream nodes and scored with the same six-criterion framework. | E26: Tier-2 replacements are normally qualified through the Tier-1 supplier; NovaDrive would need to influence Tier-1 sourcing and qualification.
